{
  "name": "谍中谍之惊雷波尔多",
  "author": "sunyi",
  "url": "http://sunyi.zgpingshu.com/5177/",
  "chapters": [
    {
      "name": "1回 - 谍中谍之惊雷波尔多",
      "url": "http://www.zgpingshu.com/play/5177/",
      "downloadUrl": "http://ops81.zgpingshu.com/%E5%AD%99%E4%B8%80/%E8%B0%8D%E4%B8%AD%E8%B0%8D%E4%B9%8B%E6%83%8A%E9%9B%B7%E6%B3%A2%E5%B0%94%E5%A4%9A%285%E5%9B%9E%29%28%E6%BC%94%E6%92%AD-%E5%AD%99%E4%B8%80%29%2832kb%29/14B9A0D661.mp3"
    },
    {
      "name": "2回 - 谍中谍之惊雷波尔多",
      "url": "http://www.zgpingshu.com/play/5177/2.html",
      "downloadUrl": "http://ops81.zgpingshu.com/%E5%AD%99%E4%B8%80/%E8%B0%8D%E4%B8%AD%E8%B0%8D%E4%B9%8B%E6%83%8A%E9%9B%B7%E6%B3%A2%E5%B0%94%E5%A4%9A%285%E5%9B%9E%29%28%E6%BC%94%E6%92%AD-%E5%AD%99%E4%B8%80%29%2832kb%29/8D0978A2D8.mp3"
    },
    {
      "name": "3回 - 谍中谍之惊雷波尔多",
      "url": "http://www.zgpingshu.com/play/5177/3.html",
      "downloadUrl": "http://ops81.zgpingshu.com/%E5%AD%99%E4%B8%80/%E8%B0%8D%E4%B8%AD%E8%B0%8D%E4%B9%8B%E6%83%8A%E9%9B%B7%E6%B3%A2%E5%B0%94%E5%A4%9A%285%E5%9B%9E%29%28%E6%BC%94%E6%92%AD-%E5%AD%99%E4%B8%80%29%2832kb%29/288593383E.mp3"
    },
    {
      "name": "4回 - 谍中谍之惊雷波尔多",
      "url": "http://www.zgpingshu.com/play/5177/4.html",
      "downloadUrl": "http://ops81.zgpingshu.com/%E5%AD%99%E4%B8%80/%E8%B0%8D%E4%B8%AD%E8%B0%8D%E4%B9%8B%E6%83%8A%E9%9B%B7%E6%B3%A2%E5%B0%94%E5%A4%9A%285%E5%9B%9E%29%28%E6%BC%94%E6%92%AD-%E5%AD%99%E4%B8%80%29%2832kb%29/89929C5BD7.mp3"
    },
    {
      "name": "5回 - 谍中谍之惊雷波尔多",
      "url": "http://www.zgpingshu.com/play/5177/5.html",
      "downloadUrl": "http://ops81.zgpingshu.com/%E5%AD%99%E4%B8%80/%E8%B0%8D%E4%B8%AD%E8%B0%8D%E4%B9%8B%E6%83%8A%E9%9B%B7%E6%B3%A2%E5%B0%94%E5%A4%9A%285%E5%9B%9E%29%28%E6%BC%94%E6%92%AD-%E5%AD%99%E4%B8%80%29%2832kb%29/C6BEC38287.mp3"
    }
  ]
}
