{
  "name": "风云人物蒋介石",
  "author": "tianzhanyi",
  "url": "http://tianzhanyi.zgpingshu.com/4123/",
  "chapters": [
    {
      "name": "001回 - 风云人物蒋介石",
      "url": "http://www.zgpingshu.com/play/4123/",
      "downloadUrl": "http://ops101.zgpingshu.com/%E7%94%B0%E6%88%98%E4%B9%89/%E9%A3%8E%E4%BA%91%E4%BA%BA%E7%89%A9%E8%92%8B%E4%BB%8B%E7%9F%B3%28162%E5%9B%9E%2932kbps/6CC68D36AC.mp3"
    },
    {
      "name": "002回 - 风云人物蒋介石",
      "url": "http://www.zgpingshu.com/play/4123/2.html",
      "downloadUrl": "http://ops101.zgpingshu.com/%E7%94%B0%E6%88%98%E4%B9%89/%E9%A3%8E%E4%BA%91%E4%BA%BA%E7%89%A9%E8%92%8B%E4%BB%8B%E7%9F%B3%28162%E5%9B%9E%2932kbps/35C859A909.mp3"
    },
    {
      "name": "003回 - 风云人物蒋介石",
      "url": "http://www.zgpingshu.com/play/4123/3.html",
      "downloadUrl": "http://ops101.zgpingshu.com/%E7%94%B0%E6%88%98%E4%B9%89/%E9%A3%8E%E4%BA%91%E4%BA%BA%E7%89%A9%E8%92%8B%E4%BB%8B%E7%9F%B3%28162%E5%9B%9E%2932kbps/5ADCEEC45B.mp3"
    },
    {
      "name": "004回 - 风云人物蒋介石",
      "url": "http://www.zgpingshu.com/play/4123/4.html",
      "downloadUrl": "http://ops101.zgpingshu.com/%E7%94%B0%E6%88%98%E4%B9%89/%E9%A3%8E%E4%BA%91%E4%BA%BA%E7%89%A9%E8%92%8B%E4%BB%8B%E7%9F%B3%28162%E5%9B%9E%2932kbps/04347CE470.mp3"
    },
    {
      "name": "005回 - 风云人物蒋介石",
      "url": "http://www.zgpingshu.com/play/4123/5.html",
      "downloadUrl": "http://ops101.zgpingshu.com/%E7%94%B0%E6%88%98%E4%B9%89/%E9%A3%8E%E4%BA%91%E4%BA%BA%E7%89%A9%E8%92%8B%E4%BB%8B%E7%9F%B3%28162%E5%9B%9E%2932kbps/533235C633.mp3"
    },
    {
      "name": "006回 - 风云人物蒋介石",
      "url": "http://www.zgpingshu.com/play/4123/6.html",
      "downloadUrl": "http://ops101.zgpingshu.com/%E7%94%B0%E6%88%98%E4%B9%89/%E9%A3%8E%E4%BA%91%E4%BA%BA%E7%89%A9%E8%92%8B%E4%BB%8B%E7%9F%B3%28162%E5%9B%9E%2932kbps/55A9B27A7B.mp3"
    },
    {
      "name": "007回 - 风云人物蒋介石",
      "url": "http://www.zgpingshu.com/play/4123/7.html",
      "downloadUrl": "http://ops101.zgpingshu.com/%E7%94%B0%E6%88%98%E4%B9%89/%E9%A3%8E%E4%BA%91%E4%BA%BA%E7%89%A9%E8%92%8B%E4%BB%8B%E7%9F%B3%28162%E5%9B%9E%2932kbps/98C36E0276.mp3"
    },
    {
      "name": "008回 - 风云人物蒋介石",
      "url": "http://www.zgpingshu.com/play/4123/8.html",
      "downloadUrl": "http://ops101.zgpingshu.com/%E7%94%B0%E6%88%98%E4%B9%89/%E9%A3%8E%E4%BA%91%E4%BA%BA%E7%89%A9%E8%92%8B%E4%BB%8B%E7%9F%B3%28162%E5%9B%9E%2932kbps/3BE143AAC6.mp3"
    },
    {
      "name": "009回 - 风云人物蒋介石",
      "url": "http://www.zgpingshu.com/play/4123/9.html",
      "downloadUrl": "http://ops101.zgpingshu.com/%E7%94%B0%E6%88%98%E4%B9%89/%E9%A3%8E%E4%BA%91%E4%BA%BA%E7%89%A9%E8%92%8B%E4%BB%8B%E7%9F%B3%28162%E5%9B%9E%2932kbps/7151D3E89D.mp3"
    },
    {
      "name": "010回 - 风云人物蒋介石",
      "url": "http://www.zgpingshu.com/play/4123/10.html",
      "downloadUrl": "http://ops101.zgpingshu.com/%E7%94%B0%E6%88%98%E4%B9%89/%E9%A3%8E%E4%BA%91%E4%BA%BA%E7%89%A9%E8%92%8B%E4%BB%8B%E7%9F%B3%28162%E5%9B%9E%2932kbps/1BE617A204.mp3"
    },
    {
      "name": "011回 - 风云人物蒋介石",
      "url": "http://www.zgpingshu.com/play/4123/11.html",
      "downloadUrl": "http://ops101.zgpingshu.com/%E7%94%B0%E6%88%98%E4%B9%89/%E9%A3%8E%E4%BA%91%E4%BA%BA%E7%89%A9%E8%92%8B%E4%BB%8B%E7%9F%B3%28162%E5%9B%9E%2932kbps/24C1BC9ACB.mp3"
    },
    {
      "name": "012回 - 风云人物蒋介石",
      "url": "http://www.zgpingshu.com/play/4123/12.html",
      "downloadUrl": "http://ops101.zgpingshu.com/%E7%94%B0%E6%88%98%E4%B9%89/%E9%A3%8E%E4%BA%91%E4%BA%BA%E7%89%A9%E8%92%8B%E4%BB%8B%E7%9F%B3%28162%E5%9B%9E%2932kbps/E9534E3891.mp3"
    },
    {
      "name": "013回 - 风云人物蒋介石",
      "url": "http://www.zgpingshu.com/play/4123/13.html",
      "downloadUrl": "http://ops101.zgpingshu.com/%E7%94%B0%E6%88%98%E4%B9%89/%E9%A3%8E%E4%BA%91%E4%BA%BA%E7%89%A9%E8%92%8B%E4%BB%8B%E7%9F%B3%28162%E5%9B%9E%2932kbps/A893AB70F8.mp3"
    },
    {
      "name": "014回 - 风云人物蒋介石",
      "url": "http://www.zgpingshu.com/play/4123/14.html",
      "downloadUrl": "http://ops101.zgpingshu.com/%E7%94%B0%E6%88%98%E4%B9%89/%E9%A3%8E%E4%BA%91%E4%BA%BA%E7%89%A9%E8%92%8B%E4%BB%8B%E7%9F%B3%28162%E5%9B%9E%2932kbps/97AC615C90.mp3"
    },
    {
      "name": "015回 - 风云人物蒋介石",
      "url": "http://www.zgpingshu.com/play/4123/15.html",
      "downloadUrl": "http://ops101.zgpingshu.com/%E7%94%B0%E6%88%98%E4%B9%89/%E9%A3%8E%E4%BA%91%E4%BA%BA%E7%89%A9%E8%92%8B%E4%BB%8B%E7%9F%B3%28162%E5%9B%9E%2932kbps/FE3375D925.mp3"
    },
    {
      "name": "016回 - 风云人物蒋介石",
      "url": "http://www.zgpingshu.com/play/4123/16.html",
      "downloadUrl": "http://ops101.zgpingshu.com/%E7%94%B0%E6%88%98%E4%B9%89/%E9%A3%8E%E4%BA%91%E4%BA%BA%E7%89%A9%E8%92%8B%E4%BB%8B%E7%9F%B3%28162%E5%9B%9E%2932kbps/7D55DC69ED.mp3"
    },
    {
      "name": "017回 - 风云人物蒋介石",
      "url": "http://www.zgpingshu.com/play/4123/17.html",
      "downloadUrl": "http://ops101.zgpingshu.com/%E7%94%B0%E6%88%98%E4%B9%89/%E9%A3%8E%E4%BA%91%E4%BA%BA%E7%89%A9%E8%92%8B%E4%BB%8B%E7%9F%B3%28162%E5%9B%9E%2932kbps/B120AAA447.mp3"
    },
    {
      "name": "018回 - 风云人物蒋介石",
      "url": "http://www.zgpingshu.com/play/4123/18.html",
      "downloadUrl": "http://ops101.zgpingshu.com/%E7%94%B0%E6%88%98%E4%B9%89/%E9%A3%8E%E4%BA%91%E4%BA%BA%E7%89%A9%E8%92%8B%E4%BB%8B%E7%9F%B3%28162%E5%9B%9E%2932kbps/E873E80FD3.mp3"
    },
    {
      "name": "019回 - 风云人物蒋介石",
      "url": "http://www.zgpingshu.com/play/4123/19.html",
      "downloadUrl": "http://ops101.zgpingshu.com/%E7%94%B0%E6%88%98%E4%B9%89/%E9%A3%8E%E4%BA%91%E4%BA%BA%E7%89%A9%E8%92%8B%E4%BB%8B%E7%9F%B3%28162%E5%9B%9E%2932kbps/C4B498E51A.mp3"
    },
    {
      "name": "020回 - 风云人物蒋介石",
      "url": "http://www.zgpingshu.com/play/4123/20.html",
      "downloadUrl": "http://ops101.zgpingshu.com/%E7%94%B0%E6%88%98%E4%B9%89/%E9%A3%8E%E4%BA%91%E4%BA%BA%E7%89%A9%E8%92%8B%E4%BB%8B%E7%9F%B3%28162%E5%9B%9E%2932kbps/A63FBAB367.mp3"
    },
    {
      "name": "021回 - 风云人物蒋介石",
      "url": "http://www.zgpingshu.com/play/4123/21.html",
      "downloadUrl": "http://ops101.zgpingshu.com/%E7%94%B0%E6%88%98%E4%B9%89/%E9%A3%8E%E4%BA%91%E4%BA%BA%E7%89%A9%E8%92%8B%E4%BB%8B%E7%9F%B3%28162%E5%9B%9E%2932kbps/04C2C7F6C1.mp3"
    },
    {
      "name": "022回 - 风云人物蒋介石",
      "url": "http://www.zgpingshu.com/play/4123/22.html",
      "downloadUrl": "http://ops101.zgpingshu.com/%E7%94%B0%E6%88%98%E4%B9%89/%E9%A3%8E%E4%BA%91%E4%BA%BA%E7%89%A9%E8%92%8B%E4%BB%8B%E7%9F%B3%28162%E5%9B%9E%2932kbps/58387C6164.mp3"
    },
    {
      "name": "023回 - 风云人物蒋介石",
      "url": "http://www.zgpingshu.com/play/4123/23.html",
      "downloadUrl": "http://ops101.zgpingshu.com/%E7%94%B0%E6%88%98%E4%B9%89/%E9%A3%8E%E4%BA%91%E4%BA%BA%E7%89%A9%E8%92%8B%E4%BB%8B%E7%9F%B3%28162%E5%9B%9E%2932kbps/9170E85C8D.mp3"
    },
    {
      "name": "024回 - 风云人物蒋介石",
      "url": "http://www.zgpingshu.com/play/4123/24.html",
      "downloadUrl": "http://ops101.zgpingshu.com/%E7%94%B0%E6%88%98%E4%B9%89/%E9%A3%8E%E4%BA%91%E4%BA%BA%E7%89%A9%E8%92%8B%E4%BB%8B%E7%9F%B3%28162%E5%9B%9E%2932kbps/B18DD89E14.mp3"
    },
    {
      "name": "025回 - 风云人物蒋介石",
      "url": "http://www.zgpingshu.com/play/4123/25.html",
      "downloadUrl": "http://ops101.zgpingshu.com/%E7%94%B0%E6%88%98%E4%B9%89/%E9%A3%8E%E4%BA%91%E4%BA%BA%E7%89%A9%E8%92%8B%E4%BB%8B%E7%9F%B3%28162%E5%9B%9E%2932kbps/ECAFD44AE8.mp3"
    },
    {
      "name": "026回 - 风云人物蒋介石",
      "url": "http://www.zgpingshu.com/play/4123/26.html",
      "downloadUrl": "http://ops101.zgpingshu.com/%E7%94%B0%E6%88%98%E4%B9%89/%E9%A3%8E%E4%BA%91%E4%BA%BA%E7%89%A9%E8%92%8B%E4%BB%8B%E7%9F%B3%28162%E5%9B%9E%2932kbps/3DE3111B75.mp3"
    },
    {
      "name": "027回 - 风云人物蒋介石",
      "url": "http://www.zgpingshu.com/play/4123/27.html",
      "downloadUrl": "http://ops101.zgpingshu.com/%E7%94%B0%E6%88%98%E4%B9%89/%E9%A3%8E%E4%BA%91%E4%BA%BA%E7%89%A9%E8%92%8B%E4%BB%8B%E7%9F%B3%28162%E5%9B%9E%2932kbps/1C05927407.mp3"
    },
    {
      "name": "028回 - 风云人物蒋介石",
      "url": "http://www.zgpingshu.com/play/4123/28.html",
      "downloadUrl": "http://ops101.zgpingshu.com/%E7%94%B0%E6%88%98%E4%B9%89/%E9%A3%8E%E4%BA%91%E4%BA%BA%E7%89%A9%E8%92%8B%E4%BB%8B%E7%9F%B3%28162%E5%9B%9E%2932kbps/D9F0141319.mp3"
    },
    {
      "name": "029回 - 风云人物蒋介石",
      "url": "http://www.zgpingshu.com/play/4123/29.html",
      "downloadUrl": "http://ops101.zgpingshu.com/%E7%94%B0%E6%88%98%E4%B9%89/%E9%A3%8E%E4%BA%91%E4%BA%BA%E7%89%A9%E8%92%8B%E4%BB%8B%E7%9F%B3%28162%E5%9B%9E%2932kbps/FE1DE724BF.mp3"
    },
    {
      "name": "030回 - 风云人物蒋介石",
      "url": "http://www.zgpingshu.com/play/4123/30.html",
      "downloadUrl": "http://ops101.zgpingshu.com/%E7%94%B0%E6%88%98%E4%B9%89/%E9%A3%8E%E4%BA%91%E4%BA%BA%E7%89%A9%E8%92%8B%E4%BB%8B%E7%9F%B3%28162%E5%9B%9E%2932kbps/F459CCEA34.mp3"
    },
    {
      "name": "031回 - 风云人物蒋介石",
      "url": "http://www.zgpingshu.com/play/4123/31.html",
      "downloadUrl": "http://ops101.zgpingshu.com/%E7%94%B0%E6%88%98%E4%B9%89/%E9%A3%8E%E4%BA%91%E4%BA%BA%E7%89%A9%E8%92%8B%E4%BB%8B%E7%9F%B3%28162%E5%9B%9E%2932kbps/779934804A.mp3"
    },
    {
      "name": "032回 - 风云人物蒋介石",
      "url": "http://www.zgpingshu.com/play/4123/32.html",
      "downloadUrl": "http://ops101.zgpingshu.com/%E7%94%B0%E6%88%98%E4%B9%89/%E9%A3%8E%E4%BA%91%E4%BA%BA%E7%89%A9%E8%92%8B%E4%BB%8B%E7%9F%B3%28162%E5%9B%9E%2932kbps/AF34F3A723.mp3"
    },
    {
      "name": "033回 - 风云人物蒋介石",
      "url": "http://www.zgpingshu.com/play/4123/33.html",
      "downloadUrl": "http://ops101.zgpingshu.com/%E7%94%B0%E6%88%98%E4%B9%89/%E9%A3%8E%E4%BA%91%E4%BA%BA%E7%89%A9%E8%92%8B%E4%BB%8B%E7%9F%B3%28162%E5%9B%9E%2932kbps/16ADE596A0.mp3"
    },
    {
      "name": "034回 - 风云人物蒋介石",
      "url": "http://www.zgpingshu.com/play/4123/34.html",
      "downloadUrl": "http://ops101.zgpingshu.com/%E7%94%B0%E6%88%98%E4%B9%89/%E9%A3%8E%E4%BA%91%E4%BA%BA%E7%89%A9%E8%92%8B%E4%BB%8B%E7%9F%B3%28162%E5%9B%9E%2932kbps/783774F595.mp3"
    },
    {
      "name": "035回 - 风云人物蒋介石",
      "url": "http://www.zgpingshu.com/play/4123/35.html",
      "downloadUrl": "http://ops101.zgpingshu.com/%E7%94%B0%E6%88%98%E4%B9%89/%E9%A3%8E%E4%BA%91%E4%BA%BA%E7%89%A9%E8%92%8B%E4%BB%8B%E7%9F%B3%28162%E5%9B%9E%2932kbps/CD25B12CDC.mp3"
    },
    {
      "name": "036回 - 风云人物蒋介石",
      "url": "http://www.zgpingshu.com/play/4123/36.html",
      "downloadUrl": "http://ops101.zgpingshu.com/%E7%94%B0%E6%88%98%E4%B9%89/%E9%A3%8E%E4%BA%91%E4%BA%BA%E7%89%A9%E8%92%8B%E4%BB%8B%E7%9F%B3%28162%E5%9B%9E%2932kbps/F559683514.mp3"
    },
    {
      "name": "037回 - 风云人物蒋介石",
      "url": "http://www.zgpingshu.com/play/4123/37.html",
      "downloadUrl": "http://ops101.zgpingshu.com/%E7%94%B0%E6%88%98%E4%B9%89/%E9%A3%8E%E4%BA%91%E4%BA%BA%E7%89%A9%E8%92%8B%E4%BB%8B%E7%9F%B3%28162%E5%9B%9E%2932kbps/AB7D20C093.mp3"
    },
    {
      "name": "038回 - 风云人物蒋介石",
      "url": "http://www.zgpingshu.com/play/4123/38.html",
      "downloadUrl": "http://ops101.zgpingshu.com/%E7%94%B0%E6%88%98%E4%B9%89/%E9%A3%8E%E4%BA%91%E4%BA%BA%E7%89%A9%E8%92%8B%E4%BB%8B%E7%9F%B3%28162%E5%9B%9E%2932kbps/5A393E7FA7.mp3"
    },
    {
      "name": "039回 - 风云人物蒋介石",
      "url": "http://www.zgpingshu.com/play/4123/39.html",
      "downloadUrl": "http://ops101.zgpingshu.com/%E7%94%B0%E6%88%98%E4%B9%89/%E9%A3%8E%E4%BA%91%E4%BA%BA%E7%89%A9%E8%92%8B%E4%BB%8B%E7%9F%B3%28162%E5%9B%9E%2932kbps/4035046665.mp3"
    },
    {
      "name": "040回 - 风云人物蒋介石",
      "url": "http://www.zgpingshu.com/play/4123/40.html",
      "downloadUrl": "http://ops101.zgpingshu.com/%E7%94%B0%E6%88%98%E4%B9%89/%E9%A3%8E%E4%BA%91%E4%BA%BA%E7%89%A9%E8%92%8B%E4%BB%8B%E7%9F%B3%28162%E5%9B%9E%2932kbps/6E64925D5D.mp3"
    },
    {
      "name": "041回 - 风云人物蒋介石",
      "url": "http://www.zgpingshu.com/play/4123/41.html",
      "downloadUrl": "http://ops101.zgpingshu.com/%E7%94%B0%E6%88%98%E4%B9%89/%E9%A3%8E%E4%BA%91%E4%BA%BA%E7%89%A9%E8%92%8B%E4%BB%8B%E7%9F%B3%28162%E5%9B%9E%2932kbps/E73EB9EF89.mp3"
    },
    {
      "name": "042回 - 风云人物蒋介石",
      "url": "http://www.zgpingshu.com/play/4123/42.html",
      "downloadUrl": "http://ops101.zgpingshu.com/%E7%94%B0%E6%88%98%E4%B9%89/%E9%A3%8E%E4%BA%91%E4%BA%BA%E7%89%A9%E8%92%8B%E4%BB%8B%E7%9F%B3%28162%E5%9B%9E%2932kbps/28C0CAED82.mp3"
    },
    {
      "name": "043回 - 风云人物蒋介石",
      "url": "http://www.zgpingshu.com/play/4123/43.html",
      "downloadUrl": "http://ops101.zgpingshu.com/%E7%94%B0%E6%88%98%E4%B9%89/%E9%A3%8E%E4%BA%91%E4%BA%BA%E7%89%A9%E8%92%8B%E4%BB%8B%E7%9F%B3%28162%E5%9B%9E%2932kbps/D4DE09761B.mp3"
    },
    {
      "name": "044回 - 风云人物蒋介石",
      "url": "http://www.zgpingshu.com/play/4123/44.html",
      "downloadUrl": "http://ops101.zgpingshu.com/%E7%94%B0%E6%88%98%E4%B9%89/%E9%A3%8E%E4%BA%91%E4%BA%BA%E7%89%A9%E8%92%8B%E4%BB%8B%E7%9F%B3%28162%E5%9B%9E%2932kbps/95BD78677B.mp3"
    },
    {
      "name": "045回 - 风云人物蒋介石",
      "url": "http://www.zgpingshu.com/play/4123/45.html",
      "downloadUrl": "http://ops101.zgpingshu.com/%E7%94%B0%E6%88%98%E4%B9%89/%E9%A3%8E%E4%BA%91%E4%BA%BA%E7%89%A9%E8%92%8B%E4%BB%8B%E7%9F%B3%28162%E5%9B%9E%2932kbps/274A1B9B58.mp3"
    },
    {
      "name": "046回 - 风云人物蒋介石",
      "url": "http://www.zgpingshu.com/play/4123/46.html",
      "downloadUrl": "http://ops101.zgpingshu.com/%E7%94%B0%E6%88%98%E4%B9%89/%E9%A3%8E%E4%BA%91%E4%BA%BA%E7%89%A9%E8%92%8B%E4%BB%8B%E7%9F%B3%28162%E5%9B%9E%2932kbps/BB4509CC38.mp3"
    },
    {
      "name": "047回 - 风云人物蒋介石",
      "url": "http://www.zgpingshu.com/play/4123/47.html",
      "downloadUrl": "http://ops101.zgpingshu.com/%E7%94%B0%E6%88%98%E4%B9%89/%E9%A3%8E%E4%BA%91%E4%BA%BA%E7%89%A9%E8%92%8B%E4%BB%8B%E7%9F%B3%28162%E5%9B%9E%2932kbps/DDFAD8317D.mp3"
    },
    {
      "name": "048回 - 风云人物蒋介石",
      "url": "http://www.zgpingshu.com/play/4123/48.html",
      "downloadUrl": "http://ops101.zgpingshu.com/%E7%94%B0%E6%88%98%E4%B9%89/%E9%A3%8E%E4%BA%91%E4%BA%BA%E7%89%A9%E8%92%8B%E4%BB%8B%E7%9F%B3%28162%E5%9B%9E%2932kbps/E1D36692EF.mp3"
    },
    {
      "name": "049回 - 风云人物蒋介石",
      "url": "http://www.zgpingshu.com/play/4123/49.html",
      "downloadUrl": "http://ops101.zgpingshu.com/%E7%94%B0%E6%88%98%E4%B9%89/%E9%A3%8E%E4%BA%91%E4%BA%BA%E7%89%A9%E8%92%8B%E4%BB%8B%E7%9F%B3%28162%E5%9B%9E%2932kbps/C70320697E.mp3"
    },
    {
      "name": "050回 - 风云人物蒋介石",
      "url": "http://www.zgpingshu.com/play/4123/50.html",
      "downloadUrl": "http://ops101.zgpingshu.com/%E7%94%B0%E6%88%98%E4%B9%89/%E9%A3%8E%E4%BA%91%E4%BA%BA%E7%89%A9%E8%92%8B%E4%BB%8B%E7%9F%B3%28162%E5%9B%9E%2932kbps/964AAC23C9.mp3"
    },
    {
      "name": "051回 - 风云人物蒋介石",
      "url": "http://www.zgpingshu.com/play/4123/51.html",
      "downloadUrl": "http://ops101.zgpingshu.com/%E7%94%B0%E6%88%98%E4%B9%89/%E9%A3%8E%E4%BA%91%E4%BA%BA%E7%89%A9%E8%92%8B%E4%BB%8B%E7%9F%B3%28162%E5%9B%9E%2932kbps/0209DED217.mp3"
    },
    {
      "name": "052回 - 风云人物蒋介石",
      "url": "http://www.zgpingshu.com/play/4123/52.html",
      "downloadUrl": "http://ops101.zgpingshu.com/%E7%94%B0%E6%88%98%E4%B9%89/%E9%A3%8E%E4%BA%91%E4%BA%BA%E7%89%A9%E8%92%8B%E4%BB%8B%E7%9F%B3%28162%E5%9B%9E%2932kbps/19FF426ED9.mp3"
    },
    {
      "name": "053回 - 风云人物蒋介石",
      "url": "http://www.zgpingshu.com/play/4123/53.html",
      "downloadUrl": "http://ops101.zgpingshu.com/%E7%94%B0%E6%88%98%E4%B9%89/%E9%A3%8E%E4%BA%91%E4%BA%BA%E7%89%A9%E8%92%8B%E4%BB%8B%E7%9F%B3%28162%E5%9B%9E%2932kbps/3D2D7959F6.mp3"
    },
    {
      "name": "054回 - 风云人物蒋介石",
      "url": "http://www.zgpingshu.com/play/4123/54.html",
      "downloadUrl": "http://ops101.zgpingshu.com/%E7%94%B0%E6%88%98%E4%B9%89/%E9%A3%8E%E4%BA%91%E4%BA%BA%E7%89%A9%E8%92%8B%E4%BB%8B%E7%9F%B3%28162%E5%9B%9E%2932kbps/DD491C0704.mp3"
    },
    {
      "name": "055回 - 风云人物蒋介石",
      "url": "http://www.zgpingshu.com/play/4123/55.html",
      "downloadUrl": "http://ops101.zgpingshu.com/%E7%94%B0%E6%88%98%E4%B9%89/%E9%A3%8E%E4%BA%91%E4%BA%BA%E7%89%A9%E8%92%8B%E4%BB%8B%E7%9F%B3%28162%E5%9B%9E%2932kbps/39E9C7AB3D.mp3"
    },
    {
      "name": "056回 - 风云人物蒋介石",
      "url": "http://www.zgpingshu.com/play/4123/56.html",
      "downloadUrl": "http://ops101.zgpingshu.com/%E7%94%B0%E6%88%98%E4%B9%89/%E9%A3%8E%E4%BA%91%E4%BA%BA%E7%89%A9%E8%92%8B%E4%BB%8B%E7%9F%B3%28162%E5%9B%9E%2932kbps/7A817306FB.mp3"
    },
    {
      "name": "057回 - 风云人物蒋介石",
      "url": "http://www.zgpingshu.com/play/4123/57.html",
      "downloadUrl": "http://ops101.zgpingshu.com/%E7%94%B0%E6%88%98%E4%B9%89/%E9%A3%8E%E4%BA%91%E4%BA%BA%E7%89%A9%E8%92%8B%E4%BB%8B%E7%9F%B3%28162%E5%9B%9E%2932kbps/2DFF03C90C.mp3"
    },
    {
      "name": "058回 - 风云人物蒋介石",
      "url": "http://www.zgpingshu.com/play/4123/58.html",
      "downloadUrl": "http://ops101.zgpingshu.com/%E7%94%B0%E6%88%98%E4%B9%89/%E9%A3%8E%E4%BA%91%E4%BA%BA%E7%89%A9%E8%92%8B%E4%BB%8B%E7%9F%B3%28162%E5%9B%9E%2932kbps/CC85DCFE03.mp3"
    },
    {
      "name": "059回 - 风云人物蒋介石",
      "url": "http://www.zgpingshu.com/play/4123/59.html",
      "downloadUrl": "http://ops101.zgpingshu.com/%E7%94%B0%E6%88%98%E4%B9%89/%E9%A3%8E%E4%BA%91%E4%BA%BA%E7%89%A9%E8%92%8B%E4%BB%8B%E7%9F%B3%28162%E5%9B%9E%2932kbps/101873F43C.mp3"
    },
    {
      "name": "060回 - 风云人物蒋介石",
      "url": "http://www.zgpingshu.com/play/4123/60.html",
      "downloadUrl": "http://ops101.zgpingshu.com/%E7%94%B0%E6%88%98%E4%B9%89/%E9%A3%8E%E4%BA%91%E4%BA%BA%E7%89%A9%E8%92%8B%E4%BB%8B%E7%9F%B3%28162%E5%9B%9E%2932kbps/AC7F900757.mp3"
    },
    {
      "name": "061回 - 风云人物蒋介石",
      "url": "http://www.zgpingshu.com/play/4123/61.html",
      "downloadUrl": "http://ops101.zgpingshu.com/%E7%94%B0%E6%88%98%E4%B9%89/%E9%A3%8E%E4%BA%91%E4%BA%BA%E7%89%A9%E8%92%8B%E4%BB%8B%E7%9F%B3%28162%E5%9B%9E%2932kbps/B33A46D08A.mp3"
    },
    {
      "name": "062回 - 风云人物蒋介石",
      "url": "http://www.zgpingshu.com/play/4123/62.html",
      "downloadUrl": "http://ops101.zgpingshu.com/%E7%94%B0%E6%88%98%E4%B9%89/%E9%A3%8E%E4%BA%91%E4%BA%BA%E7%89%A9%E8%92%8B%E4%BB%8B%E7%9F%B3%28162%E5%9B%9E%2932kbps/3E83B2B492.mp3"
    },
    {
      "name": "063回 - 风云人物蒋介石",
      "url": "http://www.zgpingshu.com/play/4123/63.html",
      "downloadUrl": "http://ops101.zgpingshu.com/%E7%94%B0%E6%88%98%E4%B9%89/%E9%A3%8E%E4%BA%91%E4%BA%BA%E7%89%A9%E8%92%8B%E4%BB%8B%E7%9F%B3%28162%E5%9B%9E%2932kbps/ED9C9E9BD3.mp3"
    },
    {
      "name": "064回 - 风云人物蒋介石",
      "url": "http://www.zgpingshu.com/play/4123/64.html",
      "downloadUrl": "http://ops101.zgpingshu.com/%E7%94%B0%E6%88%98%E4%B9%89/%E9%A3%8E%E4%BA%91%E4%BA%BA%E7%89%A9%E8%92%8B%E4%BB%8B%E7%9F%B3%28162%E5%9B%9E%2932kbps/D32F5A6FE6.mp3"
    },
    {
      "name": "065回 - 风云人物蒋介石",
      "url": "http://www.zgpingshu.com/play/4123/65.html",
      "downloadUrl": "http://ops101.zgpingshu.com/%E7%94%B0%E6%88%98%E4%B9%89/%E9%A3%8E%E4%BA%91%E4%BA%BA%E7%89%A9%E8%92%8B%E4%BB%8B%E7%9F%B3%28162%E5%9B%9E%2932kbps/1703D1F0B5.mp3"
    },
    {
      "name": "066回 - 风云人物蒋介石",
      "url": "http://www.zgpingshu.com/play/4123/66.html",
      "downloadUrl": "http://ops101.zgpingshu.com/%E7%94%B0%E6%88%98%E4%B9%89/%E9%A3%8E%E4%BA%91%E4%BA%BA%E7%89%A9%E8%92%8B%E4%BB%8B%E7%9F%B3%28162%E5%9B%9E%2932kbps/AD1568A868.mp3"
    },
    {
      "name": "067回 - 风云人物蒋介石",
      "url": "http://www.zgpingshu.com/play/4123/67.html",
      "downloadUrl": "http://ops101.zgpingshu.com/%E7%94%B0%E6%88%98%E4%B9%89/%E9%A3%8E%E4%BA%91%E4%BA%BA%E7%89%A9%E8%92%8B%E4%BB%8B%E7%9F%B3%28162%E5%9B%9E%2932kbps/DEB5843D3C.mp3"
    },
    {
      "name": "068回 - 风云人物蒋介石",
      "url": "http://www.zgpingshu.com/play/4123/68.html",
      "downloadUrl": "http://ops101.zgpingshu.com/%E7%94%B0%E6%88%98%E4%B9%89/%E9%A3%8E%E4%BA%91%E4%BA%BA%E7%89%A9%E8%92%8B%E4%BB%8B%E7%9F%B3%28162%E5%9B%9E%2932kbps/5125446FCF.mp3"
    },
    {
      "name": "069回 - 风云人物蒋介石",
      "url": "http://www.zgpingshu.com/play/4123/69.html",
      "downloadUrl": "http://ops101.zgpingshu.com/%E7%94%B0%E6%88%98%E4%B9%89/%E9%A3%8E%E4%BA%91%E4%BA%BA%E7%89%A9%E8%92%8B%E4%BB%8B%E7%9F%B3%28162%E5%9B%9E%2932kbps/4CAA5F8F3A.mp3"
    },
    {
      "name": "070回 - 风云人物蒋介石",
      "url": "http://www.zgpingshu.com/play/4123/70.html",
      "downloadUrl": "http://ops101.zgpingshu.com/%E7%94%B0%E6%88%98%E4%B9%89/%E9%A3%8E%E4%BA%91%E4%BA%BA%E7%89%A9%E8%92%8B%E4%BB%8B%E7%9F%B3%28162%E5%9B%9E%2932kbps/62D31736B2.mp3"
    },
    {
      "name": "071回 - 风云人物蒋介石",
      "url": "http://www.zgpingshu.com/play/4123/71.html",
      "downloadUrl": "http://ops101.zgpingshu.com/%E7%94%B0%E6%88%98%E4%B9%89/%E9%A3%8E%E4%BA%91%E4%BA%BA%E7%89%A9%E8%92%8B%E4%BB%8B%E7%9F%B3%28162%E5%9B%9E%2932kbps/3D4767A7E4.mp3"
    },
    {
      "name": "072回 - 风云人物蒋介石",
      "url": "http://www.zgpingshu.com/play/4123/72.html",
      "downloadUrl": "http://ops101.zgpingshu.com/%E7%94%B0%E6%88%98%E4%B9%89/%E9%A3%8E%E4%BA%91%E4%BA%BA%E7%89%A9%E8%92%8B%E4%BB%8B%E7%9F%B3%28162%E5%9B%9E%2932kbps/76076FBF7F.mp3"
    },
    {
      "name": "073回 - 风云人物蒋介石",
      "url": "http://www.zgpingshu.com/play/4123/73.html",
      "downloadUrl": "http://ops101.zgpingshu.com/%E7%94%B0%E6%88%98%E4%B9%89/%E9%A3%8E%E4%BA%91%E4%BA%BA%E7%89%A9%E8%92%8B%E4%BB%8B%E7%9F%B3%28162%E5%9B%9E%2932kbps/EFAB571193.mp3"
    },
    {
      "name": "074回 - 风云人物蒋介石",
      "url": "http://www.zgpingshu.com/play/4123/74.html",
      "downloadUrl": "http://ops101.zgpingshu.com/%E7%94%B0%E6%88%98%E4%B9%89/%E9%A3%8E%E4%BA%91%E4%BA%BA%E7%89%A9%E8%92%8B%E4%BB%8B%E7%9F%B3%28162%E5%9B%9E%2932kbps/143A0CC52F.mp3"
    },
    {
      "name": "075回 - 风云人物蒋介石",
      "url": "http://www.zgpingshu.com/play/4123/75.html",
      "downloadUrl": "http://ops101.zgpingshu.com/%E7%94%B0%E6%88%98%E4%B9%89/%E9%A3%8E%E4%BA%91%E4%BA%BA%E7%89%A9%E8%92%8B%E4%BB%8B%E7%9F%B3%28162%E5%9B%9E%2932kbps/0D60AAEEE5.mp3"
    },
    {
      "name": "076回 - 风云人物蒋介石",
      "url": "http://www.zgpingshu.com/play/4123/76.html",
      "downloadUrl": "http://ops101.zgpingshu.com/%E7%94%B0%E6%88%98%E4%B9%89/%E9%A3%8E%E4%BA%91%E4%BA%BA%E7%89%A9%E8%92%8B%E4%BB%8B%E7%9F%B3%28162%E5%9B%9E%2932kbps/CFE930AB71.mp3"
    },
    {
      "name": "077回 - 风云人物蒋介石",
      "url": "http://www.zgpingshu.com/play/4123/77.html",
      "downloadUrl": "http://ops101.zgpingshu.com/%E7%94%B0%E6%88%98%E4%B9%89/%E9%A3%8E%E4%BA%91%E4%BA%BA%E7%89%A9%E8%92%8B%E4%BB%8B%E7%9F%B3%28162%E5%9B%9E%2932kbps/C5CFD58BEF.mp3"
    },
    {
      "name": "078回 - 风云人物蒋介石",
      "url": "http://www.zgpingshu.com/play/4123/78.html",
      "downloadUrl": "http://ops101.zgpingshu.com/%E7%94%B0%E6%88%98%E4%B9%89/%E9%A3%8E%E4%BA%91%E4%BA%BA%E7%89%A9%E8%92%8B%E4%BB%8B%E7%9F%B3%28162%E5%9B%9E%2932kbps/3744940E5A.mp3"
    },
    {
      "name": "079回 - 风云人物蒋介石",
      "url": "http://www.zgpingshu.com/play/4123/79.html",
      "downloadUrl": "http://ops101.zgpingshu.com/%E7%94%B0%E6%88%98%E4%B9%89/%E9%A3%8E%E4%BA%91%E4%BA%BA%E7%89%A9%E8%92%8B%E4%BB%8B%E7%9F%B3%28162%E5%9B%9E%2932kbps/481D5BBF00.mp3"
    },
    {
      "name": "080回 - 风云人物蒋介石",
      "url": "http://www.zgpingshu.com/play/4123/80.html",
      "downloadUrl": "http://ops101.zgpingshu.com/%E7%94%B0%E6%88%98%E4%B9%89/%E9%A3%8E%E4%BA%91%E4%BA%BA%E7%89%A9%E8%92%8B%E4%BB%8B%E7%9F%B3%28162%E5%9B%9E%2932kbps/0E6E7DB5B2.mp3"
    },
    {
      "name": "081回 - 风云人物蒋介石",
      "url": "http://www.zgpingshu.com/play/4123/81.html",
      "downloadUrl": "http://ops101.zgpingshu.com/%E7%94%B0%E6%88%98%E4%B9%89/%E9%A3%8E%E4%BA%91%E4%BA%BA%E7%89%A9%E8%92%8B%E4%BB%8B%E7%9F%B3%28162%E5%9B%9E%2932kbps/72E5ED0411.mp3"
    },
    {
      "name": "082回 - 风云人物蒋介石",
      "url": "http://www.zgpingshu.com/play/4123/82.html",
      "downloadUrl": "http://ops101.zgpingshu.com/%E7%94%B0%E6%88%98%E4%B9%89/%E9%A3%8E%E4%BA%91%E4%BA%BA%E7%89%A9%E8%92%8B%E4%BB%8B%E7%9F%B3%28162%E5%9B%9E%2932kbps/F09C042CC1.mp3"
    },
    {
      "name": "083回 - 风云人物蒋介石",
      "url": "http://www.zgpingshu.com/play/4123/83.html",
      "downloadUrl": "http://ops101.zgpingshu.com/%E7%94%B0%E6%88%98%E4%B9%89/%E9%A3%8E%E4%BA%91%E4%BA%BA%E7%89%A9%E8%92%8B%E4%BB%8B%E7%9F%B3%28162%E5%9B%9E%2932kbps/98B3200F13.mp3"
    },
    {
      "name": "084回 - 风云人物蒋介石",
      "url": "http://www.zgpingshu.com/play/4123/84.html",
      "downloadUrl": "http://ops101.zgpingshu.com/%E7%94%B0%E6%88%98%E4%B9%89/%E9%A3%8E%E4%BA%91%E4%BA%BA%E7%89%A9%E8%92%8B%E4%BB%8B%E7%9F%B3%28162%E5%9B%9E%2932kbps/314E968500.mp3"
    },
    {
      "name": "085回 - 风云人物蒋介石",
      "url": "http://www.zgpingshu.com/play/4123/85.html",
      "downloadUrl": "http://ops101.zgpingshu.com/%E7%94%B0%E6%88%98%E4%B9%89/%E9%A3%8E%E4%BA%91%E4%BA%BA%E7%89%A9%E8%92%8B%E4%BB%8B%E7%9F%B3%28162%E5%9B%9E%2932kbps/BDCFE8D47A.mp3"
    },
    {
      "name": "086回 - 风云人物蒋介石",
      "url": "http://www.zgpingshu.com/play/4123/86.html",
      "downloadUrl": "http://ops101.zgpingshu.com/%E7%94%B0%E6%88%98%E4%B9%89/%E9%A3%8E%E4%BA%91%E4%BA%BA%E7%89%A9%E8%92%8B%E4%BB%8B%E7%9F%B3%28162%E5%9B%9E%2932kbps/9738F81399.mp3"
    },
    {
      "name": "087回 - 风云人物蒋介石",
      "url": "http://www.zgpingshu.com/play/4123/87.html",
      "downloadUrl": "http://ops101.zgpingshu.com/%E7%94%B0%E6%88%98%E4%B9%89/%E9%A3%8E%E4%BA%91%E4%BA%BA%E7%89%A9%E8%92%8B%E4%BB%8B%E7%9F%B3%28162%E5%9B%9E%2932kbps/E8D7E424B9.mp3"
    },
    {
      "name": "088回 - 风云人物蒋介石",
      "url": "http://www.zgpingshu.com/play/4123/88.html",
      "downloadUrl": "http://ops101.zgpingshu.com/%E7%94%B0%E6%88%98%E4%B9%89/%E9%A3%8E%E4%BA%91%E4%BA%BA%E7%89%A9%E8%92%8B%E4%BB%8B%E7%9F%B3%28162%E5%9B%9E%2932kbps/6F79F203DF.mp3"
    },
    {
      "name": "089回 - 风云人物蒋介石",
      "url": "http://www.zgpingshu.com/play/4123/89.html",
      "downloadUrl": "http://ops101.zgpingshu.com/%E7%94%B0%E6%88%98%E4%B9%89/%E9%A3%8E%E4%BA%91%E4%BA%BA%E7%89%A9%E8%92%8B%E4%BB%8B%E7%9F%B3%28162%E5%9B%9E%2932kbps/99C441DBFF.mp3"
    },
    {
      "name": "090回 - 风云人物蒋介石",
      "url": "http://www.zgpingshu.com/play/4123/90.html",
      "downloadUrl": "http://ops101.zgpingshu.com/%E7%94%B0%E6%88%98%E4%B9%89/%E9%A3%8E%E4%BA%91%E4%BA%BA%E7%89%A9%E8%92%8B%E4%BB%8B%E7%9F%B3%28162%E5%9B%9E%2932kbps/86007A787E.mp3"
    },
    {
      "name": "091回 - 风云人物蒋介石",
      "url": "http://www.zgpingshu.com/play/4123/91.html",
      "downloadUrl": "http://ops101.zgpingshu.com/%E7%94%B0%E6%88%98%E4%B9%89/%E9%A3%8E%E4%BA%91%E4%BA%BA%E7%89%A9%E8%92%8B%E4%BB%8B%E7%9F%B3%28162%E5%9B%9E%2932kbps/9E51474A26.mp3"
    },
    {
      "name": "092回 - 风云人物蒋介石",
      "url": "http://www.zgpingshu.com/play/4123/92.html",
      "downloadUrl": "http://ops101.zgpingshu.com/%E7%94%B0%E6%88%98%E4%B9%89/%E9%A3%8E%E4%BA%91%E4%BA%BA%E7%89%A9%E8%92%8B%E4%BB%8B%E7%9F%B3%28162%E5%9B%9E%2932kbps/29E5E819B4.mp3"
    },
    {
      "name": "093回 - 风云人物蒋介石",
      "url": "http://www.zgpingshu.com/play/4123/93.html",
      "downloadUrl": "http://ops101.zgpingshu.com/%E7%94%B0%E6%88%98%E4%B9%89/%E9%A3%8E%E4%BA%91%E4%BA%BA%E7%89%A9%E8%92%8B%E4%BB%8B%E7%9F%B3%28162%E5%9B%9E%2932kbps/36567DFF36.mp3"
    },
    {
      "name": "094回 - 风云人物蒋介石",
      "url": "http://www.zgpingshu.com/play/4123/94.html",
      "downloadUrl": "http://ops101.zgpingshu.com/%E7%94%B0%E6%88%98%E4%B9%89/%E9%A3%8E%E4%BA%91%E4%BA%BA%E7%89%A9%E8%92%8B%E4%BB%8B%E7%9F%B3%28162%E5%9B%9E%2932kbps/1BDE5379DD.mp3"
    },
    {
      "name": "095回 - 风云人物蒋介石",
      "url": "http://www.zgpingshu.com/play/4123/95.html",
      "downloadUrl": "http://ops101.zgpingshu.com/%E7%94%B0%E6%88%98%E4%B9%89/%E9%A3%8E%E4%BA%91%E4%BA%BA%E7%89%A9%E8%92%8B%E4%BB%8B%E7%9F%B3%28162%E5%9B%9E%2932kbps/71E61FD91B.mp3"
    },
    {
      "name": "096回 - 风云人物蒋介石",
      "url": "http://www.zgpingshu.com/play/4123/96.html",
      "downloadUrl": "http://ops101.zgpingshu.com/%E7%94%B0%E6%88%98%E4%B9%89/%E9%A3%8E%E4%BA%91%E4%BA%BA%E7%89%A9%E8%92%8B%E4%BB%8B%E7%9F%B3%28162%E5%9B%9E%2932kbps/F59079820E.mp3"
    },
    {
      "name": "097回 - 风云人物蒋介石",
      "url": "http://www.zgpingshu.com/play/4123/97.html",
      "downloadUrl": "http://ops101.zgpingshu.com/%E7%94%B0%E6%88%98%E4%B9%89/%E9%A3%8E%E4%BA%91%E4%BA%BA%E7%89%A9%E8%92%8B%E4%BB%8B%E7%9F%B3%28162%E5%9B%9E%2932kbps/1CA45CF1DB.mp3"
    },
    {
      "name": "098回 - 风云人物蒋介石",
      "url": "http://www.zgpingshu.com/play/4123/98.html",
      "downloadUrl": "http://ops101.zgpingshu.com/%E7%94%B0%E6%88%98%E4%B9%89/%E9%A3%8E%E4%BA%91%E4%BA%BA%E7%89%A9%E8%92%8B%E4%BB%8B%E7%9F%B3%28162%E5%9B%9E%2932kbps/2CECA81698.mp3"
    },
    {
      "name": "099回 - 风云人物蒋介石",
      "url": "http://www.zgpingshu.com/play/4123/99.html",
      "downloadUrl": "http://ops101.zgpingshu.com/%E7%94%B0%E6%88%98%E4%B9%89/%E9%A3%8E%E4%BA%91%E4%BA%BA%E7%89%A9%E8%92%8B%E4%BB%8B%E7%9F%B3%28162%E5%9B%9E%2932kbps/B48F0287B3.mp3"
    },
    {
      "name": "100回 - 风云人物蒋介石",
      "url": "http://www.zgpingshu.com/play/4123/100.html",
      "downloadUrl": "http://ops101.zgpingshu.com/%E7%94%B0%E6%88%98%E4%B9%89/%E9%A3%8E%E4%BA%91%E4%BA%BA%E7%89%A9%E8%92%8B%E4%BB%8B%E7%9F%B3%28162%E5%9B%9E%2932kbps/C954BFD36E.mp3"
    },
    {
      "name": "101回 - 风云人物蒋介石",
      "url": "http://www.zgpingshu.com/play/4123/101.html",
      "downloadUrl": "http://ops101.zgpingshu.com/%E7%94%B0%E6%88%98%E4%B9%89/%E9%A3%8E%E4%BA%91%E4%BA%BA%E7%89%A9%E8%92%8B%E4%BB%8B%E7%9F%B3%28162%E5%9B%9E%2932kbps/ECA0FFED3A.mp3"
    },
    {
      "name": "102回 - 风云人物蒋介石",
      "url": "http://www.zgpingshu.com/play/4123/102.html",
      "downloadUrl": "http://ops101.zgpingshu.com/%E7%94%B0%E6%88%98%E4%B9%89/%E9%A3%8E%E4%BA%91%E4%BA%BA%E7%89%A9%E8%92%8B%E4%BB%8B%E7%9F%B3%28162%E5%9B%9E%2932kbps/FA0E3D29E8.mp3"
    },
    {
      "name": "103回 - 风云人物蒋介石",
      "url": "http://www.zgpingshu.com/play/4123/103.html",
      "downloadUrl": "http://ops101.zgpingshu.com/%E7%94%B0%E6%88%98%E4%B9%89/%E9%A3%8E%E4%BA%91%E4%BA%BA%E7%89%A9%E8%92%8B%E4%BB%8B%E7%9F%B3%28162%E5%9B%9E%2932kbps/8CEE3EE9AA.mp3"
    },
    {
      "name": "104回 - 风云人物蒋介石",
      "url": "http://www.zgpingshu.com/play/4123/104.html",
      "downloadUrl": "http://ops101.zgpingshu.com/%E7%94%B0%E6%88%98%E4%B9%89/%E9%A3%8E%E4%BA%91%E4%BA%BA%E7%89%A9%E8%92%8B%E4%BB%8B%E7%9F%B3%28162%E5%9B%9E%2932kbps/5EC09EC85C.mp3"
    },
    {
      "name": "105回 - 风云人物蒋介石",
      "url": "http://www.zgpingshu.com/play/4123/105.html",
      "downloadUrl": "http://ops101.zgpingshu.com/%E7%94%B0%E6%88%98%E4%B9%89/%E9%A3%8E%E4%BA%91%E4%BA%BA%E7%89%A9%E8%92%8B%E4%BB%8B%E7%9F%B3%28162%E5%9B%9E%2932kbps/7DC9E84555.mp3"
    },
    {
      "name": "106回 - 风云人物蒋介石",
      "url": "http://www.zgpingshu.com/play/4123/106.html",
      "downloadUrl": "http://ops101.zgpingshu.com/%E7%94%B0%E6%88%98%E4%B9%89/%E9%A3%8E%E4%BA%91%E4%BA%BA%E7%89%A9%E8%92%8B%E4%BB%8B%E7%9F%B3%28162%E5%9B%9E%2932kbps/75D8D6B215.mp3"
    },
    {
      "name": "107回 - 风云人物蒋介石",
      "url": "http://www.zgpingshu.com/play/4123/107.html",
      "downloadUrl": "http://ops101.zgpingshu.com/%E7%94%B0%E6%88%98%E4%B9%89/%E9%A3%8E%E4%BA%91%E4%BA%BA%E7%89%A9%E8%92%8B%E4%BB%8B%E7%9F%B3%28162%E5%9B%9E%2932kbps/E752A2A418.mp3"
    },
    {
      "name": "108回 - 风云人物蒋介石",
      "url": "http://www.zgpingshu.com/play/4123/108.html",
      "downloadUrl": "http://ops101.zgpingshu.com/%E7%94%B0%E6%88%98%E4%B9%89/%E9%A3%8E%E4%BA%91%E4%BA%BA%E7%89%A9%E8%92%8B%E4%BB%8B%E7%9F%B3%28162%E5%9B%9E%2932kbps/0F7A6A4B0B.mp3"
    },
    {
      "name": "109回 - 风云人物蒋介石",
      "url": "http://www.zgpingshu.com/play/4123/109.html",
      "downloadUrl": "http://ops101.zgpingshu.com/%E7%94%B0%E6%88%98%E4%B9%89/%E9%A3%8E%E4%BA%91%E4%BA%BA%E7%89%A9%E8%92%8B%E4%BB%8B%E7%9F%B3%28162%E5%9B%9E%2932kbps/E4D0D0C9EB.mp3"
    },
    {
      "name": "110回 - 风云人物蒋介石",
      "url": "http://www.zgpingshu.com/play/4123/110.html",
      "downloadUrl": "http://ops101.zgpingshu.com/%E7%94%B0%E6%88%98%E4%B9%89/%E9%A3%8E%E4%BA%91%E4%BA%BA%E7%89%A9%E8%92%8B%E4%BB%8B%E7%9F%B3%28162%E5%9B%9E%2932kbps/7B31421F3E.mp3"
    },
    {
      "name": "111回 - 风云人物蒋介石",
      "url": "http://www.zgpingshu.com/play/4123/111.html",
      "downloadUrl": "http://ops101.zgpingshu.com/%E7%94%B0%E6%88%98%E4%B9%89/%E9%A3%8E%E4%BA%91%E4%BA%BA%E7%89%A9%E8%92%8B%E4%BB%8B%E7%9F%B3%28162%E5%9B%9E%2932kbps/40947EB309.mp3"
    },
    {
      "name": "112回 - 风云人物蒋介石",
      "url": "http://www.zgpingshu.com/play/4123/112.html",
      "downloadUrl": "http://ops101.zgpingshu.com/%E7%94%B0%E6%88%98%E4%B9%89/%E9%A3%8E%E4%BA%91%E4%BA%BA%E7%89%A9%E8%92%8B%E4%BB%8B%E7%9F%B3%28162%E5%9B%9E%2932kbps/18842718BD.mp3"
    },
    {
      "name": "113回 - 风云人物蒋介石",
      "url": "http://www.zgpingshu.com/play/4123/113.html",
      "downloadUrl": "http://ops101.zgpingshu.com/%E7%94%B0%E6%88%98%E4%B9%89/%E9%A3%8E%E4%BA%91%E4%BA%BA%E7%89%A9%E8%92%8B%E4%BB%8B%E7%9F%B3%28162%E5%9B%9E%2932kbps/8E161DDF03.mp3"
    },
    {
      "name": "114回 - 风云人物蒋介石",
      "url": "http://www.zgpingshu.com/play/4123/114.html",
      "downloadUrl": "http://ops101.zgpingshu.com/%E7%94%B0%E6%88%98%E4%B9%89/%E9%A3%8E%E4%BA%91%E4%BA%BA%E7%89%A9%E8%92%8B%E4%BB%8B%E7%9F%B3%28162%E5%9B%9E%2932kbps/83FE1EF2C3.mp3"
    },
    {
      "name": "115回 - 风云人物蒋介石",
      "url": "http://www.zgpingshu.com/play/4123/115.html",
      "downloadUrl": "http://ops101.zgpingshu.com/%E7%94%B0%E6%88%98%E4%B9%89/%E9%A3%8E%E4%BA%91%E4%BA%BA%E7%89%A9%E8%92%8B%E4%BB%8B%E7%9F%B3%28162%E5%9B%9E%2932kbps/60BC28716B.mp3"
    },
    {
      "name": "116回 - 风云人物蒋介石",
      "url": "http://www.zgpingshu.com/play/4123/116.html",
      "downloadUrl": "http://ops101.zgpingshu.com/%E7%94%B0%E6%88%98%E4%B9%89/%E9%A3%8E%E4%BA%91%E4%BA%BA%E7%89%A9%E8%92%8B%E4%BB%8B%E7%9F%B3%28162%E5%9B%9E%2932kbps/C6F8311E41.mp3"
    },
    {
      "name": "117回 - 风云人物蒋介石",
      "url": "http://www.zgpingshu.com/play/4123/117.html",
      "downloadUrl": "http://ops101.zgpingshu.com/%E7%94%B0%E6%88%98%E4%B9%89/%E9%A3%8E%E4%BA%91%E4%BA%BA%E7%89%A9%E8%92%8B%E4%BB%8B%E7%9F%B3%28162%E5%9B%9E%2932kbps/7E10FE2AA1.mp3"
    },
    {
      "name": "118回 - 风云人物蒋介石",
      "url": "http://www.zgpingshu.com/play/4123/118.html",
      "downloadUrl": "http://ops101.zgpingshu.com/%E7%94%B0%E6%88%98%E4%B9%89/%E9%A3%8E%E4%BA%91%E4%BA%BA%E7%89%A9%E8%92%8B%E4%BB%8B%E7%9F%B3%28162%E5%9B%9E%2932kbps/DDCDCB2054.mp3"
    },
    {
      "name": "119回 - 风云人物蒋介石",
      "url": "http://www.zgpingshu.com/play/4123/119.html",
      "downloadUrl": "http://ops101.zgpingshu.com/%E7%94%B0%E6%88%98%E4%B9%89/%E9%A3%8E%E4%BA%91%E4%BA%BA%E7%89%A9%E8%92%8B%E4%BB%8B%E7%9F%B3%28162%E5%9B%9E%2932kbps/D94D56B815.mp3"
    },
    {
      "name": "120回 - 风云人物蒋介石",
      "url": "http://www.zgpingshu.com/play/4123/120.html",
      "downloadUrl": "http://ops101.zgpingshu.com/%E7%94%B0%E6%88%98%E4%B9%89/%E9%A3%8E%E4%BA%91%E4%BA%BA%E7%89%A9%E8%92%8B%E4%BB%8B%E7%9F%B3%28162%E5%9B%9E%2932kbps/1437DB7C8A.mp3"
    },
    {
      "name": "121回 - 风云人物蒋介石",
      "url": "http://www.zgpingshu.com/play/4123/121.html",
      "downloadUrl": "http://ops101.zgpingshu.com/%E7%94%B0%E6%88%98%E4%B9%89/%E9%A3%8E%E4%BA%91%E4%BA%BA%E7%89%A9%E8%92%8B%E4%BB%8B%E7%9F%B3%28162%E5%9B%9E%2932kbps/2B9E95FD66.mp3"
    },
    {
      "name": "122回 - 风云人物蒋介石",
      "url": "http://www.zgpingshu.com/play/4123/122.html",
      "downloadUrl": "http://ops101.zgpingshu.com/%E7%94%B0%E6%88%98%E4%B9%89/%E9%A3%8E%E4%BA%91%E4%BA%BA%E7%89%A9%E8%92%8B%E4%BB%8B%E7%9F%B3%28162%E5%9B%9E%2932kbps/3814EB1928.mp3"
    },
    {
      "name": "123回 - 风云人物蒋介石",
      "url": "http://www.zgpingshu.com/play/4123/123.html",
      "downloadUrl": "http://ops101.zgpingshu.com/%E7%94%B0%E6%88%98%E4%B9%89/%E9%A3%8E%E4%BA%91%E4%BA%BA%E7%89%A9%E8%92%8B%E4%BB%8B%E7%9F%B3%28162%E5%9B%9E%2932kbps/D0849D6CF9.mp3"
    },
    {
      "name": "124回 - 风云人物蒋介石",
      "url": "http://www.zgpingshu.com/play/4123/124.html",
      "downloadUrl": "http://ops101.zgpingshu.com/%E7%94%B0%E6%88%98%E4%B9%89/%E9%A3%8E%E4%BA%91%E4%BA%BA%E7%89%A9%E8%92%8B%E4%BB%8B%E7%9F%B3%28162%E5%9B%9E%2932kbps/9AB1916FDE.mp3"
    },
    {
      "name": "125回 - 风云人物蒋介石",
      "url": "http://www.zgpingshu.com/play/4123/125.html",
      "downloadUrl": "http://ops101.zgpingshu.com/%E7%94%B0%E6%88%98%E4%B9%89/%E9%A3%8E%E4%BA%91%E4%BA%BA%E7%89%A9%E8%92%8B%E4%BB%8B%E7%9F%B3%28162%E5%9B%9E%2932kbps/F5CEFA7E40.mp3"
    },
    {
      "name": "126回 - 风云人物蒋介石",
      "url": "http://www.zgpingshu.com/play/4123/126.html",
      "downloadUrl": "http://ops101.zgpingshu.com/%E7%94%B0%E6%88%98%E4%B9%89/%E9%A3%8E%E4%BA%91%E4%BA%BA%E7%89%A9%E8%92%8B%E4%BB%8B%E7%9F%B3%28162%E5%9B%9E%2932kbps/FFEDECCB7A.mp3"
    },
    {
      "name": "127回 - 风云人物蒋介石",
      "url": "http://www.zgpingshu.com/play/4123/127.html",
      "downloadUrl": "http://ops101.zgpingshu.com/%E7%94%B0%E6%88%98%E4%B9%89/%E9%A3%8E%E4%BA%91%E4%BA%BA%E7%89%A9%E8%92%8B%E4%BB%8B%E7%9F%B3%28162%E5%9B%9E%2932kbps/F9F0E3461E.mp3"
    },
    {
      "name": "128回 - 风云人物蒋介石",
      "url": "http://www.zgpingshu.com/play/4123/128.html",
      "downloadUrl": "http://ops101.zgpingshu.com/%E7%94%B0%E6%88%98%E4%B9%89/%E9%A3%8E%E4%BA%91%E4%BA%BA%E7%89%A9%E8%92%8B%E4%BB%8B%E7%9F%B3%28162%E5%9B%9E%2932kbps/38EFA37455.mp3"
    },
    {
      "name": "129回 - 风云人物蒋介石",
      "url": "http://www.zgpingshu.com/play/4123/129.html",
      "downloadUrl": "http://ops101.zgpingshu.com/%E7%94%B0%E6%88%98%E4%B9%89/%E9%A3%8E%E4%BA%91%E4%BA%BA%E7%89%A9%E8%92%8B%E4%BB%8B%E7%9F%B3%28162%E5%9B%9E%2932kbps/F117B130E3.mp3"
    },
    {
      "name": "130回 - 风云人物蒋介石",
      "url": "http://www.zgpingshu.com/play/4123/130.html",
      "downloadUrl": "http://ops101.zgpingshu.com/%E7%94%B0%E6%88%98%E4%B9%89/%E9%A3%8E%E4%BA%91%E4%BA%BA%E7%89%A9%E8%92%8B%E4%BB%8B%E7%9F%B3%28162%E5%9B%9E%2932kbps/B983904BD9.mp3"
    },
    {
      "name": "131回 - 风云人物蒋介石",
      "url": "http://www.zgpingshu.com/play/4123/131.html",
      "downloadUrl": "http://ops101.zgpingshu.com/%E7%94%B0%E6%88%98%E4%B9%89/%E9%A3%8E%E4%BA%91%E4%BA%BA%E7%89%A9%E8%92%8B%E4%BB%8B%E7%9F%B3%28162%E5%9B%9E%2932kbps/4EE9474935.mp3"
    },
    {
      "name": "132回 - 风云人物蒋介石",
      "url": "http://www.zgpingshu.com/play/4123/132.html",
      "downloadUrl": "http://ops101.zgpingshu.com/%E7%94%B0%E6%88%98%E4%B9%89/%E9%A3%8E%E4%BA%91%E4%BA%BA%E7%89%A9%E8%92%8B%E4%BB%8B%E7%9F%B3%28162%E5%9B%9E%2932kbps/B8CD9F09CE.mp3"
    },
    {
      "name": "133回 - 风云人物蒋介石",
      "url": "http://www.zgpingshu.com/play/4123/133.html",
      "downloadUrl": "http://ops101.zgpingshu.com/%E7%94%B0%E6%88%98%E4%B9%89/%E9%A3%8E%E4%BA%91%E4%BA%BA%E7%89%A9%E8%92%8B%E4%BB%8B%E7%9F%B3%28162%E5%9B%9E%2932kbps/A57BEC467C.mp3"
    },
    {
      "name": "134回 - 风云人物蒋介石",
      "url": "http://www.zgpingshu.com/play/4123/134.html",
      "downloadUrl": "http://ops101.zgpingshu.com/%E7%94%B0%E6%88%98%E4%B9%89/%E9%A3%8E%E4%BA%91%E4%BA%BA%E7%89%A9%E8%92%8B%E4%BB%8B%E7%9F%B3%28162%E5%9B%9E%2932kbps/099FE16F0A.mp3"
    },
    {
      "name": "135回 - 风云人物蒋介石",
      "url": "http://www.zgpingshu.com/play/4123/135.html",
      "downloadUrl": "http://ops101.zgpingshu.com/%E7%94%B0%E6%88%98%E4%B9%89/%E9%A3%8E%E4%BA%91%E4%BA%BA%E7%89%A9%E8%92%8B%E4%BB%8B%E7%9F%B3%28162%E5%9B%9E%2932kbps/CE7C72F4EC.mp3"
    },
    {
      "name": "136回 - 风云人物蒋介石",
      "url": "http://www.zgpingshu.com/play/4123/136.html",
      "downloadUrl": "http://ops101.zgpingshu.com/%E7%94%B0%E6%88%98%E4%B9%89/%E9%A3%8E%E4%BA%91%E4%BA%BA%E7%89%A9%E8%92%8B%E4%BB%8B%E7%9F%B3%28162%E5%9B%9E%2932kbps/423C017C96.mp3"
    },
    {
      "name": "137回 - 风云人物蒋介石",
      "url": "http://www.zgpingshu.com/play/4123/137.html",
      "downloadUrl": "http://ops101.zgpingshu.com/%E7%94%B0%E6%88%98%E4%B9%89/%E9%A3%8E%E4%BA%91%E4%BA%BA%E7%89%A9%E8%92%8B%E4%BB%8B%E7%9F%B3%28162%E5%9B%9E%2932kbps/793FA8A2BD.mp3"
    },
    {
      "name": "138回 - 风云人物蒋介石",
      "url": "http://www.zgpingshu.com/play/4123/138.html",
      "downloadUrl": "http://ops101.zgpingshu.com/%E7%94%B0%E6%88%98%E4%B9%89/%E9%A3%8E%E4%BA%91%E4%BA%BA%E7%89%A9%E8%92%8B%E4%BB%8B%E7%9F%B3%28162%E5%9B%9E%2932kbps/49C840B05E.mp3"
    },
    {
      "name": "139回 - 风云人物蒋介石",
      "url": "http://www.zgpingshu.com/play/4123/139.html",
      "downloadUrl": "http://ops101.zgpingshu.com/%E7%94%B0%E6%88%98%E4%B9%89/%E9%A3%8E%E4%BA%91%E4%BA%BA%E7%89%A9%E8%92%8B%E4%BB%8B%E7%9F%B3%28162%E5%9B%9E%2932kbps/48DB1EF55A.mp3"
    },
    {
      "name": "140回 - 风云人物蒋介石",
      "url": "http://www.zgpingshu.com/play/4123/140.html",
      "downloadUrl": "http://ops101.zgpingshu.com/%E7%94%B0%E6%88%98%E4%B9%89/%E9%A3%8E%E4%BA%91%E4%BA%BA%E7%89%A9%E8%92%8B%E4%BB%8B%E7%9F%B3%28162%E5%9B%9E%2932kbps/F6EC64D5EC.mp3"
    },
    {
      "name": "141回 - 风云人物蒋介石",
      "url": "http://www.zgpingshu.com/play/4123/141.html",
      "downloadUrl": "http://ops101.zgpingshu.com/%E7%94%B0%E6%88%98%E4%B9%89/%E9%A3%8E%E4%BA%91%E4%BA%BA%E7%89%A9%E8%92%8B%E4%BB%8B%E7%9F%B3%28162%E5%9B%9E%2932kbps/D80B090144.mp3"
    },
    {
      "name": "142回 - 风云人物蒋介石",
      "url": "http://www.zgpingshu.com/play/4123/142.html",
      "downloadUrl": "http://ops101.zgpingshu.com/%E7%94%B0%E6%88%98%E4%B9%89/%E9%A3%8E%E4%BA%91%E4%BA%BA%E7%89%A9%E8%92%8B%E4%BB%8B%E7%9F%B3%28162%E5%9B%9E%2932kbps/C31520C78E.mp3"
    },
    {
      "name": "143回 - 风云人物蒋介石",
      "url": "http://www.zgpingshu.com/play/4123/143.html",
      "downloadUrl": "http://ops101.zgpingshu.com/%E7%94%B0%E6%88%98%E4%B9%89/%E9%A3%8E%E4%BA%91%E4%BA%BA%E7%89%A9%E8%92%8B%E4%BB%8B%E7%9F%B3%28162%E5%9B%9E%2932kbps/A8C2C2F9B5.mp3"
    },
    {
      "name": "144回 - 风云人物蒋介石",
      "url": "http://www.zgpingshu.com/play/4123/144.html",
      "downloadUrl": "http://ops101.zgpingshu.com/%E7%94%B0%E6%88%98%E4%B9%89/%E9%A3%8E%E4%BA%91%E4%BA%BA%E7%89%A9%E8%92%8B%E4%BB%8B%E7%9F%B3%28162%E5%9B%9E%2932kbps/A600191331.mp3"
    },
    { "name": "145回 - 风云人物蒋介石", "url": "http://www.zgpingshu.com/play/4123/145.html", "downloadUrl": "" },
    {
      "name": "146回 - 风云人物蒋介石",
      "url": "http://www.zgpingshu.com/play/4123/146.html",
      "downloadUrl": "http://ops101.zgpingshu.com/%E7%94%B0%E6%88%98%E4%B9%89/%E9%A3%8E%E4%BA%91%E4%BA%BA%E7%89%A9%E8%92%8B%E4%BB%8B%E7%9F%B3%28162%E5%9B%9E%2932kbps/0116497008.mp3"
    },
    {
      "name": "147回 - 风云人物蒋介石",
      "url": "http://www.zgpingshu.com/play/4123/147.html",
      "downloadUrl": "http://ops101.zgpingshu.com/%E7%94%B0%E6%88%98%E4%B9%89/%E9%A3%8E%E4%BA%91%E4%BA%BA%E7%89%A9%E8%92%8B%E4%BB%8B%E7%9F%B3%28162%E5%9B%9E%2932kbps/3D11623052.mp3"
    },
    {
      "name": "148回 - 风云人物蒋介石",
      "url": "http://www.zgpingshu.com/play/4123/148.html",
      "downloadUrl": "http://ops101.zgpingshu.com/%E7%94%B0%E6%88%98%E4%B9%89/%E9%A3%8E%E4%BA%91%E4%BA%BA%E7%89%A9%E8%92%8B%E4%BB%8B%E7%9F%B3%28162%E5%9B%9E%2932kbps/B2D1927FE7.mp3"
    },
    {
      "name": "149回 - 风云人物蒋介石",
      "url": "http://www.zgpingshu.com/play/4123/149.html",
      "downloadUrl": "http://ops101.zgpingshu.com/%E7%94%B0%E6%88%98%E4%B9%89/%E9%A3%8E%E4%BA%91%E4%BA%BA%E7%89%A9%E8%92%8B%E4%BB%8B%E7%9F%B3%28162%E5%9B%9E%2932kbps/C4BBD95AE7.mp3"
    },
    {
      "name": "150回 - 风云人物蒋介石",
      "url": "http://www.zgpingshu.com/play/4123/150.html",
      "downloadUrl": "http://ops101.zgpingshu.com/%E7%94%B0%E6%88%98%E4%B9%89/%E9%A3%8E%E4%BA%91%E4%BA%BA%E7%89%A9%E8%92%8B%E4%BB%8B%E7%9F%B3%28162%E5%9B%9E%2932kbps/ED6F10A18C.mp3"
    },
    {
      "name": "151回 - 风云人物蒋介石",
      "url": "http://www.zgpingshu.com/play/4123/151.html",
      "downloadUrl": "http://ops101.zgpingshu.com/%E7%94%B0%E6%88%98%E4%B9%89/%E9%A3%8E%E4%BA%91%E4%BA%BA%E7%89%A9%E8%92%8B%E4%BB%8B%E7%9F%B3%28162%E5%9B%9E%2932kbps/9093330F53.mp3"
    },
    {
      "name": "152回 - 风云人物蒋介石",
      "url": "http://www.zgpingshu.com/play/4123/152.html",
      "downloadUrl": "http://ops101.zgpingshu.com/%E7%94%B0%E6%88%98%E4%B9%89/%E9%A3%8E%E4%BA%91%E4%BA%BA%E7%89%A9%E8%92%8B%E4%BB%8B%E7%9F%B3%28162%E5%9B%9E%2932kbps/43C87FD571.mp3"
    },
    {
      "name": "153回 - 风云人物蒋介石",
      "url": "http://www.zgpingshu.com/play/4123/153.html",
      "downloadUrl": "http://ops101.zgpingshu.com/%E7%94%B0%E6%88%98%E4%B9%89/%E9%A3%8E%E4%BA%91%E4%BA%BA%E7%89%A9%E8%92%8B%E4%BB%8B%E7%9F%B3%28162%E5%9B%9E%2932kbps/4DCE807346.mp3"
    },
    {
      "name": "154回 - 风云人物蒋介石",
      "url": "http://www.zgpingshu.com/play/4123/154.html",
      "downloadUrl": "http://ops101.zgpingshu.com/%E7%94%B0%E6%88%98%E4%B9%89/%E9%A3%8E%E4%BA%91%E4%BA%BA%E7%89%A9%E8%92%8B%E4%BB%8B%E7%9F%B3%28162%E5%9B%9E%2932kbps/D10718DAFD.mp3"
    },
    {
      "name": "155回 - 风云人物蒋介石",
      "url": "http://www.zgpingshu.com/play/4123/155.html",
      "downloadUrl": "http://ops101.zgpingshu.com/%E7%94%B0%E6%88%98%E4%B9%89/%E9%A3%8E%E4%BA%91%E4%BA%BA%E7%89%A9%E8%92%8B%E4%BB%8B%E7%9F%B3%28162%E5%9B%9E%2932kbps/7D26758B76.mp3"
    },
    {
      "name": "156回 - 风云人物蒋介石",
      "url": "http://www.zgpingshu.com/play/4123/156.html",
      "downloadUrl": "http://ops101.zgpingshu.com/%E7%94%B0%E6%88%98%E4%B9%89/%E9%A3%8E%E4%BA%91%E4%BA%BA%E7%89%A9%E8%92%8B%E4%BB%8B%E7%9F%B3%28162%E5%9B%9E%2932kbps/B451041DF3.mp3"
    },
    {
      "name": "157回 - 风云人物蒋介石",
      "url": "http://www.zgpingshu.com/play/4123/157.html",
      "downloadUrl": "http://ops101.zgpingshu.com/%E7%94%B0%E6%88%98%E4%B9%89/%E9%A3%8E%E4%BA%91%E4%BA%BA%E7%89%A9%E8%92%8B%E4%BB%8B%E7%9F%B3%28162%E5%9B%9E%2932kbps/06FC132060.mp3"
    },
    {
      "name": "158回 - 风云人物蒋介石",
      "url": "http://www.zgpingshu.com/play/4123/158.html",
      "downloadUrl": "http://ops101.zgpingshu.com/%E7%94%B0%E6%88%98%E4%B9%89/%E9%A3%8E%E4%BA%91%E4%BA%BA%E7%89%A9%E8%92%8B%E4%BB%8B%E7%9F%B3%28162%E5%9B%9E%2932kbps/FB437BAB5B.mp3"
    },
    {
      "name": "159回 - 风云人物蒋介石",
      "url": "http://www.zgpingshu.com/play/4123/159.html",
      "downloadUrl": "http://ops101.zgpingshu.com/%E7%94%B0%E6%88%98%E4%B9%89/%E9%A3%8E%E4%BA%91%E4%BA%BA%E7%89%A9%E8%92%8B%E4%BB%8B%E7%9F%B3%28162%E5%9B%9E%2932kbps/A6582C48CB.mp3"
    },
    {
      "name": "160回 - 风云人物蒋介石",
      "url": "http://www.zgpingshu.com/play/4123/160.html",
      "downloadUrl": "http://ops101.zgpingshu.com/%E7%94%B0%E6%88%98%E4%B9%89/%E9%A3%8E%E4%BA%91%E4%BA%BA%E7%89%A9%E8%92%8B%E4%BB%8B%E7%9F%B3%28162%E5%9B%9E%2932kbps/89DE53E86E.mp3"
    },
    {
      "name": "161回 - 风云人物蒋介石",
      "url": "http://www.zgpingshu.com/play/4123/161.html",
      "downloadUrl": "http://ops101.zgpingshu.com/%E7%94%B0%E6%88%98%E4%B9%89/%E9%A3%8E%E4%BA%91%E4%BA%BA%E7%89%A9%E8%92%8B%E4%BB%8B%E7%9F%B3%28162%E5%9B%9E%2932kbps/8FF8F479C7.mp3"
    },
    {
      "name": "162回 - 风云人物蒋介石",
      "url": "http://www.zgpingshu.com/play/4123/162.html",
      "downloadUrl": "http://ops101.zgpingshu.com/%E7%94%B0%E6%88%98%E4%B9%89/%E9%A3%8E%E4%BA%91%E4%BA%BA%E7%89%A9%E8%92%8B%E4%BB%8B%E7%9F%B3%28162%E5%9B%9E%2932kbps/76CCCE5DE2.mp3"
    }
  ]
}
