{
  "name": "中国帝王史话之汉朝帝王史话",
  "author": "sunyi",
  "url": "http://sunyi.zgpingshu.com/2853/",
  "chapters": [
    {
      "name": "01回 - 中国帝王史话之汉朝帝王史话",
      "url": "http://www.zgpingshu.com/play/2853/",
      "downloadUrl": "http://osunyi1.zgpingshu.com/%E4%B8%AD%E5%9B%BD%E5%B8%9D%E7%8E%8B%E5%8F%B2%E8%AF%9D%E4%B9%8B%E6%B1%89%E6%9C%9D%E5%B8%9D%E7%8E%8B%E5%8F%B2%E8%AF%9D%2836%E5%9B%9E%2932kbps/A03300C82C.mp3"
    },
    {
      "name": "02回 - 中国帝王史话之汉朝帝王史话",
      "url": "http://www.zgpingshu.com/play/2853/2.html",
      "downloadUrl": "http://osunyi1.zgpingshu.com/%E4%B8%AD%E5%9B%BD%E5%B8%9D%E7%8E%8B%E5%8F%B2%E8%AF%9D%E4%B9%8B%E6%B1%89%E6%9C%9D%E5%B8%9D%E7%8E%8B%E5%8F%B2%E8%AF%9D%2836%E5%9B%9E%2932kbps/292F6AEF8E.mp3"
    },
    {
      "name": "03回 - 中国帝王史话之汉朝帝王史话",
      "url": "http://www.zgpingshu.com/play/2853/3.html",
      "downloadUrl": "http://osunyi1.zgpingshu.com/%E4%B8%AD%E5%9B%BD%E5%B8%9D%E7%8E%8B%E5%8F%B2%E8%AF%9D%E4%B9%8B%E6%B1%89%E6%9C%9D%E5%B8%9D%E7%8E%8B%E5%8F%B2%E8%AF%9D%2836%E5%9B%9E%2932kbps/816B11CA0E.mp3"
    },
    {
      "name": "04回 - 中国帝王史话之汉朝帝王史话",
      "url": "http://www.zgpingshu.com/play/2853/4.html",
      "downloadUrl": ""
    },
    {
      "name": "05回 - 中国帝王史话之汉朝帝王史话",
      "url": "http://www.zgpingshu.com/play/2853/5.html",
      "downloadUrl": ""
    },
    {
      "name": "06回 - 中国帝王史话之汉朝帝王史话",
      "url": "http://www.zgpingshu.com/play/2853/6.html",
      "downloadUrl": "http://osunyi1.zgpingshu.com/%E4%B8%AD%E5%9B%BD%E5%B8%9D%E7%8E%8B%E5%8F%B2%E8%AF%9D%E4%B9%8B%E6%B1%89%E6%9C%9D%E5%B8%9D%E7%8E%8B%E5%8F%B2%E8%AF%9D%2836%E5%9B%9E%2932kbps/03D6154327.mp3"
    },
    {
      "name": "07回 - 中国帝王史话之汉朝帝王史话",
      "url": "http://www.zgpingshu.com/play/2853/7.html",
      "downloadUrl": "http://osunyi1.zgpingshu.com/%E4%B8%AD%E5%9B%BD%E5%B8%9D%E7%8E%8B%E5%8F%B2%E8%AF%9D%E4%B9%8B%E6%B1%89%E6%9C%9D%E5%B8%9D%E7%8E%8B%E5%8F%B2%E8%AF%9D%2836%E5%9B%9E%2932kbps/63314FF8A5.mp3"
    },
    {
      "name": "08回 - 中国帝王史话之汉朝帝王史话",
      "url": "http://www.zgpingshu.com/play/2853/8.html",
      "downloadUrl": "http://osunyi1.zgpingshu.com/%E4%B8%AD%E5%9B%BD%E5%B8%9D%E7%8E%8B%E5%8F%B2%E8%AF%9D%E4%B9%8B%E6%B1%89%E6%9C%9D%E5%B8%9D%E7%8E%8B%E5%8F%B2%E8%AF%9D%2836%E5%9B%9E%2932kbps/FDC1EDF63A.mp3"
    },
    {
      "name": "09回 - 中国帝王史话之汉朝帝王史话",
      "url": "http://www.zgpingshu.com/play/2853/9.html",
      "downloadUrl": "http://osunyi1.zgpingshu.com/%E4%B8%AD%E5%9B%BD%E5%B8%9D%E7%8E%8B%E5%8F%B2%E8%AF%9D%E4%B9%8B%E6%B1%89%E6%9C%9D%E5%B8%9D%E7%8E%8B%E5%8F%B2%E8%AF%9D%2836%E5%9B%9E%2932kbps/71B1607C19.mp3"
    },
    {
      "name": "10回 - 中国帝王史话之汉朝帝王史话",
      "url": "http://www.zgpingshu.com/play/2853/10.html",
      "downloadUrl": "http://osunyi1.zgpingshu.com/%E4%B8%AD%E5%9B%BD%E5%B8%9D%E7%8E%8B%E5%8F%B2%E8%AF%9D%E4%B9%8B%E6%B1%89%E6%9C%9D%E5%B8%9D%E7%8E%8B%E5%8F%B2%E8%AF%9D%2836%E5%9B%9E%2932kbps/60FEB61DE2.mp3"
    },
    {
      "name": "11回 - 中国帝王史话之汉朝帝王史话",
      "url": "http://www.zgpingshu.com/play/2853/11.html",
      "downloadUrl": "http://osunyi1.zgpingshu.com/%E4%B8%AD%E5%9B%BD%E5%B8%9D%E7%8E%8B%E5%8F%B2%E8%AF%9D%E4%B9%8B%E6%B1%89%E6%9C%9D%E5%B8%9D%E7%8E%8B%E5%8F%B2%E8%AF%9D%2836%E5%9B%9E%2932kbps/83B852FBCE.mp3"
    },
    {
      "name": "12回 - 中国帝王史话之汉朝帝王史话",
      "url": "http://www.zgpingshu.com/play/2853/12.html",
      "downloadUrl": "http://osunyi1.zgpingshu.com/%E4%B8%AD%E5%9B%BD%E5%B8%9D%E7%8E%8B%E5%8F%B2%E8%AF%9D%E4%B9%8B%E6%B1%89%E6%9C%9D%E5%B8%9D%E7%8E%8B%E5%8F%B2%E8%AF%9D%2836%E5%9B%9E%2932kbps/F8861DA255.mp3"
    },
    {
      "name": "13回 - 中国帝王史话之汉朝帝王史话",
      "url": "http://www.zgpingshu.com/play/2853/13.html",
      "downloadUrl": "http://osunyi1.zgpingshu.com/%E4%B8%AD%E5%9B%BD%E5%B8%9D%E7%8E%8B%E5%8F%B2%E8%AF%9D%E4%B9%8B%E6%B1%89%E6%9C%9D%E5%B8%9D%E7%8E%8B%E5%8F%B2%E8%AF%9D%2836%E5%9B%9E%2932kbps/F83E9BD9F0.mp3"
    },
    {
      "name": "14回 - 中国帝王史话之汉朝帝王史话",
      "url": "http://www.zgpingshu.com/play/2853/14.html",
      "downloadUrl": "http://osunyi1.zgpingshu.com/%E4%B8%AD%E5%9B%BD%E5%B8%9D%E7%8E%8B%E5%8F%B2%E8%AF%9D%E4%B9%8B%E6%B1%89%E6%9C%9D%E5%B8%9D%E7%8E%8B%E5%8F%B2%E8%AF%9D%2836%E5%9B%9E%2932kbps/ECC362869E.mp3"
    },
    {
      "name": "15回 - 中国帝王史话之汉朝帝王史话",
      "url": "http://www.zgpingshu.com/play/2853/15.html",
      "downloadUrl": "http://osunyi1.zgpingshu.com/%E4%B8%AD%E5%9B%BD%E5%B8%9D%E7%8E%8B%E5%8F%B2%E8%AF%9D%E4%B9%8B%E6%B1%89%E6%9C%9D%E5%B8%9D%E7%8E%8B%E5%8F%B2%E8%AF%9D%2836%E5%9B%9E%2932kbps/9FB1A5586C.mp3"
    },
    {
      "name": "16回 - 中国帝王史话之汉朝帝王史话",
      "url": "http://www.zgpingshu.com/play/2853/16.html",
      "downloadUrl": "http://osunyi1.zgpingshu.com/%E4%B8%AD%E5%9B%BD%E5%B8%9D%E7%8E%8B%E5%8F%B2%E8%AF%9D%E4%B9%8B%E6%B1%89%E6%9C%9D%E5%B8%9D%E7%8E%8B%E5%8F%B2%E8%AF%9D%2836%E5%9B%9E%2932kbps/968242865E.mp3"
    },
    {
      "name": "17回 - 中国帝王史话之汉朝帝王史话",
      "url": "http://www.zgpingshu.com/play/2853/17.html",
      "downloadUrl": "http://osunyi1.zgpingshu.com/%E4%B8%AD%E5%9B%BD%E5%B8%9D%E7%8E%8B%E5%8F%B2%E8%AF%9D%E4%B9%8B%E6%B1%89%E6%9C%9D%E5%B8%9D%E7%8E%8B%E5%8F%B2%E8%AF%9D%2836%E5%9B%9E%2932kbps/770D3BAAD2.mp3"
    },
    {
      "name": "18回 - 中国帝王史话之汉朝帝王史话",
      "url": "http://www.zgpingshu.com/play/2853/18.html",
      "downloadUrl": "http://osunyi1.zgpingshu.com/%E4%B8%AD%E5%9B%BD%E5%B8%9D%E7%8E%8B%E5%8F%B2%E8%AF%9D%E4%B9%8B%E6%B1%89%E6%9C%9D%E5%B8%9D%E7%8E%8B%E5%8F%B2%E8%AF%9D%2836%E5%9B%9E%2932kbps/68C1B9CD51.mp3"
    },
    {
      "name": "19回 - 中国帝王史话之汉朝帝王史话",
      "url": "http://www.zgpingshu.com/play/2853/19.html",
      "downloadUrl": "http://osunyi1.zgpingshu.com/%E4%B8%AD%E5%9B%BD%E5%B8%9D%E7%8E%8B%E5%8F%B2%E8%AF%9D%E4%B9%8B%E6%B1%89%E6%9C%9D%E5%B8%9D%E7%8E%8B%E5%8F%B2%E8%AF%9D%2836%E5%9B%9E%2932kbps/CF9168A483.mp3"
    },
    {
      "name": "20回 - 中国帝王史话之汉朝帝王史话",
      "url": "http://www.zgpingshu.com/play/2853/20.html",
      "downloadUrl": "http://osunyi1.zgpingshu.com/%E4%B8%AD%E5%9B%BD%E5%B8%9D%E7%8E%8B%E5%8F%B2%E8%AF%9D%E4%B9%8B%E6%B1%89%E6%9C%9D%E5%B8%9D%E7%8E%8B%E5%8F%B2%E8%AF%9D%2836%E5%9B%9E%2932kbps/6EDEDEED62.mp3"
    },
    {
      "name": "21回 - 中国帝王史话之汉朝帝王史话",
      "url": "http://www.zgpingshu.com/play/2853/21.html",
      "downloadUrl": "http://osunyi1.zgpingshu.com/%E4%B8%AD%E5%9B%BD%E5%B8%9D%E7%8E%8B%E5%8F%B2%E8%AF%9D%E4%B9%8B%E6%B1%89%E6%9C%9D%E5%B8%9D%E7%8E%8B%E5%8F%B2%E8%AF%9D%2836%E5%9B%9E%2932kbps/769B342BEE.mp3"
    },
    {
      "name": "22回 - 中国帝王史话之汉朝帝王史话",
      "url": "http://www.zgpingshu.com/play/2853/22.html",
      "downloadUrl": "http://osunyi1.zgpingshu.com/%E4%B8%AD%E5%9B%BD%E5%B8%9D%E7%8E%8B%E5%8F%B2%E8%AF%9D%E4%B9%8B%E6%B1%89%E6%9C%9D%E5%B8%9D%E7%8E%8B%E5%8F%B2%E8%AF%9D%2836%E5%9B%9E%2932kbps/B804DF3520.mp3"
    },
    {
      "name": "23回 - 中国帝王史话之汉朝帝王史话",
      "url": "http://www.zgpingshu.com/play/2853/23.html",
      "downloadUrl": "http://osunyi1.zgpingshu.com/%E4%B8%AD%E5%9B%BD%E5%B8%9D%E7%8E%8B%E5%8F%B2%E8%AF%9D%E4%B9%8B%E6%B1%89%E6%9C%9D%E5%B8%9D%E7%8E%8B%E5%8F%B2%E8%AF%9D%2836%E5%9B%9E%2932kbps/84AA5A6474.mp3"
    },
    {
      "name": "24回 - 中国帝王史话之汉朝帝王史话",
      "url": "http://www.zgpingshu.com/play/2853/24.html",
      "downloadUrl": "http://osunyi1.zgpingshu.com/%E4%B8%AD%E5%9B%BD%E5%B8%9D%E7%8E%8B%E5%8F%B2%E8%AF%9D%E4%B9%8B%E6%B1%89%E6%9C%9D%E5%B8%9D%E7%8E%8B%E5%8F%B2%E8%AF%9D%2836%E5%9B%9E%2932kbps/3EC32F6B01.mp3"
    },
    {
      "name": "25回 - 中国帝王史话之汉朝帝王史话",
      "url": "http://www.zgpingshu.com/play/2853/25.html",
      "downloadUrl": "http://osunyi1.zgpingshu.com/%E4%B8%AD%E5%9B%BD%E5%B8%9D%E7%8E%8B%E5%8F%B2%E8%AF%9D%E4%B9%8B%E6%B1%89%E6%9C%9D%E5%B8%9D%E7%8E%8B%E5%8F%B2%E8%AF%9D%2836%E5%9B%9E%2932kbps/E1C9C0349D.mp3"
    },
    {
      "name": "26回 - 中国帝王史话之汉朝帝王史话",
      "url": "http://www.zgpingshu.com/play/2853/26.html",
      "downloadUrl": "http://osunyi1.zgpingshu.com/%E4%B8%AD%E5%9B%BD%E5%B8%9D%E7%8E%8B%E5%8F%B2%E8%AF%9D%E4%B9%8B%E6%B1%89%E6%9C%9D%E5%B8%9D%E7%8E%8B%E5%8F%B2%E8%AF%9D%2836%E5%9B%9E%2932kbps/9D83005DB7.mp3"
    },
    {
      "name": "27回 - 中国帝王史话之汉朝帝王史话",
      "url": "http://www.zgpingshu.com/play/2853/27.html",
      "downloadUrl": "http://osunyi1.zgpingshu.com/%E4%B8%AD%E5%9B%BD%E5%B8%9D%E7%8E%8B%E5%8F%B2%E8%AF%9D%E4%B9%8B%E6%B1%89%E6%9C%9D%E5%B8%9D%E7%8E%8B%E5%8F%B2%E8%AF%9D%2836%E5%9B%9E%2932kbps/4EF0FFEDE5.mp3"
    },
    {
      "name": "28回 - 中国帝王史话之汉朝帝王史话",
      "url": "http://www.zgpingshu.com/play/2853/28.html",
      "downloadUrl": "http://osunyi1.zgpingshu.com/%E4%B8%AD%E5%9B%BD%E5%B8%9D%E7%8E%8B%E5%8F%B2%E8%AF%9D%E4%B9%8B%E6%B1%89%E6%9C%9D%E5%B8%9D%E7%8E%8B%E5%8F%B2%E8%AF%9D%2836%E5%9B%9E%2932kbps/E7CBA26C3C.mp3"
    },
    {
      "name": "29回 - 中国帝王史话之汉朝帝王史话",
      "url": "http://www.zgpingshu.com/play/2853/29.html",
      "downloadUrl": "http://osunyi1.zgpingshu.com/%E4%B8%AD%E5%9B%BD%E5%B8%9D%E7%8E%8B%E5%8F%B2%E8%AF%9D%E4%B9%8B%E6%B1%89%E6%9C%9D%E5%B8%9D%E7%8E%8B%E5%8F%B2%E8%AF%9D%2836%E5%9B%9E%2932kbps/4A34ECFA4A.mp3"
    },
    {
      "name": "30回 - 中国帝王史话之汉朝帝王史话",
      "url": "http://www.zgpingshu.com/play/2853/30.html",
      "downloadUrl": "http://osunyi1.zgpingshu.com/%E4%B8%AD%E5%9B%BD%E5%B8%9D%E7%8E%8B%E5%8F%B2%E8%AF%9D%E4%B9%8B%E6%B1%89%E6%9C%9D%E5%B8%9D%E7%8E%8B%E5%8F%B2%E8%AF%9D%2836%E5%9B%9E%2932kbps/7FBCAB829F.mp3"
    },
    {
      "name": "31回 - 中国帝王史话之汉朝帝王史话",
      "url": "http://www.zgpingshu.com/play/2853/31.html",
      "downloadUrl": "http://osunyi1.zgpingshu.com/%E4%B8%AD%E5%9B%BD%E5%B8%9D%E7%8E%8B%E5%8F%B2%E8%AF%9D%E4%B9%8B%E6%B1%89%E6%9C%9D%E5%B8%9D%E7%8E%8B%E5%8F%B2%E8%AF%9D%2836%E5%9B%9E%2932kbps/948A87EF69.mp3"
    },
    {
      "name": "32回 - 中国帝王史话之汉朝帝王史话",
      "url": "http://www.zgpingshu.com/play/2853/32.html",
      "downloadUrl": "http://osunyi1.zgpingshu.com/%E4%B8%AD%E5%9B%BD%E5%B8%9D%E7%8E%8B%E5%8F%B2%E8%AF%9D%E4%B9%8B%E6%B1%89%E6%9C%9D%E5%B8%9D%E7%8E%8B%E5%8F%B2%E8%AF%9D%2836%E5%9B%9E%2932kbps/329E3F765E.mp3"
    },
    {
      "name": "33回 - 中国帝王史话之汉朝帝王史话",
      "url": "http://www.zgpingshu.com/play/2853/33.html",
      "downloadUrl": "http://osunyi1.zgpingshu.com/%E4%B8%AD%E5%9B%BD%E5%B8%9D%E7%8E%8B%E5%8F%B2%E8%AF%9D%E4%B9%8B%E6%B1%89%E6%9C%9D%E5%B8%9D%E7%8E%8B%E5%8F%B2%E8%AF%9D%2836%E5%9B%9E%2932kbps/910A6B2A89.mp3"
    },
    {
      "name": "34回 - 中国帝王史话之汉朝帝王史话",
      "url": "http://www.zgpingshu.com/play/2853/34.html",
      "downloadUrl": "http://osunyi1.zgpingshu.com/%E4%B8%AD%E5%9B%BD%E5%B8%9D%E7%8E%8B%E5%8F%B2%E8%AF%9D%E4%B9%8B%E6%B1%89%E6%9C%9D%E5%B8%9D%E7%8E%8B%E5%8F%B2%E8%AF%9D%2836%E5%9B%9E%2932kbps/4A11DAE5A7.mp3"
    },
    {
      "name": "35回 - 中国帝王史话之汉朝帝王史话",
      "url": "http://www.zgpingshu.com/play/2853/35.html",
      "downloadUrl": "http://osunyi1.zgpingshu.com/%E4%B8%AD%E5%9B%BD%E5%B8%9D%E7%8E%8B%E5%8F%B2%E8%AF%9D%E4%B9%8B%E6%B1%89%E6%9C%9D%E5%B8%9D%E7%8E%8B%E5%8F%B2%E8%AF%9D%2836%E5%9B%9E%2932kbps/49E93E2E56.mp3"
    },
    {
      "name": "36回 - 中国帝王史话之汉朝帝王史话",
      "url": "http://www.zgpingshu.com/play/2853/36.html",
      "downloadUrl": "http://osunyi1.zgpingshu.com/%E4%B8%AD%E5%9B%BD%E5%B8%9D%E7%8E%8B%E5%8F%B2%E8%AF%9D%E4%B9%8B%E6%B1%89%E6%9C%9D%E5%B8%9D%E7%8E%8B%E5%8F%B2%E8%AF%9D%2836%E5%9B%9E%2932kbps/35ABBE0A2A.mp3"
    }
  ]
}
