{"name":"话清史之孝庄真相大揭秘","author":"jilianhai","url":"http://bjjt.zgpingshu.com/3036/","chapters":[{"name":"1集 - 话清史之孝庄真相大揭秘","url":"http://www.zgpingshu.com/play/3036/","downloadUrl":"http://objjt1.zgpingshu.com/%E8%AF%9D%E6%B8%85%E5%8F%B2%E4%B9%8B%E5%AD%9D%E5%BA%84%E7%9C%9F%E7%9B%B8%E5%A4%A7%E6%8F%AD%E7%A7%98%282%E9%9B%86%2932kbps/51F31A3BCA.mp3"},{"name":"2集 - 话清史之孝庄真相大揭秘","url":"http://www.zgpingshu.com/play/3036/2.html","downloadUrl":"http://objjt1.zgpingshu.com/%E8%AF%9D%E6%B8%85%E5%8F%B2%E4%B9%8B%E5%AD%9D%E5%BA%84%E7%9C%9F%E7%9B%B8%E5%A4%A7%E6%8F%AD%E7%A7%98%282%E9%9B%86%2932kbps/9CD431E2F1.mp3"}]}
