{
  "name": "红色间谍",
  "author": "zhangshaozuo",
  "url": "http://zhangshaozuo.zgpingshu.com/5282/",
  "chapters": [
    {
      "name": "001回 - 红色间谍",
      "url": "http://www.zgpingshu.com/play/5282/",
      "downloadUrl": "http://ops81.zgpingshu.com/%E5%BC%A0%E5%B0%91%E4%BD%90/%E7%BA%A2%E8%89%B2%E9%97%B4%E8%B0%8D%2850%E5%9B%9E%29%28%E6%BC%94%E6%92%AD-%E5%BC%A0%E5%B0%91%E4%BD%90%29%2832kb%29/5F64F4F12B.mp3"
    },
    {
      "name": "002回 - 红色间谍",
      "url": "http://www.zgpingshu.com/play/5282/2.html",
      "downloadUrl": "http://ops81.zgpingshu.com/%E5%BC%A0%E5%B0%91%E4%BD%90/%E7%BA%A2%E8%89%B2%E9%97%B4%E8%B0%8D%2850%E5%9B%9E%29%28%E6%BC%94%E6%92%AD-%E5%BC%A0%E5%B0%91%E4%BD%90%29%2832kb%29/79245622CE.mp3"
    },
    {
      "name": "003回 - 红色间谍",
      "url": "http://www.zgpingshu.com/play/5282/3.html",
      "downloadUrl": "http://ops81.zgpingshu.com/%E5%BC%A0%E5%B0%91%E4%BD%90/%E7%BA%A2%E8%89%B2%E9%97%B4%E8%B0%8D%2850%E5%9B%9E%29%28%E6%BC%94%E6%92%AD-%E5%BC%A0%E5%B0%91%E4%BD%90%29%2832kb%29/18F8026D76.mp3"
    },
    {
      "name": "004回 - 红色间谍",
      "url": "http://www.zgpingshu.com/play/5282/4.html",
      "downloadUrl": "http://ops81.zgpingshu.com/%E5%BC%A0%E5%B0%91%E4%BD%90/%E7%BA%A2%E8%89%B2%E9%97%B4%E8%B0%8D%2850%E5%9B%9E%29%28%E6%BC%94%E6%92%AD-%E5%BC%A0%E5%B0%91%E4%BD%90%29%2832kb%29/2CD6973936.mp3"
    },
    {
      "name": "005回 - 红色间谍",
      "url": "http://www.zgpingshu.com/play/5282/5.html",
      "downloadUrl": "http://ops81.zgpingshu.com/%E5%BC%A0%E5%B0%91%E4%BD%90/%E7%BA%A2%E8%89%B2%E9%97%B4%E8%B0%8D%2850%E5%9B%9E%29%28%E6%BC%94%E6%92%AD-%E5%BC%A0%E5%B0%91%E4%BD%90%29%2832kb%29/5CCCF75F70.mp3"
    },
    {
      "name": "006回 - 红色间谍",
      "url": "http://www.zgpingshu.com/play/5282/6.html",
      "downloadUrl": "http://ops81.zgpingshu.com/%E5%BC%A0%E5%B0%91%E4%BD%90/%E7%BA%A2%E8%89%B2%E9%97%B4%E8%B0%8D%2850%E5%9B%9E%29%28%E6%BC%94%E6%92%AD-%E5%BC%A0%E5%B0%91%E4%BD%90%29%2832kb%29/DFF50F358C.mp3"
    },
    {
      "name": "007回 - 红色间谍",
      "url": "http://www.zgpingshu.com/play/5282/7.html",
      "downloadUrl": "http://ops81.zgpingshu.com/%E5%BC%A0%E5%B0%91%E4%BD%90/%E7%BA%A2%E8%89%B2%E9%97%B4%E8%B0%8D%2850%E5%9B%9E%29%28%E6%BC%94%E6%92%AD-%E5%BC%A0%E5%B0%91%E4%BD%90%29%2832kb%29/87F81571EF.mp3"
    },
    {
      "name": "008回 - 红色间谍",
      "url": "http://www.zgpingshu.com/play/5282/8.html",
      "downloadUrl": "http://ops81.zgpingshu.com/%E5%BC%A0%E5%B0%91%E4%BD%90/%E7%BA%A2%E8%89%B2%E9%97%B4%E8%B0%8D%2850%E5%9B%9E%29%28%E6%BC%94%E6%92%AD-%E5%BC%A0%E5%B0%91%E4%BD%90%29%2832kb%29/A4F294B4D5.mp3"
    },
    {
      "name": "009回 - 红色间谍",
      "url": "http://www.zgpingshu.com/play/5282/9.html",
      "downloadUrl": "http://ops81.zgpingshu.com/%E5%BC%A0%E5%B0%91%E4%BD%90/%E7%BA%A2%E8%89%B2%E9%97%B4%E8%B0%8D%2850%E5%9B%9E%29%28%E6%BC%94%E6%92%AD-%E5%BC%A0%E5%B0%91%E4%BD%90%29%2832kb%29/FD232041F0.mp3"
    },
    {
      "name": "010回 - 红色间谍",
      "url": "http://www.zgpingshu.com/play/5282/10.html",
      "downloadUrl": "http://ops81.zgpingshu.com/%E5%BC%A0%E5%B0%91%E4%BD%90/%E7%BA%A2%E8%89%B2%E9%97%B4%E8%B0%8D%2850%E5%9B%9E%29%28%E6%BC%94%E6%92%AD-%E5%BC%A0%E5%B0%91%E4%BD%90%29%2832kb%29/9BC35D8307.mp3"
    },
    {
      "name": "011回 - 红色间谍",
      "url": "http://www.zgpingshu.com/play/5282/11.html",
      "downloadUrl": "http://ops81.zgpingshu.com/%E5%BC%A0%E5%B0%91%E4%BD%90/%E7%BA%A2%E8%89%B2%E9%97%B4%E8%B0%8D%2850%E5%9B%9E%29%28%E6%BC%94%E6%92%AD-%E5%BC%A0%E5%B0%91%E4%BD%90%29%2832kb%29/5EF3D66796.mp3"
    },
    {
      "name": "012回 - 红色间谍",
      "url": "http://www.zgpingshu.com/play/5282/12.html",
      "downloadUrl": "http://ops81.zgpingshu.com/%E5%BC%A0%E5%B0%91%E4%BD%90/%E7%BA%A2%E8%89%B2%E9%97%B4%E8%B0%8D%2850%E5%9B%9E%29%28%E6%BC%94%E6%92%AD-%E5%BC%A0%E5%B0%91%E4%BD%90%29%2832kb%29/1E1972732D.mp3"
    },
    {
      "name": "013回 - 红色间谍",
      "url": "http://www.zgpingshu.com/play/5282/13.html",
      "downloadUrl": "http://ops81.zgpingshu.com/%E5%BC%A0%E5%B0%91%E4%BD%90/%E7%BA%A2%E8%89%B2%E9%97%B4%E8%B0%8D%2850%E5%9B%9E%29%28%E6%BC%94%E6%92%AD-%E5%BC%A0%E5%B0%91%E4%BD%90%29%2832kb%29/EA442EA52C.mp3"
    },
    {
      "name": "014回 - 红色间谍",
      "url": "http://www.zgpingshu.com/play/5282/14.html",
      "downloadUrl": "http://ops81.zgpingshu.com/%E5%BC%A0%E5%B0%91%E4%BD%90/%E7%BA%A2%E8%89%B2%E9%97%B4%E8%B0%8D%2850%E5%9B%9E%29%28%E6%BC%94%E6%92%AD-%E5%BC%A0%E5%B0%91%E4%BD%90%29%2832kb%29/F7B4EC3A59.mp3"
    },
    {
      "name": "015回 - 红色间谍",
      "url": "http://www.zgpingshu.com/play/5282/15.html",
      "downloadUrl": "http://ops81.zgpingshu.com/%E5%BC%A0%E5%B0%91%E4%BD%90/%E7%BA%A2%E8%89%B2%E9%97%B4%E8%B0%8D%2850%E5%9B%9E%29%28%E6%BC%94%E6%92%AD-%E5%BC%A0%E5%B0%91%E4%BD%90%29%2832kb%29/46AC2E8494.mp3"
    },
    {
      "name": "016回 - 红色间谍",
      "url": "http://www.zgpingshu.com/play/5282/16.html",
      "downloadUrl": "http://ops81.zgpingshu.com/%E5%BC%A0%E5%B0%91%E4%BD%90/%E7%BA%A2%E8%89%B2%E9%97%B4%E8%B0%8D%2850%E5%9B%9E%29%28%E6%BC%94%E6%92%AD-%E5%BC%A0%E5%B0%91%E4%BD%90%29%2832kb%29/51D306B8A2.mp3"
    },
    {
      "name": "017回 - 红色间谍",
      "url": "http://www.zgpingshu.com/play/5282/17.html",
      "downloadUrl": "http://ops81.zgpingshu.com/%E5%BC%A0%E5%B0%91%E4%BD%90/%E7%BA%A2%E8%89%B2%E9%97%B4%E8%B0%8D%2850%E5%9B%9E%29%28%E6%BC%94%E6%92%AD-%E5%BC%A0%E5%B0%91%E4%BD%90%29%2832kb%29/63665134A0.mp3"
    },
    {
      "name": "018回 - 红色间谍",
      "url": "http://www.zgpingshu.com/play/5282/18.html",
      "downloadUrl": "http://ops81.zgpingshu.com/%E5%BC%A0%E5%B0%91%E4%BD%90/%E7%BA%A2%E8%89%B2%E9%97%B4%E8%B0%8D%2850%E5%9B%9E%29%28%E6%BC%94%E6%92%AD-%E5%BC%A0%E5%B0%91%E4%BD%90%29%2832kb%29/1D129151AE.mp3"
    },
    {
      "name": "019回 - 红色间谍",
      "url": "http://www.zgpingshu.com/play/5282/19.html",
      "downloadUrl": "http://ops81.zgpingshu.com/%E5%BC%A0%E5%B0%91%E4%BD%90/%E7%BA%A2%E8%89%B2%E9%97%B4%E8%B0%8D%2850%E5%9B%9E%29%28%E6%BC%94%E6%92%AD-%E5%BC%A0%E5%B0%91%E4%BD%90%29%2832kb%29/AE52D43B9E.mp3"
    },
    {
      "name": "020回 - 红色间谍",
      "url": "http://www.zgpingshu.com/play/5282/20.html",
      "downloadUrl": "http://ops81.zgpingshu.com/%E5%BC%A0%E5%B0%91%E4%BD%90/%E7%BA%A2%E8%89%B2%E9%97%B4%E8%B0%8D%2850%E5%9B%9E%29%28%E6%BC%94%E6%92%AD-%E5%BC%A0%E5%B0%91%E4%BD%90%29%2832kb%29/4CEA66DB48.mp3"
    },
    {
      "name": "021回 - 红色间谍",
      "url": "http://www.zgpingshu.com/play/5282/21.html",
      "downloadUrl": "http://ops81.zgpingshu.com/%E5%BC%A0%E5%B0%91%E4%BD%90/%E7%BA%A2%E8%89%B2%E9%97%B4%E8%B0%8D%2850%E5%9B%9E%29%28%E6%BC%94%E6%92%AD-%E5%BC%A0%E5%B0%91%E4%BD%90%29%2832kb%29/4D4E596EEC.mp3"
    },
    {
      "name": "022回 - 红色间谍",
      "url": "http://www.zgpingshu.com/play/5282/22.html",
      "downloadUrl": "http://ops81.zgpingshu.com/%E5%BC%A0%E5%B0%91%E4%BD%90/%E7%BA%A2%E8%89%B2%E9%97%B4%E8%B0%8D%2850%E5%9B%9E%29%28%E6%BC%94%E6%92%AD-%E5%BC%A0%E5%B0%91%E4%BD%90%29%2832kb%29/E8FE39BA9D.mp3"
    },
    {
      "name": "023回 - 红色间谍",
      "url": "http://www.zgpingshu.com/play/5282/23.html",
      "downloadUrl": "http://ops81.zgpingshu.com/%E5%BC%A0%E5%B0%91%E4%BD%90/%E7%BA%A2%E8%89%B2%E9%97%B4%E8%B0%8D%2850%E5%9B%9E%29%28%E6%BC%94%E6%92%AD-%E5%BC%A0%E5%B0%91%E4%BD%90%29%2832kb%29/BCE0BE2721.mp3"
    },
    {
      "name": "024回 - 红色间谍",
      "url": "http://www.zgpingshu.com/play/5282/24.html",
      "downloadUrl": "http://ops81.zgpingshu.com/%E5%BC%A0%E5%B0%91%E4%BD%90/%E7%BA%A2%E8%89%B2%E9%97%B4%E8%B0%8D%2850%E5%9B%9E%29%28%E6%BC%94%E6%92%AD-%E5%BC%A0%E5%B0%91%E4%BD%90%29%2832kb%29/C5F41EC719.mp3"
    },
    {
      "name": "025回 - 红色间谍",
      "url": "http://www.zgpingshu.com/play/5282/25.html",
      "downloadUrl": "http://ops81.zgpingshu.com/%E5%BC%A0%E5%B0%91%E4%BD%90/%E7%BA%A2%E8%89%B2%E9%97%B4%E8%B0%8D%2850%E5%9B%9E%29%28%E6%BC%94%E6%92%AD-%E5%BC%A0%E5%B0%91%E4%BD%90%29%2832kb%29/A67ECF69B9.mp3"
    },
    {
      "name": "026回 - 红色间谍",
      "url": "http://www.zgpingshu.com/play/5282/26.html",
      "downloadUrl": "http://ops81.zgpingshu.com/%E5%BC%A0%E5%B0%91%E4%BD%90/%E7%BA%A2%E8%89%B2%E9%97%B4%E8%B0%8D%2850%E5%9B%9E%29%28%E6%BC%94%E6%92%AD-%E5%BC%A0%E5%B0%91%E4%BD%90%29%2832kb%29/D272CEFB6D.mp3"
    },
    {
      "name": "027回 - 红色间谍",
      "url": "http://www.zgpingshu.com/play/5282/27.html",
      "downloadUrl": "http://ops81.zgpingshu.com/%E5%BC%A0%E5%B0%91%E4%BD%90/%E7%BA%A2%E8%89%B2%E9%97%B4%E8%B0%8D%2850%E5%9B%9E%29%28%E6%BC%94%E6%92%AD-%E5%BC%A0%E5%B0%91%E4%BD%90%29%2832kb%29/1695C5C03B.mp3"
    },
    {
      "name": "028回 - 红色间谍",
      "url": "http://www.zgpingshu.com/play/5282/28.html",
      "downloadUrl": "http://ops81.zgpingshu.com/%E5%BC%A0%E5%B0%91%E4%BD%90/%E7%BA%A2%E8%89%B2%E9%97%B4%E8%B0%8D%2850%E5%9B%9E%29%28%E6%BC%94%E6%92%AD-%E5%BC%A0%E5%B0%91%E4%BD%90%29%2832kb%29/58FD34C8DB.mp3"
    },
    {
      "name": "029回 - 红色间谍",
      "url": "http://www.zgpingshu.com/play/5282/29.html",
      "downloadUrl": "http://ops81.zgpingshu.com/%E5%BC%A0%E5%B0%91%E4%BD%90/%E7%BA%A2%E8%89%B2%E9%97%B4%E8%B0%8D%2850%E5%9B%9E%29%28%E6%BC%94%E6%92%AD-%E5%BC%A0%E5%B0%91%E4%BD%90%29%2832kb%29/B13962F7C1.mp3"
    },
    {
      "name": "030回 - 红色间谍",
      "url": "http://www.zgpingshu.com/play/5282/30.html",
      "downloadUrl": "http://ops81.zgpingshu.com/%E5%BC%A0%E5%B0%91%E4%BD%90/%E7%BA%A2%E8%89%B2%E9%97%B4%E8%B0%8D%2850%E5%9B%9E%29%28%E6%BC%94%E6%92%AD-%E5%BC%A0%E5%B0%91%E4%BD%90%29%2832kb%29/F76A9978CD.mp3"
    },
    {
      "name": "031回 - 红色间谍",
      "url": "http://www.zgpingshu.com/play/5282/31.html",
      "downloadUrl": "http://ops81.zgpingshu.com/%E5%BC%A0%E5%B0%91%E4%BD%90/%E7%BA%A2%E8%89%B2%E9%97%B4%E8%B0%8D%2850%E5%9B%9E%29%28%E6%BC%94%E6%92%AD-%E5%BC%A0%E5%B0%91%E4%BD%90%29%2832kb%29/AB7A081EFF.mp3"
    },
    {
      "name": "032回 - 红色间谍",
      "url": "http://www.zgpingshu.com/play/5282/32.html",
      "downloadUrl": "http://ops81.zgpingshu.com/%E5%BC%A0%E5%B0%91%E4%BD%90/%E7%BA%A2%E8%89%B2%E9%97%B4%E8%B0%8D%2850%E5%9B%9E%29%28%E6%BC%94%E6%92%AD-%E5%BC%A0%E5%B0%91%E4%BD%90%29%2832kb%29/ED15888208.mp3"
    },
    {
      "name": "033回 - 红色间谍",
      "url": "http://www.zgpingshu.com/play/5282/33.html",
      "downloadUrl": "http://ops81.zgpingshu.com/%E5%BC%A0%E5%B0%91%E4%BD%90/%E7%BA%A2%E8%89%B2%E9%97%B4%E8%B0%8D%2850%E5%9B%9E%29%28%E6%BC%94%E6%92%AD-%E5%BC%A0%E5%B0%91%E4%BD%90%29%2832kb%29/7B05CACF4E.mp3"
    },
    {
      "name": "034回 - 红色间谍",
      "url": "http://www.zgpingshu.com/play/5282/34.html",
      "downloadUrl": "http://ops81.zgpingshu.com/%E5%BC%A0%E5%B0%91%E4%BD%90/%E7%BA%A2%E8%89%B2%E9%97%B4%E8%B0%8D%2850%E5%9B%9E%29%28%E6%BC%94%E6%92%AD-%E5%BC%A0%E5%B0%91%E4%BD%90%29%2832kb%29/4B659A8CDB.mp3"
    },
    {
      "name": "035回 - 红色间谍",
      "url": "http://www.zgpingshu.com/play/5282/35.html",
      "downloadUrl": "http://ops81.zgpingshu.com/%E5%BC%A0%E5%B0%91%E4%BD%90/%E7%BA%A2%E8%89%B2%E9%97%B4%E8%B0%8D%2850%E5%9B%9E%29%28%E6%BC%94%E6%92%AD-%E5%BC%A0%E5%B0%91%E4%BD%90%29%2832kb%29/C1B10649F2.mp3"
    },
    {
      "name": "036回 - 红色间谍",
      "url": "http://www.zgpingshu.com/play/5282/36.html",
      "downloadUrl": "http://ops81.zgpingshu.com/%E5%BC%A0%E5%B0%91%E4%BD%90/%E7%BA%A2%E8%89%B2%E9%97%B4%E8%B0%8D%2850%E5%9B%9E%29%28%E6%BC%94%E6%92%AD-%E5%BC%A0%E5%B0%91%E4%BD%90%29%2832kb%29/4307741DBD.mp3"
    },
    {
      "name": "037回 - 红色间谍",
      "url": "http://www.zgpingshu.com/play/5282/37.html",
      "downloadUrl": "http://ops81.zgpingshu.com/%E5%BC%A0%E5%B0%91%E4%BD%90/%E7%BA%A2%E8%89%B2%E9%97%B4%E8%B0%8D%2850%E5%9B%9E%29%28%E6%BC%94%E6%92%AD-%E5%BC%A0%E5%B0%91%E4%BD%90%29%2832kb%29/2D606CE9E0.mp3"
    },
    {
      "name": "038回 - 红色间谍",
      "url": "http://www.zgpingshu.com/play/5282/38.html",
      "downloadUrl": "http://ops81.zgpingshu.com/%E5%BC%A0%E5%B0%91%E4%BD%90/%E7%BA%A2%E8%89%B2%E9%97%B4%E8%B0%8D%2850%E5%9B%9E%29%28%E6%BC%94%E6%92%AD-%E5%BC%A0%E5%B0%91%E4%BD%90%29%2832kb%29/81ED26CF95.mp3"
    },
    {
      "name": "039回 - 红色间谍",
      "url": "http://www.zgpingshu.com/play/5282/39.html",
      "downloadUrl": "http://ops81.zgpingshu.com/%E5%BC%A0%E5%B0%91%E4%BD%90/%E7%BA%A2%E8%89%B2%E9%97%B4%E8%B0%8D%2850%E5%9B%9E%29%28%E6%BC%94%E6%92%AD-%E5%BC%A0%E5%B0%91%E4%BD%90%29%2832kb%29/CF881FA0CA.mp3"
    },
    {
      "name": "040回 - 红色间谍",
      "url": "http://www.zgpingshu.com/play/5282/40.html",
      "downloadUrl": "http://ops81.zgpingshu.com/%E5%BC%A0%E5%B0%91%E4%BD%90/%E7%BA%A2%E8%89%B2%E9%97%B4%E8%B0%8D%2850%E5%9B%9E%29%28%E6%BC%94%E6%92%AD-%E5%BC%A0%E5%B0%91%E4%BD%90%29%2832kb%29/7F5B3DCCF9.mp3"
    },
    {
      "name": "041回 - 红色间谍",
      "url": "http://www.zgpingshu.com/play/5282/41.html",
      "downloadUrl": "http://ops81.zgpingshu.com/%E5%BC%A0%E5%B0%91%E4%BD%90/%E7%BA%A2%E8%89%B2%E9%97%B4%E8%B0%8D%2850%E5%9B%9E%29%28%E6%BC%94%E6%92%AD-%E5%BC%A0%E5%B0%91%E4%BD%90%29%2832kb%29/8FA29ACE19.mp3"
    },
    {
      "name": "042回 - 红色间谍",
      "url": "http://www.zgpingshu.com/play/5282/42.html",
      "downloadUrl": "http://ops81.zgpingshu.com/%E5%BC%A0%E5%B0%91%E4%BD%90/%E7%BA%A2%E8%89%B2%E9%97%B4%E8%B0%8D%2850%E5%9B%9E%29%28%E6%BC%94%E6%92%AD-%E5%BC%A0%E5%B0%91%E4%BD%90%29%2832kb%29/9E6AC95D57.mp3"
    },
    {
      "name": "043回 - 红色间谍",
      "url": "http://www.zgpingshu.com/play/5282/43.html",
      "downloadUrl": "http://ops81.zgpingshu.com/%E5%BC%A0%E5%B0%91%E4%BD%90/%E7%BA%A2%E8%89%B2%E9%97%B4%E8%B0%8D%2850%E5%9B%9E%29%28%E6%BC%94%E6%92%AD-%E5%BC%A0%E5%B0%91%E4%BD%90%29%2832kb%29/B1ECA43C5C.mp3"
    },
    {
      "name": "044回 - 红色间谍",
      "url": "http://www.zgpingshu.com/play/5282/44.html",
      "downloadUrl": "http://ops81.zgpingshu.com/%E5%BC%A0%E5%B0%91%E4%BD%90/%E7%BA%A2%E8%89%B2%E9%97%B4%E8%B0%8D%2850%E5%9B%9E%29%28%E6%BC%94%E6%92%AD-%E5%BC%A0%E5%B0%91%E4%BD%90%29%2832kb%29/9255712FDB.mp3"
    },
    {
      "name": "045回 - 红色间谍",
      "url": "http://www.zgpingshu.com/play/5282/45.html",
      "downloadUrl": "http://ops81.zgpingshu.com/%E5%BC%A0%E5%B0%91%E4%BD%90/%E7%BA%A2%E8%89%B2%E9%97%B4%E8%B0%8D%2850%E5%9B%9E%29%28%E6%BC%94%E6%92%AD-%E5%BC%A0%E5%B0%91%E4%BD%90%29%2832kb%29/FF45349AC9.mp3"
    },
    {
      "name": "046回 - 红色间谍",
      "url": "http://www.zgpingshu.com/play/5282/46.html",
      "downloadUrl": "http://ops81.zgpingshu.com/%E5%BC%A0%E5%B0%91%E4%BD%90/%E7%BA%A2%E8%89%B2%E9%97%B4%E8%B0%8D%2850%E5%9B%9E%29%28%E6%BC%94%E6%92%AD-%E5%BC%A0%E5%B0%91%E4%BD%90%29%2832kb%29/A62C22850A.mp3"
    },
    {
      "name": "047回 - 红色间谍",
      "url": "http://www.zgpingshu.com/play/5282/47.html",
      "downloadUrl": "http://ops81.zgpingshu.com/%E5%BC%A0%E5%B0%91%E4%BD%90/%E7%BA%A2%E8%89%B2%E9%97%B4%E8%B0%8D%2850%E5%9B%9E%29%28%E6%BC%94%E6%92%AD-%E5%BC%A0%E5%B0%91%E4%BD%90%29%2832kb%29/C77595C898.mp3"
    },
    {
      "name": "048回 - 红色间谍",
      "url": "http://www.zgpingshu.com/play/5282/48.html",
      "downloadUrl": "http://ops81.zgpingshu.com/%E5%BC%A0%E5%B0%91%E4%BD%90/%E7%BA%A2%E8%89%B2%E9%97%B4%E8%B0%8D%2850%E5%9B%9E%29%28%E6%BC%94%E6%92%AD-%E5%BC%A0%E5%B0%91%E4%BD%90%29%2832kb%29/2D3ED858CC.mp3"
    },
    {
      "name": "049回 - 红色间谍",
      "url": "http://www.zgpingshu.com/play/5282/49.html",
      "downloadUrl": "http://ops81.zgpingshu.com/%E5%BC%A0%E5%B0%91%E4%BD%90/%E7%BA%A2%E8%89%B2%E9%97%B4%E8%B0%8D%2850%E5%9B%9E%29%28%E6%BC%94%E6%92%AD-%E5%BC%A0%E5%B0%91%E4%BD%90%29%2832kb%29/DD06F91CC9.mp3"
    },
    {
      "name": "050回 - 红色间谍",
      "url": "http://www.zgpingshu.com/play/5282/50.html",
      "downloadUrl": "http://ops81.zgpingshu.com/%E5%BC%A0%E5%B0%91%E4%BD%90/%E7%BA%A2%E8%89%B2%E9%97%B4%E8%B0%8D%2850%E5%9B%9E%29%28%E6%BC%94%E6%92%AD-%E5%BC%A0%E5%B0%91%E4%BD%90%29%2832kb%29/B8D1A53921.mp3"
    }
  ]
}
