{
  "name": "刘伶传奇(电台版)",
  "url": "http://shantianfang.zgpingshu.com/4559/",
  "chapters": [
    {
      "name": "001回 - 刘伶传奇(电台版)",
      "url": "http://www.zgpingshu.com/down/4559/",
      "downloadUrl": "http://dops41.zgpingshu.com/%E5%8D%95%E7%94%B0%E8%8A%B3/%E7%94%B5%E5%8F%B0%E7%89%88%E5%88%98%E4%BC%B6%E4%BC%A0%E5%A5%87%28100%E5%9B%9E%29%28%E6%92%AD%E9%9F%B3-%E5%8D%95%E7%94%B0%E8%8A%B3%29%2832kbps%29/2074022171.mp3"
    },
    {
      "name": "002回 - 刘伶传奇(电台版)",
      "url": "http://www.zgpingshu.com/down/4559/2.html",
      "downloadUrl": "http://dops41.zgpingshu.com/%E5%8D%95%E7%94%B0%E8%8A%B3/%E7%94%B5%E5%8F%B0%E7%89%88%E5%88%98%E4%BC%B6%E4%BC%A0%E5%A5%87%28100%E5%9B%9E%29%28%E6%92%AD%E9%9F%B3-%E5%8D%95%E7%94%B0%E8%8A%B3%29%2832kbps%29/4D0C936E90.mp3"
    },
    {
      "name": "003回 - 刘伶传奇(电台版)",
      "url": "http://www.zgpingshu.com/down/4559/3.html",
      "downloadUrl": "http://dops41.zgpingshu.com/%E5%8D%95%E7%94%B0%E8%8A%B3/%E7%94%B5%E5%8F%B0%E7%89%88%E5%88%98%E4%BC%B6%E4%BC%A0%E5%A5%87%28100%E5%9B%9E%29%28%E6%92%AD%E9%9F%B3-%E5%8D%95%E7%94%B0%E8%8A%B3%29%2832kbps%29/EC5B07EC99.mp3"
    },
    {
      "name": "004回 - 刘伶传奇(电台版)",
      "url": "http://www.zgpingshu.com/down/4559/4.html",
      "downloadUrl": "http://dops41.zgpingshu.com/%E5%8D%95%E7%94%B0%E8%8A%B3/%E7%94%B5%E5%8F%B0%E7%89%88%E5%88%98%E4%BC%B6%E4%BC%A0%E5%A5%87%28100%E5%9B%9E%29%28%E6%92%AD%E9%9F%B3-%E5%8D%95%E7%94%B0%E8%8A%B3%29%2832kbps%29/8776FE0864.mp3"
    },
    {
      "name": "005回 - 刘伶传奇(电台版)",
      "url": "http://www.zgpingshu.com/down/4559/5.html",
      "downloadUrl": "http://dops41.zgpingshu.com/%E5%8D%95%E7%94%B0%E8%8A%B3/%E7%94%B5%E5%8F%B0%E7%89%88%E5%88%98%E4%BC%B6%E4%BC%A0%E5%A5%87%28100%E5%9B%9E%29%28%E6%92%AD%E9%9F%B3-%E5%8D%95%E7%94%B0%E8%8A%B3%29%2832kbps%29/F3CCD2915B.mp3"
    },
    {
      "name": "006回 - 刘伶传奇(电台版)",
      "url": "http://www.zgpingshu.com/down/4559/6.html",
      "downloadUrl": "http://dops41.zgpingshu.com/%E5%8D%95%E7%94%B0%E8%8A%B3/%E7%94%B5%E5%8F%B0%E7%89%88%E5%88%98%E4%BC%B6%E4%BC%A0%E5%A5%87%28100%E5%9B%9E%29%28%E6%92%AD%E9%9F%B3-%E5%8D%95%E7%94%B0%E8%8A%B3%29%2832kbps%29/5BFAD275CA.mp3"
    },
    {
      "name": "007回 - 刘伶传奇(电台版)",
      "url": "http://www.zgpingshu.com/down/4559/7.html",
      "downloadUrl": "http://dops41.zgpingshu.com/%E5%8D%95%E7%94%B0%E8%8A%B3/%E7%94%B5%E5%8F%B0%E7%89%88%E5%88%98%E4%BC%B6%E4%BC%A0%E5%A5%87%28100%E5%9B%9E%29%28%E6%92%AD%E9%9F%B3-%E5%8D%95%E7%94%B0%E8%8A%B3%29%2832kbps%29/442254BAE7.mp3"
    },
    {
      "name": "008回 - 刘伶传奇(电台版)",
      "url": "http://www.zgpingshu.com/down/4559/8.html",
      "downloadUrl": "http://dops41.zgpingshu.com/%E5%8D%95%E7%94%B0%E8%8A%B3/%E7%94%B5%E5%8F%B0%E7%89%88%E5%88%98%E4%BC%B6%E4%BC%A0%E5%A5%87%28100%E5%9B%9E%29%28%E6%92%AD%E9%9F%B3-%E5%8D%95%E7%94%B0%E8%8A%B3%29%2832kbps%29/2D126CDF35.mp3"
    },
    {
      "name": "009回 - 刘伶传奇(电台版)",
      "url": "http://www.zgpingshu.com/down/4559/9.html",
      "downloadUrl": "http://dops41.zgpingshu.com/%E5%8D%95%E7%94%B0%E8%8A%B3/%E7%94%B5%E5%8F%B0%E7%89%88%E5%88%98%E4%BC%B6%E4%BC%A0%E5%A5%87%28100%E5%9B%9E%29%28%E6%92%AD%E9%9F%B3-%E5%8D%95%E7%94%B0%E8%8A%B3%29%2832kbps%29/2519EC8CDA.mp3"
    },
    {
      "name": "010回 - 刘伶传奇(电台版)",
      "url": "http://www.zgpingshu.com/down/4559/10.html",
      "downloadUrl": "http://dops41.zgpingshu.com/%E5%8D%95%E7%94%B0%E8%8A%B3/%E7%94%B5%E5%8F%B0%E7%89%88%E5%88%98%E4%BC%B6%E4%BC%A0%E5%A5%87%28100%E5%9B%9E%29%28%E6%92%AD%E9%9F%B3-%E5%8D%95%E7%94%B0%E8%8A%B3%29%2832kbps%29/18F8744E61.mp3"
    },
    {
      "name": "011回 - 刘伶传奇(电台版)",
      "url": "http://www.zgpingshu.com/down/4559/11.html",
      "downloadUrl": "http://dops41.zgpingshu.com/%E5%8D%95%E7%94%B0%E8%8A%B3/%E7%94%B5%E5%8F%B0%E7%89%88%E5%88%98%E4%BC%B6%E4%BC%A0%E5%A5%87%28100%E5%9B%9E%29%28%E6%92%AD%E9%9F%B3-%E5%8D%95%E7%94%B0%E8%8A%B3%29%2832kbps%29/EA9C721411.mp3"
    },
    {
      "name": "012回 - 刘伶传奇(电台版)",
      "url": "http://www.zgpingshu.com/down/4559/12.html",
      "downloadUrl": "http://dops41.zgpingshu.com/%E5%8D%95%E7%94%B0%E8%8A%B3/%E7%94%B5%E5%8F%B0%E7%89%88%E5%88%98%E4%BC%B6%E4%BC%A0%E5%A5%87%28100%E5%9B%9E%29%28%E6%92%AD%E9%9F%B3-%E5%8D%95%E7%94%B0%E8%8A%B3%29%2832kbps%29/54C5A10971.mp3"
    },
    {
      "name": "013回 - 刘伶传奇(电台版)",
      "url": "http://www.zgpingshu.com/down/4559/13.html",
      "downloadUrl": "http://dops41.zgpingshu.com/%E5%8D%95%E7%94%B0%E8%8A%B3/%E7%94%B5%E5%8F%B0%E7%89%88%E5%88%98%E4%BC%B6%E4%BC%A0%E5%A5%87%28100%E5%9B%9E%29%28%E6%92%AD%E9%9F%B3-%E5%8D%95%E7%94%B0%E8%8A%B3%29%2832kbps%29/54B3EF04BD.mp3"
    },
    {
      "name": "014回 - 刘伶传奇(电台版)",
      "url": "http://www.zgpingshu.com/down/4559/14.html",
      "downloadUrl": "http://dops41.zgpingshu.com/%E5%8D%95%E7%94%B0%E8%8A%B3/%E7%94%B5%E5%8F%B0%E7%89%88%E5%88%98%E4%BC%B6%E4%BC%A0%E5%A5%87%28100%E5%9B%9E%29%28%E6%92%AD%E9%9F%B3-%E5%8D%95%E7%94%B0%E8%8A%B3%29%2832kbps%29/38C38A0EB3.mp3"
    },
    {
      "name": "015回 - 刘伶传奇(电台版)",
      "url": "http://www.zgpingshu.com/down/4559/15.html",
      "downloadUrl": "http://dops41.zgpingshu.com/%E5%8D%95%E7%94%B0%E8%8A%B3/%E7%94%B5%E5%8F%B0%E7%89%88%E5%88%98%E4%BC%B6%E4%BC%A0%E5%A5%87%28100%E5%9B%9E%29%28%E6%92%AD%E9%9F%B3-%E5%8D%95%E7%94%B0%E8%8A%B3%29%2832kbps%29/43C747E5CB.mp3"
    },
    { "name": "016回 - 刘伶传奇(电台版)", "url": "http://www.zgpingshu.com/down/4559/16.html", "downloadUrl": "" },
    {
      "name": "017回 - 刘伶传奇(电台版)",
      "url": "http://www.zgpingshu.com/down/4559/17.html",
      "downloadUrl": "http://dops41.zgpingshu.com/%E5%8D%95%E7%94%B0%E8%8A%B3/%E7%94%B5%E5%8F%B0%E7%89%88%E5%88%98%E4%BC%B6%E4%BC%A0%E5%A5%87%28100%E5%9B%9E%29%28%E6%92%AD%E9%9F%B3-%E5%8D%95%E7%94%B0%E8%8A%B3%29%2832kbps%29/3486BB56BF.mp3"
    },
    {
      "name": "018回 - 刘伶传奇(电台版)",
      "url": "http://www.zgpingshu.com/down/4559/18.html",
      "downloadUrl": "http://dops41.zgpingshu.com/%E5%8D%95%E7%94%B0%E8%8A%B3/%E7%94%B5%E5%8F%B0%E7%89%88%E5%88%98%E4%BC%B6%E4%BC%A0%E5%A5%87%28100%E5%9B%9E%29%28%E6%92%AD%E9%9F%B3-%E5%8D%95%E7%94%B0%E8%8A%B3%29%2832kbps%29/1F283F813A.mp3"
    },
    {
      "name": "019回 - 刘伶传奇(电台版)",
      "url": "http://www.zgpingshu.com/down/4559/19.html",
      "downloadUrl": "http://dops41.zgpingshu.com/%E5%8D%95%E7%94%B0%E8%8A%B3/%E7%94%B5%E5%8F%B0%E7%89%88%E5%88%98%E4%BC%B6%E4%BC%A0%E5%A5%87%28100%E5%9B%9E%29%28%E6%92%AD%E9%9F%B3-%E5%8D%95%E7%94%B0%E8%8A%B3%29%2832kbps%29/BCC0FA35E6.mp3"
    },
    {
      "name": "020回 - 刘伶传奇(电台版)",
      "url": "http://www.zgpingshu.com/down/4559/20.html",
      "downloadUrl": "http://dops41.zgpingshu.com/%E5%8D%95%E7%94%B0%E8%8A%B3/%E7%94%B5%E5%8F%B0%E7%89%88%E5%88%98%E4%BC%B6%E4%BC%A0%E5%A5%87%28100%E5%9B%9E%29%28%E6%92%AD%E9%9F%B3-%E5%8D%95%E7%94%B0%E8%8A%B3%29%2832kbps%29/91C8499430.mp3"
    },
    {
      "name": "021回 - 刘伶传奇(电台版)",
      "url": "http://www.zgpingshu.com/down/4559/21.html",
      "downloadUrl": "http://dops41.zgpingshu.com/%E5%8D%95%E7%94%B0%E8%8A%B3/%E7%94%B5%E5%8F%B0%E7%89%88%E5%88%98%E4%BC%B6%E4%BC%A0%E5%A5%87%28100%E5%9B%9E%29%28%E6%92%AD%E9%9F%B3-%E5%8D%95%E7%94%B0%E8%8A%B3%29%2832kbps%29/6B3D687A63.mp3"
    },
    {
      "name": "022回 - 刘伶传奇(电台版)",
      "url": "http://www.zgpingshu.com/down/4559/22.html",
      "downloadUrl": "http://dops41.zgpingshu.com/%E5%8D%95%E7%94%B0%E8%8A%B3/%E7%94%B5%E5%8F%B0%E7%89%88%E5%88%98%E4%BC%B6%E4%BC%A0%E5%A5%87%28100%E5%9B%9E%29%28%E6%92%AD%E9%9F%B3-%E5%8D%95%E7%94%B0%E8%8A%B3%29%2832kbps%29/827E42C4C5.mp3"
    },
    {
      "name": "023回 - 刘伶传奇(电台版)",
      "url": "http://www.zgpingshu.com/down/4559/23.html",
      "downloadUrl": "http://dops41.zgpingshu.com/%E5%8D%95%E7%94%B0%E8%8A%B3/%E7%94%B5%E5%8F%B0%E7%89%88%E5%88%98%E4%BC%B6%E4%BC%A0%E5%A5%87%28100%E5%9B%9E%29%28%E6%92%AD%E9%9F%B3-%E5%8D%95%E7%94%B0%E8%8A%B3%29%2832kbps%29/D726697D4F.mp3"
    },
    {
      "name": "024回 - 刘伶传奇(电台版)",
      "url": "http://www.zgpingshu.com/down/4559/24.html",
      "downloadUrl": "http://dops41.zgpingshu.com/%E5%8D%95%E7%94%B0%E8%8A%B3/%E7%94%B5%E5%8F%B0%E7%89%88%E5%88%98%E4%BC%B6%E4%BC%A0%E5%A5%87%28100%E5%9B%9E%29%28%E6%92%AD%E9%9F%B3-%E5%8D%95%E7%94%B0%E8%8A%B3%29%2832kbps%29/451F5EFFBF.mp3"
    },
    {
      "name": "025回 - 刘伶传奇(电台版)",
      "url": "http://www.zgpingshu.com/down/4559/25.html",
      "downloadUrl": "http://dops41.zgpingshu.com/%E5%8D%95%E7%94%B0%E8%8A%B3/%E7%94%B5%E5%8F%B0%E7%89%88%E5%88%98%E4%BC%B6%E4%BC%A0%E5%A5%87%28100%E5%9B%9E%29%28%E6%92%AD%E9%9F%B3-%E5%8D%95%E7%94%B0%E8%8A%B3%29%2832kbps%29/E64DD4C41A.mp3"
    },
    {
      "name": "026回 - 刘伶传奇(电台版)",
      "url": "http://www.zgpingshu.com/down/4559/26.html",
      "downloadUrl": "http://dops41.zgpingshu.com/%E5%8D%95%E7%94%B0%E8%8A%B3/%E7%94%B5%E5%8F%B0%E7%89%88%E5%88%98%E4%BC%B6%E4%BC%A0%E5%A5%87%28100%E5%9B%9E%29%28%E6%92%AD%E9%9F%B3-%E5%8D%95%E7%94%B0%E8%8A%B3%29%2832kbps%29/2908B904B7.mp3"
    },
    {
      "name": "027回 - 刘伶传奇(电台版)",
      "url": "http://www.zgpingshu.com/down/4559/27.html",
      "downloadUrl": "http://dops41.zgpingshu.com/%E5%8D%95%E7%94%B0%E8%8A%B3/%E7%94%B5%E5%8F%B0%E7%89%88%E5%88%98%E4%BC%B6%E4%BC%A0%E5%A5%87%28100%E5%9B%9E%29%28%E6%92%AD%E9%9F%B3-%E5%8D%95%E7%94%B0%E8%8A%B3%29%2832kbps%29/BEF903B45D.mp3"
    },
    {
      "name": "028回 - 刘伶传奇(电台版)",
      "url": "http://www.zgpingshu.com/down/4559/28.html",
      "downloadUrl": "http://dops41.zgpingshu.com/%E5%8D%95%E7%94%B0%E8%8A%B3/%E7%94%B5%E5%8F%B0%E7%89%88%E5%88%98%E4%BC%B6%E4%BC%A0%E5%A5%87%28100%E5%9B%9E%29%28%E6%92%AD%E9%9F%B3-%E5%8D%95%E7%94%B0%E8%8A%B3%29%2832kbps%29/382F04DBE2.mp3"
    },
    {
      "name": "029回 - 刘伶传奇(电台版)",
      "url": "http://www.zgpingshu.com/down/4559/29.html",
      "downloadUrl": "http://dops41.zgpingshu.com/%E5%8D%95%E7%94%B0%E8%8A%B3/%E7%94%B5%E5%8F%B0%E7%89%88%E5%88%98%E4%BC%B6%E4%BC%A0%E5%A5%87%28100%E5%9B%9E%29%28%E6%92%AD%E9%9F%B3-%E5%8D%95%E7%94%B0%E8%8A%B3%29%2832kbps%29/9D43F3B4B2.mp3"
    },
    {
      "name": "030回 - 刘伶传奇(电台版)",
      "url": "http://www.zgpingshu.com/down/4559/30.html",
      "downloadUrl": "http://dops41.zgpingshu.com/%E5%8D%95%E7%94%B0%E8%8A%B3/%E7%94%B5%E5%8F%B0%E7%89%88%E5%88%98%E4%BC%B6%E4%BC%A0%E5%A5%87%28100%E5%9B%9E%29%28%E6%92%AD%E9%9F%B3-%E5%8D%95%E7%94%B0%E8%8A%B3%29%2832kbps%29/C03A9ECE53.mp3"
    },
    {
      "name": "031回 - 刘伶传奇(电台版)",
      "url": "http://www.zgpingshu.com/down/4559/31.html",
      "downloadUrl": "http://dops41.zgpingshu.com/%E5%8D%95%E7%94%B0%E8%8A%B3/%E7%94%B5%E5%8F%B0%E7%89%88%E5%88%98%E4%BC%B6%E4%BC%A0%E5%A5%87%28100%E5%9B%9E%29%28%E6%92%AD%E9%9F%B3-%E5%8D%95%E7%94%B0%E8%8A%B3%29%2832kbps%29/800F9C8122.mp3"
    },
    {
      "name": "032回 - 刘伶传奇(电台版)",
      "url": "http://www.zgpingshu.com/down/4559/32.html",
      "downloadUrl": "http://dops41.zgpingshu.com/%E5%8D%95%E7%94%B0%E8%8A%B3/%E7%94%B5%E5%8F%B0%E7%89%88%E5%88%98%E4%BC%B6%E4%BC%A0%E5%A5%87%28100%E5%9B%9E%29%28%E6%92%AD%E9%9F%B3-%E5%8D%95%E7%94%B0%E8%8A%B3%29%2832kbps%29/6C804A5507.mp3"
    },
    {
      "name": "033回 - 刘伶传奇(电台版)",
      "url": "http://www.zgpingshu.com/down/4559/33.html",
      "downloadUrl": "http://dops41.zgpingshu.com/%E5%8D%95%E7%94%B0%E8%8A%B3/%E7%94%B5%E5%8F%B0%E7%89%88%E5%88%98%E4%BC%B6%E4%BC%A0%E5%A5%87%28100%E5%9B%9E%29%28%E6%92%AD%E9%9F%B3-%E5%8D%95%E7%94%B0%E8%8A%B3%29%2832kbps%29/79F1138D6C.mp3"
    },
    {
      "name": "034回 - 刘伶传奇(电台版)",
      "url": "http://www.zgpingshu.com/down/4559/34.html",
      "downloadUrl": "http://dops41.zgpingshu.com/%E5%8D%95%E7%94%B0%E8%8A%B3/%E7%94%B5%E5%8F%B0%E7%89%88%E5%88%98%E4%BC%B6%E4%BC%A0%E5%A5%87%28100%E5%9B%9E%29%28%E6%92%AD%E9%9F%B3-%E5%8D%95%E7%94%B0%E8%8A%B3%29%2832kbps%29/7EA3EC3836.mp3"
    },
    { "name": "035回 - 刘伶传奇(电台版)", "url": "http://www.zgpingshu.com/down/4559/35.html", "downloadUrl": "" },
    {
      "name": "036回 - 刘伶传奇(电台版)",
      "url": "http://www.zgpingshu.com/down/4559/36.html",
      "downloadUrl": "http://dops41.zgpingshu.com/%E5%8D%95%E7%94%B0%E8%8A%B3/%E7%94%B5%E5%8F%B0%E7%89%88%E5%88%98%E4%BC%B6%E4%BC%A0%E5%A5%87%28100%E5%9B%9E%29%28%E6%92%AD%E9%9F%B3-%E5%8D%95%E7%94%B0%E8%8A%B3%29%2832kbps%29/DCFBE62DDB.mp3"
    },
    {
      "name": "037回 - 刘伶传奇(电台版)",
      "url": "http://www.zgpingshu.com/down/4559/37.html",
      "downloadUrl": "http://dops41.zgpingshu.com/%E5%8D%95%E7%94%B0%E8%8A%B3/%E7%94%B5%E5%8F%B0%E7%89%88%E5%88%98%E4%BC%B6%E4%BC%A0%E5%A5%87%28100%E5%9B%9E%29%28%E6%92%AD%E9%9F%B3-%E5%8D%95%E7%94%B0%E8%8A%B3%29%2832kbps%29/F11D38CE75.mp3"
    },
    {
      "name": "038回 - 刘伶传奇(电台版)",
      "url": "http://www.zgpingshu.com/down/4559/38.html",
      "downloadUrl": "http://dops41.zgpingshu.com/%E5%8D%95%E7%94%B0%E8%8A%B3/%E7%94%B5%E5%8F%B0%E7%89%88%E5%88%98%E4%BC%B6%E4%BC%A0%E5%A5%87%28100%E5%9B%9E%29%28%E6%92%AD%E9%9F%B3-%E5%8D%95%E7%94%B0%E8%8A%B3%29%2832kbps%29/95274EFAC2.mp3"
    },
    {
      "name": "039回 - 刘伶传奇(电台版)",
      "url": "http://www.zgpingshu.com/down/4559/39.html",
      "downloadUrl": "http://dops41.zgpingshu.com/%E5%8D%95%E7%94%B0%E8%8A%B3/%E7%94%B5%E5%8F%B0%E7%89%88%E5%88%98%E4%BC%B6%E4%BC%A0%E5%A5%87%28100%E5%9B%9E%29%28%E6%92%AD%E9%9F%B3-%E5%8D%95%E7%94%B0%E8%8A%B3%29%2832kbps%29/F7F4ED326E.mp3"
    },
    {
      "name": "040回 - 刘伶传奇(电台版)",
      "url": "http://www.zgpingshu.com/down/4559/40.html",
      "downloadUrl": "http://dops41.zgpingshu.com/%E5%8D%95%E7%94%B0%E8%8A%B3/%E7%94%B5%E5%8F%B0%E7%89%88%E5%88%98%E4%BC%B6%E4%BC%A0%E5%A5%87%28100%E5%9B%9E%29%28%E6%92%AD%E9%9F%B3-%E5%8D%95%E7%94%B0%E8%8A%B3%29%2832kbps%29/5854013ECD.mp3"
    },
    {
      "name": "041回 - 刘伶传奇(电台版)",
      "url": "http://www.zgpingshu.com/down/4559/41.html",
      "downloadUrl": "http://dops41.zgpingshu.com/%E5%8D%95%E7%94%B0%E8%8A%B3/%E7%94%B5%E5%8F%B0%E7%89%88%E5%88%98%E4%BC%B6%E4%BC%A0%E5%A5%87%28100%E5%9B%9E%29%28%E6%92%AD%E9%9F%B3-%E5%8D%95%E7%94%B0%E8%8A%B3%29%2832kbps%29/3F889A52B5.mp3"
    },
    {
      "name": "042回 - 刘伶传奇(电台版)",
      "url": "http://www.zgpingshu.com/down/4559/42.html",
      "downloadUrl": "http://dops41.zgpingshu.com/%E5%8D%95%E7%94%B0%E8%8A%B3/%E7%94%B5%E5%8F%B0%E7%89%88%E5%88%98%E4%BC%B6%E4%BC%A0%E5%A5%87%28100%E5%9B%9E%29%28%E6%92%AD%E9%9F%B3-%E5%8D%95%E7%94%B0%E8%8A%B3%29%2832kbps%29/01A1F2BE47.mp3"
    },
    {
      "name": "043回 - 刘伶传奇(电台版)",
      "url": "http://www.zgpingshu.com/down/4559/43.html",
      "downloadUrl": "http://dops41.zgpingshu.com/%E5%8D%95%E7%94%B0%E8%8A%B3/%E7%94%B5%E5%8F%B0%E7%89%88%E5%88%98%E4%BC%B6%E4%BC%A0%E5%A5%87%28100%E5%9B%9E%29%28%E6%92%AD%E9%9F%B3-%E5%8D%95%E7%94%B0%E8%8A%B3%29%2832kbps%29/15884FAA7C.mp3"
    },
    {
      "name": "044回 - 刘伶传奇(电台版)",
      "url": "http://www.zgpingshu.com/down/4559/44.html",
      "downloadUrl": "http://dops41.zgpingshu.com/%E5%8D%95%E7%94%B0%E8%8A%B3/%E7%94%B5%E5%8F%B0%E7%89%88%E5%88%98%E4%BC%B6%E4%BC%A0%E5%A5%87%28100%E5%9B%9E%29%28%E6%92%AD%E9%9F%B3-%E5%8D%95%E7%94%B0%E8%8A%B3%29%2832kbps%29/1FFD80D36E.mp3"
    },
    {
      "name": "045回 - 刘伶传奇(电台版)",
      "url": "http://www.zgpingshu.com/down/4559/45.html",
      "downloadUrl": "http://dops41.zgpingshu.com/%E5%8D%95%E7%94%B0%E8%8A%B3/%E7%94%B5%E5%8F%B0%E7%89%88%E5%88%98%E4%BC%B6%E4%BC%A0%E5%A5%87%28100%E5%9B%9E%29%28%E6%92%AD%E9%9F%B3-%E5%8D%95%E7%94%B0%E8%8A%B3%29%2832kbps%29/B8E70EAC83.mp3"
    },
    {
      "name": "046回 - 刘伶传奇(电台版)",
      "url": "http://www.zgpingshu.com/down/4559/46.html",
      "downloadUrl": "http://dops41.zgpingshu.com/%E5%8D%95%E7%94%B0%E8%8A%B3/%E7%94%B5%E5%8F%B0%E7%89%88%E5%88%98%E4%BC%B6%E4%BC%A0%E5%A5%87%28100%E5%9B%9E%29%28%E6%92%AD%E9%9F%B3-%E5%8D%95%E7%94%B0%E8%8A%B3%29%2832kbps%29/B69F6D20F1.mp3"
    },
    {
      "name": "047回 - 刘伶传奇(电台版)",
      "url": "http://www.zgpingshu.com/down/4559/47.html",
      "downloadUrl": "http://dops41.zgpingshu.com/%E5%8D%95%E7%94%B0%E8%8A%B3/%E7%94%B5%E5%8F%B0%E7%89%88%E5%88%98%E4%BC%B6%E4%BC%A0%E5%A5%87%28100%E5%9B%9E%29%28%E6%92%AD%E9%9F%B3-%E5%8D%95%E7%94%B0%E8%8A%B3%29%2832kbps%29/02ACB47FA7.mp3"
    },
    {
      "name": "048回 - 刘伶传奇(电台版)",
      "url": "http://www.zgpingshu.com/down/4559/48.html",
      "downloadUrl": "http://dops41.zgpingshu.com/%E5%8D%95%E7%94%B0%E8%8A%B3/%E7%94%B5%E5%8F%B0%E7%89%88%E5%88%98%E4%BC%B6%E4%BC%A0%E5%A5%87%28100%E5%9B%9E%29%28%E6%92%AD%E9%9F%B3-%E5%8D%95%E7%94%B0%E8%8A%B3%29%2832kbps%29/DA1B3022E7.mp3"
    },
    {
      "name": "049回 - 刘伶传奇(电台版)",
      "url": "http://www.zgpingshu.com/down/4559/49.html",
      "downloadUrl": "http://dops41.zgpingshu.com/%E5%8D%95%E7%94%B0%E8%8A%B3/%E7%94%B5%E5%8F%B0%E7%89%88%E5%88%98%E4%BC%B6%E4%BC%A0%E5%A5%87%28100%E5%9B%9E%29%28%E6%92%AD%E9%9F%B3-%E5%8D%95%E7%94%B0%E8%8A%B3%29%2832kbps%29/1699E0D454.mp3"
    },
    {
      "name": "050回 - 刘伶传奇(电台版)",
      "url": "http://www.zgpingshu.com/down/4559/50.html",
      "downloadUrl": "http://dops41.zgpingshu.com/%E5%8D%95%E7%94%B0%E8%8A%B3/%E7%94%B5%E5%8F%B0%E7%89%88%E5%88%98%E4%BC%B6%E4%BC%A0%E5%A5%87%28100%E5%9B%9E%29%28%E6%92%AD%E9%9F%B3-%E5%8D%95%E7%94%B0%E8%8A%B3%29%2832kbps%29/42C26F2F36.mp3"
    },
    {
      "name": "051回 - 刘伶传奇(电台版)",
      "url": "http://www.zgpingshu.com/down/4559/51.html",
      "downloadUrl": "http://dops41.zgpingshu.com/%E5%8D%95%E7%94%B0%E8%8A%B3/%E7%94%B5%E5%8F%B0%E7%89%88%E5%88%98%E4%BC%B6%E4%BC%A0%E5%A5%87%28100%E5%9B%9E%29%28%E6%92%AD%E9%9F%B3-%E5%8D%95%E7%94%B0%E8%8A%B3%29%2832kbps%29/6BA251A391.mp3"
    },
    {
      "name": "052回 - 刘伶传奇(电台版)",
      "url": "http://www.zgpingshu.com/down/4559/52.html",
      "downloadUrl": "http://dops41.zgpingshu.com/%E5%8D%95%E7%94%B0%E8%8A%B3/%E7%94%B5%E5%8F%B0%E7%89%88%E5%88%98%E4%BC%B6%E4%BC%A0%E5%A5%87%28100%E5%9B%9E%29%28%E6%92%AD%E9%9F%B3-%E5%8D%95%E7%94%B0%E8%8A%B3%29%2832kbps%29/412217A0F1.mp3"
    },
    {
      "name": "053回 - 刘伶传奇(电台版)",
      "url": "http://www.zgpingshu.com/down/4559/53.html",
      "downloadUrl": "http://dops41.zgpingshu.com/%E5%8D%95%E7%94%B0%E8%8A%B3/%E7%94%B5%E5%8F%B0%E7%89%88%E5%88%98%E4%BC%B6%E4%BC%A0%E5%A5%87%28100%E5%9B%9E%29%28%E6%92%AD%E9%9F%B3-%E5%8D%95%E7%94%B0%E8%8A%B3%29%2832kbps%29/F0137EEC15.mp3"
    },
    {
      "name": "054回 - 刘伶传奇(电台版)",
      "url": "http://www.zgpingshu.com/down/4559/54.html",
      "downloadUrl": "http://dops41.zgpingshu.com/%E5%8D%95%E7%94%B0%E8%8A%B3/%E7%94%B5%E5%8F%B0%E7%89%88%E5%88%98%E4%BC%B6%E4%BC%A0%E5%A5%87%28100%E5%9B%9E%29%28%E6%92%AD%E9%9F%B3-%E5%8D%95%E7%94%B0%E8%8A%B3%29%2832kbps%29/B136976F64.mp3"
    },
    { "name": "055回 - 刘伶传奇(电台版)", "url": "http://www.zgpingshu.com/down/4559/55.html", "downloadUrl": "" },
    {
      "name": "056回 - 刘伶传奇(电台版)",
      "url": "http://www.zgpingshu.com/down/4559/56.html",
      "downloadUrl": "http://dops41.zgpingshu.com/%E5%8D%95%E7%94%B0%E8%8A%B3/%E7%94%B5%E5%8F%B0%E7%89%88%E5%88%98%E4%BC%B6%E4%BC%A0%E5%A5%87%28100%E5%9B%9E%29%28%E6%92%AD%E9%9F%B3-%E5%8D%95%E7%94%B0%E8%8A%B3%29%2832kbps%29/12B75F2C07.mp3"
    },
    {
      "name": "057回 - 刘伶传奇(电台版)",
      "url": "http://www.zgpingshu.com/down/4559/57.html",
      "downloadUrl": "http://dops41.zgpingshu.com/%E5%8D%95%E7%94%B0%E8%8A%B3/%E7%94%B5%E5%8F%B0%E7%89%88%E5%88%98%E4%BC%B6%E4%BC%A0%E5%A5%87%28100%E5%9B%9E%29%28%E6%92%AD%E9%9F%B3-%E5%8D%95%E7%94%B0%E8%8A%B3%29%2832kbps%29/89FB41A825.mp3"
    },
    {
      "name": "058回 - 刘伶传奇(电台版)",
      "url": "http://www.zgpingshu.com/down/4559/58.html",
      "downloadUrl": "http://dops41.zgpingshu.com/%E5%8D%95%E7%94%B0%E8%8A%B3/%E7%94%B5%E5%8F%B0%E7%89%88%E5%88%98%E4%BC%B6%E4%BC%A0%E5%A5%87%28100%E5%9B%9E%29%28%E6%92%AD%E9%9F%B3-%E5%8D%95%E7%94%B0%E8%8A%B3%29%2832kbps%29/BE5F23C2E1.mp3"
    },
    {
      "name": "059回 - 刘伶传奇(电台版)",
      "url": "http://www.zgpingshu.com/down/4559/59.html",
      "downloadUrl": "http://dops41.zgpingshu.com/%E5%8D%95%E7%94%B0%E8%8A%B3/%E7%94%B5%E5%8F%B0%E7%89%88%E5%88%98%E4%BC%B6%E4%BC%A0%E5%A5%87%28100%E5%9B%9E%29%28%E6%92%AD%E9%9F%B3-%E5%8D%95%E7%94%B0%E8%8A%B3%29%2832kbps%29/5E59F0D982.mp3"
    },
    {
      "name": "060回 - 刘伶传奇(电台版)",
      "url": "http://www.zgpingshu.com/down/4559/60.html",
      "downloadUrl": "http://dops41.zgpingshu.com/%E5%8D%95%E7%94%B0%E8%8A%B3/%E7%94%B5%E5%8F%B0%E7%89%88%E5%88%98%E4%BC%B6%E4%BC%A0%E5%A5%87%28100%E5%9B%9E%29%28%E6%92%AD%E9%9F%B3-%E5%8D%95%E7%94%B0%E8%8A%B3%29%2832kbps%29/6177998A3A.mp3"
    },
    {
      "name": "061回 - 刘伶传奇(电台版)",
      "url": "http://www.zgpingshu.com/down/4559/61.html",
      "downloadUrl": "http://dops41.zgpingshu.com/%E5%8D%95%E7%94%B0%E8%8A%B3/%E7%94%B5%E5%8F%B0%E7%89%88%E5%88%98%E4%BC%B6%E4%BC%A0%E5%A5%87%28100%E5%9B%9E%29%28%E6%92%AD%E9%9F%B3-%E5%8D%95%E7%94%B0%E8%8A%B3%29%2832kbps%29/1B94162217.mp3"
    },
    {
      "name": "062回 - 刘伶传奇(电台版)",
      "url": "http://www.zgpingshu.com/down/4559/62.html",
      "downloadUrl": "http://dops41.zgpingshu.com/%E5%8D%95%E7%94%B0%E8%8A%B3/%E7%94%B5%E5%8F%B0%E7%89%88%E5%88%98%E4%BC%B6%E4%BC%A0%E5%A5%87%28100%E5%9B%9E%29%28%E6%92%AD%E9%9F%B3-%E5%8D%95%E7%94%B0%E8%8A%B3%29%2832kbps%29/845141CE6D.mp3"
    },
    {
      "name": "063回 - 刘伶传奇(电台版)",
      "url": "http://www.zgpingshu.com/down/4559/63.html",
      "downloadUrl": "http://dops41.zgpingshu.com/%E5%8D%95%E7%94%B0%E8%8A%B3/%E7%94%B5%E5%8F%B0%E7%89%88%E5%88%98%E4%BC%B6%E4%BC%A0%E5%A5%87%28100%E5%9B%9E%29%28%E6%92%AD%E9%9F%B3-%E5%8D%95%E7%94%B0%E8%8A%B3%29%2832kbps%29/8659040DA4.mp3"
    },
    {
      "name": "064回 - 刘伶传奇(电台版)",
      "url": "http://www.zgpingshu.com/down/4559/64.html",
      "downloadUrl": "http://dops41.zgpingshu.com/%E5%8D%95%E7%94%B0%E8%8A%B3/%E7%94%B5%E5%8F%B0%E7%89%88%E5%88%98%E4%BC%B6%E4%BC%A0%E5%A5%87%28100%E5%9B%9E%29%28%E6%92%AD%E9%9F%B3-%E5%8D%95%E7%94%B0%E8%8A%B3%29%2832kbps%29/72602CCF42.mp3"
    },
    {
      "name": "065回 - 刘伶传奇(电台版)",
      "url": "http://www.zgpingshu.com/down/4559/65.html",
      "downloadUrl": "http://dops41.zgpingshu.com/%E5%8D%95%E7%94%B0%E8%8A%B3/%E7%94%B5%E5%8F%B0%E7%89%88%E5%88%98%E4%BC%B6%E4%BC%A0%E5%A5%87%28100%E5%9B%9E%29%28%E6%92%AD%E9%9F%B3-%E5%8D%95%E7%94%B0%E8%8A%B3%29%2832kbps%29/D4580168B7.mp3"
    },
    {
      "name": "066回 - 刘伶传奇(电台版)",
      "url": "http://www.zgpingshu.com/down/4559/66.html",
      "downloadUrl": "http://dops41.zgpingshu.com/%E5%8D%95%E7%94%B0%E8%8A%B3/%E7%94%B5%E5%8F%B0%E7%89%88%E5%88%98%E4%BC%B6%E4%BC%A0%E5%A5%87%28100%E5%9B%9E%29%28%E6%92%AD%E9%9F%B3-%E5%8D%95%E7%94%B0%E8%8A%B3%29%2832kbps%29/2A1F73BB19.mp3"
    },
    {
      "name": "067回 - 刘伶传奇(电台版)",
      "url": "http://www.zgpingshu.com/down/4559/67.html",
      "downloadUrl": "http://dops41.zgpingshu.com/%E5%8D%95%E7%94%B0%E8%8A%B3/%E7%94%B5%E5%8F%B0%E7%89%88%E5%88%98%E4%BC%B6%E4%BC%A0%E5%A5%87%28100%E5%9B%9E%29%28%E6%92%AD%E9%9F%B3-%E5%8D%95%E7%94%B0%E8%8A%B3%29%2832kbps%29/08A0750688.mp3"
    },
    {
      "name": "068回 - 刘伶传奇(电台版)",
      "url": "http://www.zgpingshu.com/down/4559/68.html",
      "downloadUrl": "http://dops41.zgpingshu.com/%E5%8D%95%E7%94%B0%E8%8A%B3/%E7%94%B5%E5%8F%B0%E7%89%88%E5%88%98%E4%BC%B6%E4%BC%A0%E5%A5%87%28100%E5%9B%9E%29%28%E6%92%AD%E9%9F%B3-%E5%8D%95%E7%94%B0%E8%8A%B3%29%2832kbps%29/5470148A0F.mp3"
    },
    {
      "name": "069回 - 刘伶传奇(电台版)",
      "url": "http://www.zgpingshu.com/down/4559/69.html",
      "downloadUrl": "http://dops41.zgpingshu.com/%E5%8D%95%E7%94%B0%E8%8A%B3/%E7%94%B5%E5%8F%B0%E7%89%88%E5%88%98%E4%BC%B6%E4%BC%A0%E5%A5%87%28100%E5%9B%9E%29%28%E6%92%AD%E9%9F%B3-%E5%8D%95%E7%94%B0%E8%8A%B3%29%2832kbps%29/4AF91751B7.mp3"
    },
    { "name": "070回 - 刘伶传奇(电台版)", "url": "http://www.zgpingshu.com/down/4559/70.html", "downloadUrl": "" },
    { "name": "071回 - 刘伶传奇(电台版)", "url": "http://www.zgpingshu.com/down/4559/71.html", "downloadUrl": "" },
    {
      "name": "072回 - 刘伶传奇(电台版)",
      "url": "http://www.zgpingshu.com/down/4559/72.html",
      "downloadUrl": "http://dops41.zgpingshu.com/%E5%8D%95%E7%94%B0%E8%8A%B3/%E7%94%B5%E5%8F%B0%E7%89%88%E5%88%98%E4%BC%B6%E4%BC%A0%E5%A5%87%28100%E5%9B%9E%29%28%E6%92%AD%E9%9F%B3-%E5%8D%95%E7%94%B0%E8%8A%B3%29%2832kbps%29/B1827D13A5.mp3"
    },
    {
      "name": "073回 - 刘伶传奇(电台版)",
      "url": "http://www.zgpingshu.com/down/4559/73.html",
      "downloadUrl": "http://dops41.zgpingshu.com/%E5%8D%95%E7%94%B0%E8%8A%B3/%E7%94%B5%E5%8F%B0%E7%89%88%E5%88%98%E4%BC%B6%E4%BC%A0%E5%A5%87%28100%E5%9B%9E%29%28%E6%92%AD%E9%9F%B3-%E5%8D%95%E7%94%B0%E8%8A%B3%29%2832kbps%29/B27FAEF9A6.mp3"
    },
    {
      "name": "074回 - 刘伶传奇(电台版)",
      "url": "http://www.zgpingshu.com/down/4559/74.html",
      "downloadUrl": "http://dops41.zgpingshu.com/%E5%8D%95%E7%94%B0%E8%8A%B3/%E7%94%B5%E5%8F%B0%E7%89%88%E5%88%98%E4%BC%B6%E4%BC%A0%E5%A5%87%28100%E5%9B%9E%29%28%E6%92%AD%E9%9F%B3-%E5%8D%95%E7%94%B0%E8%8A%B3%29%2832kbps%29/D6DAD69947.mp3"
    },
    {
      "name": "075回 - 刘伶传奇(电台版)",
      "url": "http://www.zgpingshu.com/down/4559/75.html",
      "downloadUrl": "http://dops41.zgpingshu.com/%E5%8D%95%E7%94%B0%E8%8A%B3/%E7%94%B5%E5%8F%B0%E7%89%88%E5%88%98%E4%BC%B6%E4%BC%A0%E5%A5%87%28100%E5%9B%9E%29%28%E6%92%AD%E9%9F%B3-%E5%8D%95%E7%94%B0%E8%8A%B3%29%2832kbps%29/7C2145B9B1.mp3"
    },
    {
      "name": "076回 - 刘伶传奇(电台版)",
      "url": "http://www.zgpingshu.com/down/4559/76.html",
      "downloadUrl": "http://dops41.zgpingshu.com/%E5%8D%95%E7%94%B0%E8%8A%B3/%E7%94%B5%E5%8F%B0%E7%89%88%E5%88%98%E4%BC%B6%E4%BC%A0%E5%A5%87%28100%E5%9B%9E%29%28%E6%92%AD%E9%9F%B3-%E5%8D%95%E7%94%B0%E8%8A%B3%29%2832kbps%29/C23637818E.mp3"
    },
    {
      "name": "077回 - 刘伶传奇(电台版)",
      "url": "http://www.zgpingshu.com/down/4559/77.html",
      "downloadUrl": "http://dops41.zgpingshu.com/%E5%8D%95%E7%94%B0%E8%8A%B3/%E7%94%B5%E5%8F%B0%E7%89%88%E5%88%98%E4%BC%B6%E4%BC%A0%E5%A5%87%28100%E5%9B%9E%29%28%E6%92%AD%E9%9F%B3-%E5%8D%95%E7%94%B0%E8%8A%B3%29%2832kbps%29/B3168A6AFE.mp3"
    },
    {
      "name": "078回 - 刘伶传奇(电台版)",
      "url": "http://www.zgpingshu.com/down/4559/78.html",
      "downloadUrl": "http://dops41.zgpingshu.com/%E5%8D%95%E7%94%B0%E8%8A%B3/%E7%94%B5%E5%8F%B0%E7%89%88%E5%88%98%E4%BC%B6%E4%BC%A0%E5%A5%87%28100%E5%9B%9E%29%28%E6%92%AD%E9%9F%B3-%E5%8D%95%E7%94%B0%E8%8A%B3%29%2832kbps%29/A663C9E219.mp3"
    },
    {
      "name": "079回 - 刘伶传奇(电台版)",
      "url": "http://www.zgpingshu.com/down/4559/79.html",
      "downloadUrl": "http://dops41.zgpingshu.com/%E5%8D%95%E7%94%B0%E8%8A%B3/%E7%94%B5%E5%8F%B0%E7%89%88%E5%88%98%E4%BC%B6%E4%BC%A0%E5%A5%87%28100%E5%9B%9E%29%28%E6%92%AD%E9%9F%B3-%E5%8D%95%E7%94%B0%E8%8A%B3%29%2832kbps%29/A633C0D985.mp3"
    },
    {
      "name": "080回 - 刘伶传奇(电台版)",
      "url": "http://www.zgpingshu.com/down/4559/80.html",
      "downloadUrl": "http://dops41.zgpingshu.com/%E5%8D%95%E7%94%B0%E8%8A%B3/%E7%94%B5%E5%8F%B0%E7%89%88%E5%88%98%E4%BC%B6%E4%BC%A0%E5%A5%87%28100%E5%9B%9E%29%28%E6%92%AD%E9%9F%B3-%E5%8D%95%E7%94%B0%E8%8A%B3%29%2832kbps%29/99577EDFF0.mp3"
    },
    {
      "name": "081回 - 刘伶传奇(电台版)",
      "url": "http://www.zgpingshu.com/down/4559/81.html",
      "downloadUrl": "http://dops41.zgpingshu.com/%E5%8D%95%E7%94%B0%E8%8A%B3/%E7%94%B5%E5%8F%B0%E7%89%88%E5%88%98%E4%BC%B6%E4%BC%A0%E5%A5%87%28100%E5%9B%9E%29%28%E6%92%AD%E9%9F%B3-%E5%8D%95%E7%94%B0%E8%8A%B3%29%2832kbps%29/10A5664096.mp3"
    },
    {
      "name": "082回 - 刘伶传奇(电台版)",
      "url": "http://www.zgpingshu.com/down/4559/82.html",
      "downloadUrl": "http://dops41.zgpingshu.com/%E5%8D%95%E7%94%B0%E8%8A%B3/%E7%94%B5%E5%8F%B0%E7%89%88%E5%88%98%E4%BC%B6%E4%BC%A0%E5%A5%87%28100%E5%9B%9E%29%28%E6%92%AD%E9%9F%B3-%E5%8D%95%E7%94%B0%E8%8A%B3%29%2832kbps%29/BC655726CF.mp3"
    },
    {
      "name": "083回 - 刘伶传奇(电台版)",
      "url": "http://www.zgpingshu.com/down/4559/83.html",
      "downloadUrl": "http://dops41.zgpingshu.com/%E5%8D%95%E7%94%B0%E8%8A%B3/%E7%94%B5%E5%8F%B0%E7%89%88%E5%88%98%E4%BC%B6%E4%BC%A0%E5%A5%87%28100%E5%9B%9E%29%28%E6%92%AD%E9%9F%B3-%E5%8D%95%E7%94%B0%E8%8A%B3%29%2832kbps%29/A2BD7673C2.mp3"
    },
    {
      "name": "084回 - 刘伶传奇(电台版)",
      "url": "http://www.zgpingshu.com/down/4559/84.html",
      "downloadUrl": "http://dops41.zgpingshu.com/%E5%8D%95%E7%94%B0%E8%8A%B3/%E7%94%B5%E5%8F%B0%E7%89%88%E5%88%98%E4%BC%B6%E4%BC%A0%E5%A5%87%28100%E5%9B%9E%29%28%E6%92%AD%E9%9F%B3-%E5%8D%95%E7%94%B0%E8%8A%B3%29%2832kbps%29/C92D4F6DFE.mp3"
    },
    {
      "name": "085回 - 刘伶传奇(电台版)",
      "url": "http://www.zgpingshu.com/down/4559/85.html",
      "downloadUrl": "http://dops41.zgpingshu.com/%E5%8D%95%E7%94%B0%E8%8A%B3/%E7%94%B5%E5%8F%B0%E7%89%88%E5%88%98%E4%BC%B6%E4%BC%A0%E5%A5%87%28100%E5%9B%9E%29%28%E6%92%AD%E9%9F%B3-%E5%8D%95%E7%94%B0%E8%8A%B3%29%2832kbps%29/58E23B4D31.mp3"
    },
    {
      "name": "086回 - 刘伶传奇(电台版)",
      "url": "http://www.zgpingshu.com/down/4559/86.html",
      "downloadUrl": "http://dops41.zgpingshu.com/%E5%8D%95%E7%94%B0%E8%8A%B3/%E7%94%B5%E5%8F%B0%E7%89%88%E5%88%98%E4%BC%B6%E4%BC%A0%E5%A5%87%28100%E5%9B%9E%29%28%E6%92%AD%E9%9F%B3-%E5%8D%95%E7%94%B0%E8%8A%B3%29%2832kbps%29/2628154B76.mp3"
    },
    {
      "name": "087回 - 刘伶传奇(电台版)",
      "url": "http://www.zgpingshu.com/down/4559/87.html",
      "downloadUrl": "http://dops41.zgpingshu.com/%E5%8D%95%E7%94%B0%E8%8A%B3/%E7%94%B5%E5%8F%B0%E7%89%88%E5%88%98%E4%BC%B6%E4%BC%A0%E5%A5%87%28100%E5%9B%9E%29%28%E6%92%AD%E9%9F%B3-%E5%8D%95%E7%94%B0%E8%8A%B3%29%2832kbps%29/1FA4B9AA12.mp3"
    },
    {
      "name": "088回 - 刘伶传奇(电台版)",
      "url": "http://www.zgpingshu.com/down/4559/88.html",
      "downloadUrl": "http://dops41.zgpingshu.com/%E5%8D%95%E7%94%B0%E8%8A%B3/%E7%94%B5%E5%8F%B0%E7%89%88%E5%88%98%E4%BC%B6%E4%BC%A0%E5%A5%87%28100%E5%9B%9E%29%28%E6%92%AD%E9%9F%B3-%E5%8D%95%E7%94%B0%E8%8A%B3%29%2832kbps%29/ECCC0F70A7.mp3"
    },
    {
      "name": "089回 - 刘伶传奇(电台版)",
      "url": "http://www.zgpingshu.com/down/4559/89.html",
      "downloadUrl": "http://dops41.zgpingshu.com/%E5%8D%95%E7%94%B0%E8%8A%B3/%E7%94%B5%E5%8F%B0%E7%89%88%E5%88%98%E4%BC%B6%E4%BC%A0%E5%A5%87%28100%E5%9B%9E%29%28%E6%92%AD%E9%9F%B3-%E5%8D%95%E7%94%B0%E8%8A%B3%29%2832kbps%29/398247B281.mp3"
    },
    {
      "name": "090回 - 刘伶传奇(电台版)",
      "url": "http://www.zgpingshu.com/down/4559/90.html",
      "downloadUrl": "http://dops41.zgpingshu.com/%E5%8D%95%E7%94%B0%E8%8A%B3/%E7%94%B5%E5%8F%B0%E7%89%88%E5%88%98%E4%BC%B6%E4%BC%A0%E5%A5%87%28100%E5%9B%9E%29%28%E6%92%AD%E9%9F%B3-%E5%8D%95%E7%94%B0%E8%8A%B3%29%2832kbps%29/FC232DC463.mp3"
    },
    {
      "name": "091回 - 刘伶传奇(电台版)",
      "url": "http://www.zgpingshu.com/down/4559/91.html",
      "downloadUrl": "http://dops41.zgpingshu.com/%E5%8D%95%E7%94%B0%E8%8A%B3/%E7%94%B5%E5%8F%B0%E7%89%88%E5%88%98%E4%BC%B6%E4%BC%A0%E5%A5%87%28100%E5%9B%9E%29%28%E6%92%AD%E9%9F%B3-%E5%8D%95%E7%94%B0%E8%8A%B3%29%2832kbps%29/10D2FD1C2D.mp3"
    },
    {
      "name": "092回 - 刘伶传奇(电台版)",
      "url": "http://www.zgpingshu.com/down/4559/92.html",
      "downloadUrl": "http://dops41.zgpingshu.com/%E5%8D%95%E7%94%B0%E8%8A%B3/%E7%94%B5%E5%8F%B0%E7%89%88%E5%88%98%E4%BC%B6%E4%BC%A0%E5%A5%87%28100%E5%9B%9E%29%28%E6%92%AD%E9%9F%B3-%E5%8D%95%E7%94%B0%E8%8A%B3%29%2832kbps%29/822682F6DC.mp3"
    },
    {
      "name": "093回 - 刘伶传奇(电台版)",
      "url": "http://www.zgpingshu.com/down/4559/93.html",
      "downloadUrl": "http://dops41.zgpingshu.com/%E5%8D%95%E7%94%B0%E8%8A%B3/%E7%94%B5%E5%8F%B0%E7%89%88%E5%88%98%E4%BC%B6%E4%BC%A0%E5%A5%87%28100%E5%9B%9E%29%28%E6%92%AD%E9%9F%B3-%E5%8D%95%E7%94%B0%E8%8A%B3%29%2832kbps%29/DFBE915BB4.mp3"
    },
    {
      "name": "094回 - 刘伶传奇(电台版)",
      "url": "http://www.zgpingshu.com/down/4559/94.html",
      "downloadUrl": "http://dops41.zgpingshu.com/%E5%8D%95%E7%94%B0%E8%8A%B3/%E7%94%B5%E5%8F%B0%E7%89%88%E5%88%98%E4%BC%B6%E4%BC%A0%E5%A5%87%28100%E5%9B%9E%29%28%E6%92%AD%E9%9F%B3-%E5%8D%95%E7%94%B0%E8%8A%B3%29%2832kbps%29/208B88E34B.mp3"
    },
    {
      "name": "095回 - 刘伶传奇(电台版)",
      "url": "http://www.zgpingshu.com/down/4559/95.html",
      "downloadUrl": "http://dops41.zgpingshu.com/%E5%8D%95%E7%94%B0%E8%8A%B3/%E7%94%B5%E5%8F%B0%E7%89%88%E5%88%98%E4%BC%B6%E4%BC%A0%E5%A5%87%28100%E5%9B%9E%29%28%E6%92%AD%E9%9F%B3-%E5%8D%95%E7%94%B0%E8%8A%B3%29%2832kbps%29/A43AE4DA74.mp3"
    },
    {
      "name": "096回 - 刘伶传奇(电台版)",
      "url": "http://www.zgpingshu.com/down/4559/96.html",
      "downloadUrl": "http://dops41.zgpingshu.com/%E5%8D%95%E7%94%B0%E8%8A%B3/%E7%94%B5%E5%8F%B0%E7%89%88%E5%88%98%E4%BC%B6%E4%BC%A0%E5%A5%87%28100%E5%9B%9E%29%28%E6%92%AD%E9%9F%B3-%E5%8D%95%E7%94%B0%E8%8A%B3%29%2832kbps%29/8839D55781.mp3"
    },
    {
      "name": "097回 - 刘伶传奇(电台版)",
      "url": "http://www.zgpingshu.com/down/4559/97.html",
      "downloadUrl": "http://dops41.zgpingshu.com/%E5%8D%95%E7%94%B0%E8%8A%B3/%E7%94%B5%E5%8F%B0%E7%89%88%E5%88%98%E4%BC%B6%E4%BC%A0%E5%A5%87%28100%E5%9B%9E%29%28%E6%92%AD%E9%9F%B3-%E5%8D%95%E7%94%B0%E8%8A%B3%29%2832kbps%29/75EC71BBE6.mp3"
    },
    {
      "name": "098回 - 刘伶传奇(电台版)",
      "url": "http://www.zgpingshu.com/down/4559/98.html",
      "downloadUrl": "http://dops41.zgpingshu.com/%E5%8D%95%E7%94%B0%E8%8A%B3/%E7%94%B5%E5%8F%B0%E7%89%88%E5%88%98%E4%BC%B6%E4%BC%A0%E5%A5%87%28100%E5%9B%9E%29%28%E6%92%AD%E9%9F%B3-%E5%8D%95%E7%94%B0%E8%8A%B3%29%2832kbps%29/440C89B881.mp3"
    },
    {
      "name": "099回 - 刘伶传奇(电台版)",
      "url": "http://www.zgpingshu.com/down/4559/99.html",
      "downloadUrl": "http://dops41.zgpingshu.com/%E5%8D%95%E7%94%B0%E8%8A%B3/%E7%94%B5%E5%8F%B0%E7%89%88%E5%88%98%E4%BC%B6%E4%BC%A0%E5%A5%87%28100%E5%9B%9E%29%28%E6%92%AD%E9%9F%B3-%E5%8D%95%E7%94%B0%E8%8A%B3%29%2832kbps%29/46BFB823AD.mp3"
    },
    {
      "name": "100回 - 刘伶传奇(电台版)",
      "url": "http://www.zgpingshu.com/down/4559/100.html",
      "downloadUrl": "http://dops41.zgpingshu.com/%E5%8D%95%E7%94%B0%E8%8A%B3/%E7%94%B5%E5%8F%B0%E7%89%88%E5%88%98%E4%BC%B6%E4%BC%A0%E5%A5%87%28100%E5%9B%9E%29%28%E6%92%AD%E9%9F%B3-%E5%8D%95%E7%94%B0%E8%8A%B3%29%2832kbps%29/D502F53755.mp3"
    }
  ]
}
