{
  "name": "杨么传",
  "url": "http://shantianfang.zgpingshu.com/12/",
  "chapters": [
    {
      "name": "01回 - 杨么传",
      "url": "http://www.zgpingshu.com/down/12/",
      "downloadUrl": "http://doshantianfang1.zgpingshu.com/%E6%9D%A8%E4%B9%88%E4%BC%A0%2850%E5%9B%9E%2932kbps/F671EEC794.mp3"
    },
    {
      "name": "02回 - 杨么传",
      "url": "http://www.zgpingshu.com/down/12/2.html",
      "downloadUrl": "http://doshantianfang1.zgpingshu.com/%E6%9D%A8%E4%B9%88%E4%BC%A0%2850%E5%9B%9E%2932kbps/7B6A6111A9.mp3"
    },
    {
      "name": "03回 - 杨么传",
      "url": "http://www.zgpingshu.com/down/12/3.html",
      "downloadUrl": "http://doshantianfang1.zgpingshu.com/%E6%9D%A8%E4%B9%88%E4%BC%A0%2850%E5%9B%9E%2932kbps/7D91EA736B.mp3"
    },
    {
      "name": "04回 - 杨么传",
      "url": "http://www.zgpingshu.com/down/12/4.html",
      "downloadUrl": "http://doshantianfang1.zgpingshu.com/%E6%9D%A8%E4%B9%88%E4%BC%A0%2850%E5%9B%9E%2932kbps/8F30AE3267.mp3"
    },
    { "name": "05回 - 杨么传", "url": "http://www.zgpingshu.com/down/12/5.html", "downloadUrl": "" },
    {
      "name": "06回 - 杨么传",
      "url": "http://www.zgpingshu.com/down/12/6.html",
      "downloadUrl": "http://doshantianfang1.zgpingshu.com/%E6%9D%A8%E4%B9%88%E4%BC%A0%2850%E5%9B%9E%2932kbps/2494F6199C.mp3"
    },
    {
      "name": "07回 - 杨么传",
      "url": "http://www.zgpingshu.com/down/12/7.html",
      "downloadUrl": "http://doshantianfang1.zgpingshu.com/%E6%9D%A8%E4%B9%88%E4%BC%A0%2850%E5%9B%9E%2932kbps/C86E8DA9EC.mp3"
    },
    {
      "name": "08回 - 杨么传",
      "url": "http://www.zgpingshu.com/down/12/8.html",
      "downloadUrl": "http://doshantianfang1.zgpingshu.com/%E6%9D%A8%E4%B9%88%E4%BC%A0%2850%E5%9B%9E%2932kbps/4B9D9AB4CA.mp3"
    },
    {
      "name": "09回 - 杨么传",
      "url": "http://www.zgpingshu.com/down/12/9.html",
      "downloadUrl": "http://doshantianfang1.zgpingshu.com/%E6%9D%A8%E4%B9%88%E4%BC%A0%2850%E5%9B%9E%2932kbps/E75AC0B836.mp3"
    },
    {
      "name": "10回 - 杨么传",
      "url": "http://www.zgpingshu.com/down/12/10.html",
      "downloadUrl": "http://doshantianfang1.zgpingshu.com/%E6%9D%A8%E4%B9%88%E4%BC%A0%2850%E5%9B%9E%2932kbps/69645A9D6D.mp3"
    },
    {
      "name": "11回 - 杨么传",
      "url": "http://www.zgpingshu.com/down/12/11.html",
      "downloadUrl": "http://doshantianfang1.zgpingshu.com/%E6%9D%A8%E4%B9%88%E4%BC%A0%2850%E5%9B%9E%2932kbps/AE006554F0.mp3"
    },
    {
      "name": "12回 - 杨么传",
      "url": "http://www.zgpingshu.com/down/12/12.html",
      "downloadUrl": "http://doshantianfang1.zgpingshu.com/%E6%9D%A8%E4%B9%88%E4%BC%A0%2850%E5%9B%9E%2932kbps/BCBB999577.mp3"
    },
    {
      "name": "13回 - 杨么传",
      "url": "http://www.zgpingshu.com/down/12/13.html",
      "downloadUrl": "http://doshantianfang1.zgpingshu.com/%E6%9D%A8%E4%B9%88%E4%BC%A0%2850%E5%9B%9E%2932kbps/42E67ED822.mp3"
    },
    {
      "name": "14回 - 杨么传",
      "url": "http://www.zgpingshu.com/down/12/14.html",
      "downloadUrl": "http://doshantianfang1.zgpingshu.com/%E6%9D%A8%E4%B9%88%E4%BC%A0%2850%E5%9B%9E%2932kbps/50EA73589F.mp3"
    },
    { "name": "15回 - 杨么传", "url": "http://www.zgpingshu.com/down/12/15.html", "downloadUrl": "" },
    {
      "name": "16回 - 杨么传",
      "url": "http://www.zgpingshu.com/down/12/16.html",
      "downloadUrl": "http://doshantianfang1.zgpingshu.com/%E6%9D%A8%E4%B9%88%E4%BC%A0%2850%E5%9B%9E%2932kbps/6E3D156221.mp3"
    },
    {
      "name": "17回 - 杨么传",
      "url": "http://www.zgpingshu.com/down/12/17.html",
      "downloadUrl": "http://doshantianfang1.zgpingshu.com/%E6%9D%A8%E4%B9%88%E4%BC%A0%2850%E5%9B%9E%2932kbps/867D90A8FB.mp3"
    },
    {
      "name": "18回 - 杨么传",
      "url": "http://www.zgpingshu.com/down/12/18.html",
      "downloadUrl": "http://doshantianfang1.zgpingshu.com/%E6%9D%A8%E4%B9%88%E4%BC%A0%2850%E5%9B%9E%2932kbps/50735AF2F9.mp3"
    },
    {
      "name": "19回 - 杨么传",
      "url": "http://www.zgpingshu.com/down/12/19.html",
      "downloadUrl": "http://doshantianfang1.zgpingshu.com/%E6%9D%A8%E4%B9%88%E4%BC%A0%2850%E5%9B%9E%2932kbps/D89E34946B.mp3"
    },
    {
      "name": "20回 - 杨么传",
      "url": "http://www.zgpingshu.com/down/12/20.html",
      "downloadUrl": "http://doshantianfang1.zgpingshu.com/%E6%9D%A8%E4%B9%88%E4%BC%A0%2850%E5%9B%9E%2932kbps/9F8813ED09.mp3"
    },
    {
      "name": "21回 - 杨么传",
      "url": "http://www.zgpingshu.com/down/12/21.html",
      "downloadUrl": "http://doshantianfang1.zgpingshu.com/%E6%9D%A8%E4%B9%88%E4%BC%A0%2850%E5%9B%9E%2932kbps/FD27FBF70A.mp3"
    },
    {
      "name": "22回 - 杨么传",
      "url": "http://www.zgpingshu.com/down/12/22.html",
      "downloadUrl": "http://doshantianfang1.zgpingshu.com/%E6%9D%A8%E4%B9%88%E4%BC%A0%2850%E5%9B%9E%2932kbps/2DC36BA2D1.mp3"
    },
    {
      "name": "23回 - 杨么传",
      "url": "http://www.zgpingshu.com/down/12/23.html",
      "downloadUrl": "http://doshantianfang1.zgpingshu.com/%E6%9D%A8%E4%B9%88%E4%BC%A0%2850%E5%9B%9E%2932kbps/BBCF64041D.mp3"
    },
    {
      "name": "24回 - 杨么传",
      "url": "http://www.zgpingshu.com/down/12/24.html",
      "downloadUrl": "http://doshantianfang1.zgpingshu.com/%E6%9D%A8%E4%B9%88%E4%BC%A0%2850%E5%9B%9E%2932kbps/C9C8B8E87E.mp3"
    },
    {
      "name": "25回 - 杨么传",
      "url": "http://www.zgpingshu.com/down/12/25.html",
      "downloadUrl": "http://doshantianfang1.zgpingshu.com/%E6%9D%A8%E4%B9%88%E4%BC%A0%2850%E5%9B%9E%2932kbps/7F1B4A0C73.mp3"
    },
    {
      "name": "26回 - 杨么传",
      "url": "http://www.zgpingshu.com/down/12/26.html",
      "downloadUrl": "http://doshantianfang1.zgpingshu.com/%E6%9D%A8%E4%B9%88%E4%BC%A0%2850%E5%9B%9E%2932kbps/A9DAF25E53.mp3"
    },
    {
      "name": "27回 - 杨么传",
      "url": "http://www.zgpingshu.com/down/12/27.html",
      "downloadUrl": "http://doshantianfang1.zgpingshu.com/%E6%9D%A8%E4%B9%88%E4%BC%A0%2850%E5%9B%9E%2932kbps/094D4A80E0.mp3"
    },
    {
      "name": "28回 - 杨么传",
      "url": "http://www.zgpingshu.com/down/12/28.html",
      "downloadUrl": "http://doshantianfang1.zgpingshu.com/%E6%9D%A8%E4%B9%88%E4%BC%A0%2850%E5%9B%9E%2932kbps/E88B23D48C.mp3"
    },
    {
      "name": "29回 - 杨么传",
      "url": "http://www.zgpingshu.com/down/12/29.html",
      "downloadUrl": "http://doshantianfang1.zgpingshu.com/%E6%9D%A8%E4%B9%88%E4%BC%A0%2850%E5%9B%9E%2932kbps/665FD650F9.mp3"
    },
    {
      "name": "30回 - 杨么传",
      "url": "http://www.zgpingshu.com/down/12/30.html",
      "downloadUrl": "http://doshantianfang1.zgpingshu.com/%E6%9D%A8%E4%B9%88%E4%BC%A0%2850%E5%9B%9E%2932kbps/6DC56A9351.mp3"
    },
    {
      "name": "31回 - 杨么传",
      "url": "http://www.zgpingshu.com/down/12/31.html",
      "downloadUrl": "http://doshantianfang1.zgpingshu.com/%E6%9D%A8%E4%B9%88%E4%BC%A0%2850%E5%9B%9E%2932kbps/F7DC86FF0B.mp3"
    },
    {
      "name": "32回 - 杨么传",
      "url": "http://www.zgpingshu.com/down/12/32.html",
      "downloadUrl": "http://doshantianfang1.zgpingshu.com/%E6%9D%A8%E4%B9%88%E4%BC%A0%2850%E5%9B%9E%2932kbps/B41A3FF20C.mp3"
    },
    {
      "name": "33回 - 杨么传",
      "url": "http://www.zgpingshu.com/down/12/33.html",
      "downloadUrl": "http://doshantianfang1.zgpingshu.com/%E6%9D%A8%E4%B9%88%E4%BC%A0%2850%E5%9B%9E%2932kbps/FCB706B75A.mp3"
    },
    {
      "name": "34回 - 杨么传",
      "url": "http://www.zgpingshu.com/down/12/34.html",
      "downloadUrl": "http://doshantianfang1.zgpingshu.com/%E6%9D%A8%E4%B9%88%E4%BC%A0%2850%E5%9B%9E%2932kbps/347D7FA9F4.mp3"
    },
    {
      "name": "35回 - 杨么传",
      "url": "http://www.zgpingshu.com/down/12/35.html",
      "downloadUrl": "http://doshantianfang1.zgpingshu.com/%E6%9D%A8%E4%B9%88%E4%BC%A0%2850%E5%9B%9E%2932kbps/F9F48430E6.mp3"
    },
    {
      "name": "36回 - 杨么传",
      "url": "http://www.zgpingshu.com/down/12/36.html",
      "downloadUrl": "http://doshantianfang1.zgpingshu.com/%E6%9D%A8%E4%B9%88%E4%BC%A0%2850%E5%9B%9E%2932kbps/A26A323140.mp3"
    },
    {
      "name": "37回 - 杨么传",
      "url": "http://www.zgpingshu.com/down/12/37.html",
      "downloadUrl": "http://doshantianfang1.zgpingshu.com/%E6%9D%A8%E4%B9%88%E4%BC%A0%2850%E5%9B%9E%2932kbps/DFB57ACEBB.mp3"
    },
    {
      "name": "38回 - 杨么传",
      "url": "http://www.zgpingshu.com/down/12/38.html",
      "downloadUrl": "http://doshantianfang1.zgpingshu.com/%E6%9D%A8%E4%B9%88%E4%BC%A0%2850%E5%9B%9E%2932kbps/922A6E10F7.mp3"
    },
    { "name": "39回 - 杨么传", "url": "http://www.zgpingshu.com/down/12/39.html", "downloadUrl": "" },
    {
      "name": "40回 - 杨么传",
      "url": "http://www.zgpingshu.com/down/12/40.html",
      "downloadUrl": "http://doshantianfang1.zgpingshu.com/%E6%9D%A8%E4%B9%88%E4%BC%A0%2850%E5%9B%9E%2932kbps/D004FE8565.mp3"
    },
    {
      "name": "41回 - 杨么传",
      "url": "http://www.zgpingshu.com/down/12/41.html",
      "downloadUrl": "http://doshantianfang1.zgpingshu.com/%E6%9D%A8%E4%B9%88%E4%BC%A0%2850%E5%9B%9E%2932kbps/BB23CD7722.mp3"
    },
    {
      "name": "42回 - 杨么传",
      "url": "http://www.zgpingshu.com/down/12/42.html",
      "downloadUrl": "http://doshantianfang1.zgpingshu.com/%E6%9D%A8%E4%B9%88%E4%BC%A0%2850%E5%9B%9E%2932kbps/02322263EF.mp3"
    },
    {
      "name": "43回 - 杨么传",
      "url": "http://www.zgpingshu.com/down/12/43.html",
      "downloadUrl": "http://doshantianfang1.zgpingshu.com/%E6%9D%A8%E4%B9%88%E4%BC%A0%2850%E5%9B%9E%2932kbps/8DA1D76089.mp3"
    },
    { "name": "44回 - 杨么传", "url": "http://www.zgpingshu.com/down/12/44.html", "downloadUrl": "" },
    {
      "name": "45回 - 杨么传",
      "url": "http://www.zgpingshu.com/down/12/45.html",
      "downloadUrl": "http://doshantianfang1.zgpingshu.com/%E6%9D%A8%E4%B9%88%E4%BC%A0%2850%E5%9B%9E%2932kbps/33F7DD0949.mp3"
    },
    {
      "name": "46回 - 杨么传",
      "url": "http://www.zgpingshu.com/down/12/46.html",
      "downloadUrl": "http://doshantianfang1.zgpingshu.com/%E6%9D%A8%E4%B9%88%E4%BC%A0%2850%E5%9B%9E%2932kbps/9AF495E997.mp3"
    },
    {
      "name": "47回 - 杨么传",
      "url": "http://www.zgpingshu.com/down/12/47.html",
      "downloadUrl": "http://doshantianfang1.zgpingshu.com/%E6%9D%A8%E4%B9%88%E4%BC%A0%2850%E5%9B%9E%2932kbps/95EAD71A25.mp3"
    },
    {
      "name": "48回 - 杨么传",
      "url": "http://www.zgpingshu.com/down/12/48.html",
      "downloadUrl": "http://doshantianfang1.zgpingshu.com/%E6%9D%A8%E4%B9%88%E4%BC%A0%2850%E5%9B%9E%2932kbps/27263D29E9.mp3"
    },
    {
      "name": "49回 - 杨么传",
      "url": "http://www.zgpingshu.com/down/12/49.html",
      "downloadUrl": "http://doshantianfang1.zgpingshu.com/%E6%9D%A8%E4%B9%88%E4%BC%A0%2850%E5%9B%9E%2932kbps/B3BCA3AFC9.mp3"
    },
    {
      "name": "50回 - 杨么传",
      "url": "http://www.zgpingshu.com/down/12/50.html",
      "downloadUrl": "http://doshantianfang1.zgpingshu.com/%E6%9D%A8%E4%B9%88%E4%BC%A0%2850%E5%9B%9E%2932kbps/1DB2D6B542.mp3"
    }
  ]
}
