{
  "name": "尘埃落定",
  "author": "zhongweiwei",
  "url": "http://zhongweiwei.zgpingshu.com/3286/",
  "chapters": [
    {
      "name": "01回 - 尘埃落定",
      "url": "http://www.zgpingshu.com/play/3286/",
      "downloadUrl": "http://ops21.zgpingshu.com/%E4%BB%B2%E7%BB%B4%E7%BB%B4/%5B%E6%BC%94%E6%92%AD%EF%BC%9A%E4%BB%B2%E7%BB%B4%E7%BB%B4%5D%E5%B0%98%E5%9F%83%E8%90%BD%E5%AE%9A%5B46%E5%9B%9E%5D%2832k%29/646684DB49.mp3"
    },
    {
      "name": "02回 - 尘埃落定",
      "url": "http://www.zgpingshu.com/play/3286/2.html",
      "downloadUrl": "http://ops21.zgpingshu.com/%E4%BB%B2%E7%BB%B4%E7%BB%B4/%5B%E6%BC%94%E6%92%AD%EF%BC%9A%E4%BB%B2%E7%BB%B4%E7%BB%B4%5D%E5%B0%98%E5%9F%83%E8%90%BD%E5%AE%9A%5B46%E5%9B%9E%5D%2832k%29/D0D75BB493.mp3"
    },
    {
      "name": "03回 - 尘埃落定",
      "url": "http://www.zgpingshu.com/play/3286/3.html",
      "downloadUrl": "http://ops21.zgpingshu.com/%E4%BB%B2%E7%BB%B4%E7%BB%B4/%5B%E6%BC%94%E6%92%AD%EF%BC%9A%E4%BB%B2%E7%BB%B4%E7%BB%B4%5D%E5%B0%98%E5%9F%83%E8%90%BD%E5%AE%9A%5B46%E5%9B%9E%5D%2832k%29/A915768DE2.mp3"
    },
    {
      "name": "04回 - 尘埃落定",
      "url": "http://www.zgpingshu.com/play/3286/4.html",
      "downloadUrl": "http://ops21.zgpingshu.com/%E4%BB%B2%E7%BB%B4%E7%BB%B4/%5B%E6%BC%94%E6%92%AD%EF%BC%9A%E4%BB%B2%E7%BB%B4%E7%BB%B4%5D%E5%B0%98%E5%9F%83%E8%90%BD%E5%AE%9A%5B46%E5%9B%9E%5D%2832k%29/ABE75B9760.mp3"
    },
    {
      "name": "05回 - 尘埃落定",
      "url": "http://www.zgpingshu.com/play/3286/5.html",
      "downloadUrl": "http://ops21.zgpingshu.com/%E4%BB%B2%E7%BB%B4%E7%BB%B4/%5B%E6%BC%94%E6%92%AD%EF%BC%9A%E4%BB%B2%E7%BB%B4%E7%BB%B4%5D%E5%B0%98%E5%9F%83%E8%90%BD%E5%AE%9A%5B46%E5%9B%9E%5D%2832k%29/9B45A8172D.mp3"
    },
    {
      "name": "06回 - 尘埃落定",
      "url": "http://www.zgpingshu.com/play/3286/6.html",
      "downloadUrl": "http://ops21.zgpingshu.com/%E4%BB%B2%E7%BB%B4%E7%BB%B4/%5B%E6%BC%94%E6%92%AD%EF%BC%9A%E4%BB%B2%E7%BB%B4%E7%BB%B4%5D%E5%B0%98%E5%9F%83%E8%90%BD%E5%AE%9A%5B46%E5%9B%9E%5D%2832k%29/A4C735451A.mp3"
    },
    {
      "name": "07回 - 尘埃落定",
      "url": "http://www.zgpingshu.com/play/3286/7.html",
      "downloadUrl": "http://ops21.zgpingshu.com/%E4%BB%B2%E7%BB%B4%E7%BB%B4/%5B%E6%BC%94%E6%92%AD%EF%BC%9A%E4%BB%B2%E7%BB%B4%E7%BB%B4%5D%E5%B0%98%E5%9F%83%E8%90%BD%E5%AE%9A%5B46%E5%9B%9E%5D%2832k%29/CD2EFE1EE0.mp3"
    },
    {
      "name": "08回 - 尘埃落定",
      "url": "http://www.zgpingshu.com/play/3286/8.html",
      "downloadUrl": "http://ops21.zgpingshu.com/%E4%BB%B2%E7%BB%B4%E7%BB%B4/%5B%E6%BC%94%E6%92%AD%EF%BC%9A%E4%BB%B2%E7%BB%B4%E7%BB%B4%5D%E5%B0%98%E5%9F%83%E8%90%BD%E5%AE%9A%5B46%E5%9B%9E%5D%2832k%29/B445F84C0D.mp3"
    },
    {
      "name": "09回 - 尘埃落定",
      "url": "http://www.zgpingshu.com/play/3286/9.html",
      "downloadUrl": "http://ops21.zgpingshu.com/%E4%BB%B2%E7%BB%B4%E7%BB%B4/%5B%E6%BC%94%E6%92%AD%EF%BC%9A%E4%BB%B2%E7%BB%B4%E7%BB%B4%5D%E5%B0%98%E5%9F%83%E8%90%BD%E5%AE%9A%5B46%E5%9B%9E%5D%2832k%29/AED353AEB1.mp3"
    },
    {
      "name": "10回 - 尘埃落定",
      "url": "http://www.zgpingshu.com/play/3286/10.html",
      "downloadUrl": "http://ops21.zgpingshu.com/%E4%BB%B2%E7%BB%B4%E7%BB%B4/%5B%E6%BC%94%E6%92%AD%EF%BC%9A%E4%BB%B2%E7%BB%B4%E7%BB%B4%5D%E5%B0%98%E5%9F%83%E8%90%BD%E5%AE%9A%5B46%E5%9B%9E%5D%2832k%29/FD4C4BF46C.mp3"
    },
    {
      "name": "11回 - 尘埃落定",
      "url": "http://www.zgpingshu.com/play/3286/11.html",
      "downloadUrl": "http://ops21.zgpingshu.com/%E4%BB%B2%E7%BB%B4%E7%BB%B4/%5B%E6%BC%94%E6%92%AD%EF%BC%9A%E4%BB%B2%E7%BB%B4%E7%BB%B4%5D%E5%B0%98%E5%9F%83%E8%90%BD%E5%AE%9A%5B46%E5%9B%9E%5D%2832k%29/116CDA0222.mp3"
    },
    {
      "name": "12回 - 尘埃落定",
      "url": "http://www.zgpingshu.com/play/3286/12.html",
      "downloadUrl": "http://ops21.zgpingshu.com/%E4%BB%B2%E7%BB%B4%E7%BB%B4/%5B%E6%BC%94%E6%92%AD%EF%BC%9A%E4%BB%B2%E7%BB%B4%E7%BB%B4%5D%E5%B0%98%E5%9F%83%E8%90%BD%E5%AE%9A%5B46%E5%9B%9E%5D%2832k%29/0406012EDC.mp3"
    },
    {
      "name": "13回 - 尘埃落定",
      "url": "http://www.zgpingshu.com/play/3286/13.html",
      "downloadUrl": "http://ops21.zgpingshu.com/%E4%BB%B2%E7%BB%B4%E7%BB%B4/%5B%E6%BC%94%E6%92%AD%EF%BC%9A%E4%BB%B2%E7%BB%B4%E7%BB%B4%5D%E5%B0%98%E5%9F%83%E8%90%BD%E5%AE%9A%5B46%E5%9B%9E%5D%2832k%29/9EEDCB57DA.mp3"
    },
    {
      "name": "14回 - 尘埃落定",
      "url": "http://www.zgpingshu.com/play/3286/14.html",
      "downloadUrl": "http://ops21.zgpingshu.com/%E4%BB%B2%E7%BB%B4%E7%BB%B4/%5B%E6%BC%94%E6%92%AD%EF%BC%9A%E4%BB%B2%E7%BB%B4%E7%BB%B4%5D%E5%B0%98%E5%9F%83%E8%90%BD%E5%AE%9A%5B46%E5%9B%9E%5D%2832k%29/A2FAED1D2E.mp3"
    },
    {
      "name": "15回 - 尘埃落定",
      "url": "http://www.zgpingshu.com/play/3286/15.html",
      "downloadUrl": "http://ops21.zgpingshu.com/%E4%BB%B2%E7%BB%B4%E7%BB%B4/%5B%E6%BC%94%E6%92%AD%EF%BC%9A%E4%BB%B2%E7%BB%B4%E7%BB%B4%5D%E5%B0%98%E5%9F%83%E8%90%BD%E5%AE%9A%5B46%E5%9B%9E%5D%2832k%29/65095EAEC2.mp3"
    },
    {
      "name": "16回 - 尘埃落定",
      "url": "http://www.zgpingshu.com/play/3286/16.html",
      "downloadUrl": "http://ops21.zgpingshu.com/%E4%BB%B2%E7%BB%B4%E7%BB%B4/%5B%E6%BC%94%E6%92%AD%EF%BC%9A%E4%BB%B2%E7%BB%B4%E7%BB%B4%5D%E5%B0%98%E5%9F%83%E8%90%BD%E5%AE%9A%5B46%E5%9B%9E%5D%2832k%29/983D02FB54.mp3"
    },
    {
      "name": "17回 - 尘埃落定",
      "url": "http://www.zgpingshu.com/play/3286/17.html",
      "downloadUrl": "http://ops21.zgpingshu.com/%E4%BB%B2%E7%BB%B4%E7%BB%B4/%5B%E6%BC%94%E6%92%AD%EF%BC%9A%E4%BB%B2%E7%BB%B4%E7%BB%B4%5D%E5%B0%98%E5%9F%83%E8%90%BD%E5%AE%9A%5B46%E5%9B%9E%5D%2832k%29/173C479032.mp3"
    },
    {
      "name": "18回 - 尘埃落定",
      "url": "http://www.zgpingshu.com/play/3286/18.html",
      "downloadUrl": "http://ops21.zgpingshu.com/%E4%BB%B2%E7%BB%B4%E7%BB%B4/%5B%E6%BC%94%E6%92%AD%EF%BC%9A%E4%BB%B2%E7%BB%B4%E7%BB%B4%5D%E5%B0%98%E5%9F%83%E8%90%BD%E5%AE%9A%5B46%E5%9B%9E%5D%2832k%29/816FF62F7B.mp3"
    },
    {
      "name": "19回 - 尘埃落定",
      "url": "http://www.zgpingshu.com/play/3286/19.html",
      "downloadUrl": "http://ops21.zgpingshu.com/%E4%BB%B2%E7%BB%B4%E7%BB%B4/%5B%E6%BC%94%E6%92%AD%EF%BC%9A%E4%BB%B2%E7%BB%B4%E7%BB%B4%5D%E5%B0%98%E5%9F%83%E8%90%BD%E5%AE%9A%5B46%E5%9B%9E%5D%2832k%29/0075A16391.mp3"
    },
    {
      "name": "20回 - 尘埃落定",
      "url": "http://www.zgpingshu.com/play/3286/20.html",
      "downloadUrl": "http://ops21.zgpingshu.com/%E4%BB%B2%E7%BB%B4%E7%BB%B4/%5B%E6%BC%94%E6%92%AD%EF%BC%9A%E4%BB%B2%E7%BB%B4%E7%BB%B4%5D%E5%B0%98%E5%9F%83%E8%90%BD%E5%AE%9A%5B46%E5%9B%9E%5D%2832k%29/C5C07C3904.mp3"
    },
    {
      "name": "21回 - 尘埃落定",
      "url": "http://www.zgpingshu.com/play/3286/21.html",
      "downloadUrl": "http://ops21.zgpingshu.com/%E4%BB%B2%E7%BB%B4%E7%BB%B4/%5B%E6%BC%94%E6%92%AD%EF%BC%9A%E4%BB%B2%E7%BB%B4%E7%BB%B4%5D%E5%B0%98%E5%9F%83%E8%90%BD%E5%AE%9A%5B46%E5%9B%9E%5D%2832k%29/2917EDD468.mp3"
    },
    {
      "name": "22回 - 尘埃落定",
      "url": "http://www.zgpingshu.com/play/3286/22.html",
      "downloadUrl": "http://ops21.zgpingshu.com/%E4%BB%B2%E7%BB%B4%E7%BB%B4/%5B%E6%BC%94%E6%92%AD%EF%BC%9A%E4%BB%B2%E7%BB%B4%E7%BB%B4%5D%E5%B0%98%E5%9F%83%E8%90%BD%E5%AE%9A%5B46%E5%9B%9E%5D%2832k%29/E5D7A03B55.mp3"
    },
    {
      "name": "23回 - 尘埃落定",
      "url": "http://www.zgpingshu.com/play/3286/23.html",
      "downloadUrl": "http://ops21.zgpingshu.com/%E4%BB%B2%E7%BB%B4%E7%BB%B4/%5B%E6%BC%94%E6%92%AD%EF%BC%9A%E4%BB%B2%E7%BB%B4%E7%BB%B4%5D%E5%B0%98%E5%9F%83%E8%90%BD%E5%AE%9A%5B46%E5%9B%9E%5D%2832k%29/9527D30145.mp3"
    },
    {
      "name": "24回 - 尘埃落定",
      "url": "http://www.zgpingshu.com/play/3286/24.html",
      "downloadUrl": "http://ops21.zgpingshu.com/%E4%BB%B2%E7%BB%B4%E7%BB%B4/%5B%E6%BC%94%E6%92%AD%EF%BC%9A%E4%BB%B2%E7%BB%B4%E7%BB%B4%5D%E5%B0%98%E5%9F%83%E8%90%BD%E5%AE%9A%5B46%E5%9B%9E%5D%2832k%29/F41F16CEB9.mp3"
    },
    {
      "name": "25回 - 尘埃落定",
      "url": "http://www.zgpingshu.com/play/3286/25.html",
      "downloadUrl": "http://ops21.zgpingshu.com/%E4%BB%B2%E7%BB%B4%E7%BB%B4/%5B%E6%BC%94%E6%92%AD%EF%BC%9A%E4%BB%B2%E7%BB%B4%E7%BB%B4%5D%E5%B0%98%E5%9F%83%E8%90%BD%E5%AE%9A%5B46%E5%9B%9E%5D%2832k%29/69F8F18CC8.mp3"
    },
    {
      "name": "26回 - 尘埃落定",
      "url": "http://www.zgpingshu.com/play/3286/26.html",
      "downloadUrl": "http://ops21.zgpingshu.com/%E4%BB%B2%E7%BB%B4%E7%BB%B4/%5B%E6%BC%94%E6%92%AD%EF%BC%9A%E4%BB%B2%E7%BB%B4%E7%BB%B4%5D%E5%B0%98%E5%9F%83%E8%90%BD%E5%AE%9A%5B46%E5%9B%9E%5D%2832k%29/D0F1F3E8D5.mp3"
    },
    {
      "name": "27回 - 尘埃落定",
      "url": "http://www.zgpingshu.com/play/3286/27.html",
      "downloadUrl": "http://ops21.zgpingshu.com/%E4%BB%B2%E7%BB%B4%E7%BB%B4/%5B%E6%BC%94%E6%92%AD%EF%BC%9A%E4%BB%B2%E7%BB%B4%E7%BB%B4%5D%E5%B0%98%E5%9F%83%E8%90%BD%E5%AE%9A%5B46%E5%9B%9E%5D%2832k%29/F85320480F.mp3"
    },
    {
      "name": "28回 - 尘埃落定",
      "url": "http://www.zgpingshu.com/play/3286/28.html",
      "downloadUrl": "http://ops21.zgpingshu.com/%E4%BB%B2%E7%BB%B4%E7%BB%B4/%5B%E6%BC%94%E6%92%AD%EF%BC%9A%E4%BB%B2%E7%BB%B4%E7%BB%B4%5D%E5%B0%98%E5%9F%83%E8%90%BD%E5%AE%9A%5B46%E5%9B%9E%5D%2832k%29/E151B6E36B.mp3"
    },
    {
      "name": "29回 - 尘埃落定",
      "url": "http://www.zgpingshu.com/play/3286/29.html",
      "downloadUrl": "http://ops21.zgpingshu.com/%E4%BB%B2%E7%BB%B4%E7%BB%B4/%5B%E6%BC%94%E6%92%AD%EF%BC%9A%E4%BB%B2%E7%BB%B4%E7%BB%B4%5D%E5%B0%98%E5%9F%83%E8%90%BD%E5%AE%9A%5B46%E5%9B%9E%5D%2832k%29/E6E1E8DC35.mp3"
    },
    {
      "name": "30回 - 尘埃落定",
      "url": "http://www.zgpingshu.com/play/3286/30.html",
      "downloadUrl": "http://ops21.zgpingshu.com/%E4%BB%B2%E7%BB%B4%E7%BB%B4/%5B%E6%BC%94%E6%92%AD%EF%BC%9A%E4%BB%B2%E7%BB%B4%E7%BB%B4%5D%E5%B0%98%E5%9F%83%E8%90%BD%E5%AE%9A%5B46%E5%9B%9E%5D%2832k%29/AA50E550A5.mp3"
    },
    {
      "name": "31回 - 尘埃落定",
      "url": "http://www.zgpingshu.com/play/3286/31.html",
      "downloadUrl": "http://ops21.zgpingshu.com/%E4%BB%B2%E7%BB%B4%E7%BB%B4/%5B%E6%BC%94%E6%92%AD%EF%BC%9A%E4%BB%B2%E7%BB%B4%E7%BB%B4%5D%E5%B0%98%E5%9F%83%E8%90%BD%E5%AE%9A%5B46%E5%9B%9E%5D%2832k%29/000923ED0B.mp3"
    },
    {
      "name": "32回 - 尘埃落定",
      "url": "http://www.zgpingshu.com/play/3286/32.html",
      "downloadUrl": "http://ops21.zgpingshu.com/%E4%BB%B2%E7%BB%B4%E7%BB%B4/%5B%E6%BC%94%E6%92%AD%EF%BC%9A%E4%BB%B2%E7%BB%B4%E7%BB%B4%5D%E5%B0%98%E5%9F%83%E8%90%BD%E5%AE%9A%5B46%E5%9B%9E%5D%2832k%29/CCAC7517F6.mp3"
    },
    {
      "name": "33回 - 尘埃落定",
      "url": "http://www.zgpingshu.com/play/3286/33.html",
      "downloadUrl": "http://ops21.zgpingshu.com/%E4%BB%B2%E7%BB%B4%E7%BB%B4/%5B%E6%BC%94%E6%92%AD%EF%BC%9A%E4%BB%B2%E7%BB%B4%E7%BB%B4%5D%E5%B0%98%E5%9F%83%E8%90%BD%E5%AE%9A%5B46%E5%9B%9E%5D%2832k%29/66DE7ED72F.mp3"
    },
    {
      "name": "34回 - 尘埃落定",
      "url": "http://www.zgpingshu.com/play/3286/34.html",
      "downloadUrl": "http://ops21.zgpingshu.com/%E4%BB%B2%E7%BB%B4%E7%BB%B4/%5B%E6%BC%94%E6%92%AD%EF%BC%9A%E4%BB%B2%E7%BB%B4%E7%BB%B4%5D%E5%B0%98%E5%9F%83%E8%90%BD%E5%AE%9A%5B46%E5%9B%9E%5D%2832k%29/D54C0B63E8.mp3"
    },
    {
      "name": "35回 - 尘埃落定",
      "url": "http://www.zgpingshu.com/play/3286/35.html",
      "downloadUrl": "http://ops21.zgpingshu.com/%E4%BB%B2%E7%BB%B4%E7%BB%B4/%5B%E6%BC%94%E6%92%AD%EF%BC%9A%E4%BB%B2%E7%BB%B4%E7%BB%B4%5D%E5%B0%98%E5%9F%83%E8%90%BD%E5%AE%9A%5B46%E5%9B%9E%5D%2832k%29/B4100C6B9B.mp3"
    },
    {
      "name": "36回 - 尘埃落定",
      "url": "http://www.zgpingshu.com/play/3286/36.html",
      "downloadUrl": "http://ops21.zgpingshu.com/%E4%BB%B2%E7%BB%B4%E7%BB%B4/%5B%E6%BC%94%E6%92%AD%EF%BC%9A%E4%BB%B2%E7%BB%B4%E7%BB%B4%5D%E5%B0%98%E5%9F%83%E8%90%BD%E5%AE%9A%5B46%E5%9B%9E%5D%2832k%29/00379C43F4.mp3"
    },
    {
      "name": "37回 - 尘埃落定",
      "url": "http://www.zgpingshu.com/play/3286/37.html",
      "downloadUrl": "http://ops21.zgpingshu.com/%E4%BB%B2%E7%BB%B4%E7%BB%B4/%5B%E6%BC%94%E6%92%AD%EF%BC%9A%E4%BB%B2%E7%BB%B4%E7%BB%B4%5D%E5%B0%98%E5%9F%83%E8%90%BD%E5%AE%9A%5B46%E5%9B%9E%5D%2832k%29/32F68D7ACF.mp3"
    },
    {
      "name": "38回 - 尘埃落定",
      "url": "http://www.zgpingshu.com/play/3286/38.html",
      "downloadUrl": "http://ops21.zgpingshu.com/%E4%BB%B2%E7%BB%B4%E7%BB%B4/%5B%E6%BC%94%E6%92%AD%EF%BC%9A%E4%BB%B2%E7%BB%B4%E7%BB%B4%5D%E5%B0%98%E5%9F%83%E8%90%BD%E5%AE%9A%5B46%E5%9B%9E%5D%2832k%29/01F21DF65A.mp3"
    },
    {
      "name": "39回 - 尘埃落定",
      "url": "http://www.zgpingshu.com/play/3286/39.html",
      "downloadUrl": "http://ops21.zgpingshu.com/%E4%BB%B2%E7%BB%B4%E7%BB%B4/%5B%E6%BC%94%E6%92%AD%EF%BC%9A%E4%BB%B2%E7%BB%B4%E7%BB%B4%5D%E5%B0%98%E5%9F%83%E8%90%BD%E5%AE%9A%5B46%E5%9B%9E%5D%2832k%29/28935DEF7A.mp3"
    },
    {
      "name": "40回 - 尘埃落定",
      "url": "http://www.zgpingshu.com/play/3286/40.html",
      "downloadUrl": "http://ops21.zgpingshu.com/%E4%BB%B2%E7%BB%B4%E7%BB%B4/%5B%E6%BC%94%E6%92%AD%EF%BC%9A%E4%BB%B2%E7%BB%B4%E7%BB%B4%5D%E5%B0%98%E5%9F%83%E8%90%BD%E5%AE%9A%5B46%E5%9B%9E%5D%2832k%29/0994103F31.mp3"
    },
    {
      "name": "41回 - 尘埃落定",
      "url": "http://www.zgpingshu.com/play/3286/41.html",
      "downloadUrl": "http://ops21.zgpingshu.com/%E4%BB%B2%E7%BB%B4%E7%BB%B4/%5B%E6%BC%94%E6%92%AD%EF%BC%9A%E4%BB%B2%E7%BB%B4%E7%BB%B4%5D%E5%B0%98%E5%9F%83%E8%90%BD%E5%AE%9A%5B46%E5%9B%9E%5D%2832k%29/E309A6BD72.mp3"
    },
    {
      "name": "42回 - 尘埃落定",
      "url": "http://www.zgpingshu.com/play/3286/42.html",
      "downloadUrl": "http://ops21.zgpingshu.com/%E4%BB%B2%E7%BB%B4%E7%BB%B4/%5B%E6%BC%94%E6%92%AD%EF%BC%9A%E4%BB%B2%E7%BB%B4%E7%BB%B4%5D%E5%B0%98%E5%9F%83%E8%90%BD%E5%AE%9A%5B46%E5%9B%9E%5D%2832k%29/F73C5CB21A.mp3"
    },
    {
      "name": "43回 - 尘埃落定",
      "url": "http://www.zgpingshu.com/play/3286/43.html",
      "downloadUrl": "http://ops21.zgpingshu.com/%E4%BB%B2%E7%BB%B4%E7%BB%B4/%5B%E6%BC%94%E6%92%AD%EF%BC%9A%E4%BB%B2%E7%BB%B4%E7%BB%B4%5D%E5%B0%98%E5%9F%83%E8%90%BD%E5%AE%9A%5B46%E5%9B%9E%5D%2832k%29/7DB0AEDB64.mp3"
    },
    {
      "name": "44回 - 尘埃落定",
      "url": "http://www.zgpingshu.com/play/3286/44.html",
      "downloadUrl": "http://ops21.zgpingshu.com/%E4%BB%B2%E7%BB%B4%E7%BB%B4/%5B%E6%BC%94%E6%92%AD%EF%BC%9A%E4%BB%B2%E7%BB%B4%E7%BB%B4%5D%E5%B0%98%E5%9F%83%E8%90%BD%E5%AE%9A%5B46%E5%9B%9E%5D%2832k%29/EAF5D938B8.mp3"
    },
    {
      "name": "45回 - 尘埃落定",
      "url": "http://www.zgpingshu.com/play/3286/45.html",
      "downloadUrl": "http://ops21.zgpingshu.com/%E4%BB%B2%E7%BB%B4%E7%BB%B4/%5B%E6%BC%94%E6%92%AD%EF%BC%9A%E4%BB%B2%E7%BB%B4%E7%BB%B4%5D%E5%B0%98%E5%9F%83%E8%90%BD%E5%AE%9A%5B46%E5%9B%9E%5D%2832k%29/69FAE419FC.mp3"
    },
    {
      "name": "46回 - 尘埃落定",
      "url": "http://www.zgpingshu.com/play/3286/46.html",
      "downloadUrl": "http://ops21.zgpingshu.com/%E4%BB%B2%E7%BB%B4%E7%BB%B4/%5B%E6%BC%94%E6%92%AD%EF%BC%9A%E4%BB%B2%E7%BB%B4%E7%BB%B4%5D%E5%B0%98%E5%9F%83%E8%90%BD%E5%AE%9A%5B46%E5%9B%9E%5D%2832k%29/8C86B9A584.mp3"
    }
  ]
}
